Workbook

Sheet total
A1: 45413 | D1: 45445 | G1: 45474 | J1: 45505 | M1: 45566 | P1: 45597 | S1: 45627 | V1: 45658 | Y1: 45689 | AB1: 45717 | AE1: 45748 | AH1: 45779 | AK1: 45809 | AN1: 45839 | AQ1: 45870 | AT1: 45931 | AW1: 45962 | AZ1: 45992 | BC1: 46034 | BF1: 46080 | BI1: ???
A2: Bond | B2: 951450 | D2: Bond | E2: 951450 | G2: pf | H2: 808008 | J2: pf | K2: 808008 | M2: pf | N2: 796070 | P2: pf | Q2: 796070 | S2: pf | T2: 833372 | V2: pf | W2: 833372 | Y2: pf | Z2: 833372 | AB2: pf | AC2: 833372 | AE2: pf | AF2: 865324 | AH2: pf | AI2: 865324 | AK2: pf | AL2: 865324 | AN2: pf | AO2: 865324 | AQ2: pf | AR2: 865324 | AT2: pf | AU2: 865324 | AW2: pf | AX2: 865324 | AZ2: pf | BA2: 865324 | BC2: pf | BD2: =651717+358128 -> 1009845 | BF2: pf | BG2: =651717+358128 -> 1009845 | BI2: aniketstocks | BJ2: =441521 -> 441521
A3: pf | B3: 668528 | D3: pf | E3: 668528 | G3: tata mmf | H3: 1000345.7 | J3: tata mmf | K3: 1007126.1 | M3: tata mmf | N3: 1019698.2 | P3: tata mmf | Q3: 1026151 | S3: tata mmf | T3: 1032099.8 | V3: tata mmf | W3: 1038473.1 | Y3: tata mmf | Z3: 1045060.9 | AB3: tata mmf | AC3: 1050943.1 | AE3: tata mmf | AF3: 1060365.4 | AH3: tata mmf | AI3: 1069730.5 | AK3: tata mmf | AL3: 1076904 | AN3: tata mmf | AO3: 1084164.5 | AQ3: tata mmf | AR3: 1090508.8 | AT3: tata mmf | AU3: 1101242.3 | AW3: tata mmf | AX3: 1106977.3 | AZ3: tata mmf | BA3: 1112472.9 | BC3: tata mmf | BD3: 1118888.2 | BF3: tata mmf | BG3: 1128386 | BI3: amrutastocks | BJ3: =1415595.78 -> 1415595.8
A4: axis overnight | B4: 1419634.1 | D4: axis overnight | E4: 1427820.6 | G4: axis overnight | H4: 1435262.6 | J4: axis overnight | K4: 1443090.3 | M4: axis overnight | N4: 0 | P4: axis overnight | Q4: 0 | S4: axis overnight | T4: 0 | V4: axis overnight | W4: 0 | Y4: axis overnight | Z4: 0 | AB4: axis overnight | AC4: 0 | AE4: amruta tata mmf | AF4: 0 | AH4: amruta tata mmf | AI4: 1006035.5 | AK4: amruta tata mmf | AL4: 1012782 | AN4: - | AO4: 0 | AQ4: - | AR4: 0 | AT4: - | AU4: 0 | AW4: - | AX4: 0 | AZ4: - | BA4: 0 | BC4: - | BD4: 0 | BF4: - | BG4: 0 | BI4: MO midcap | BJ4: 869738
A5: nippon overnight | B5: 905550.14 | D5: nippon overnight | E5: 910768.4 | G5: nippon overnight | H5: 915518 | J5: nippon overnight | K5: 920507.89 | M5: nippon overnight | N5: 0 | P5: nippon overnight | Q5: 0 | S5: nippon overnight | T5: 0 | V5: nippon overnight | W5: 0 | Y5: nippon overnight | Z5: 0 | AB5: nippon overnight | AC5: 0 | AE5: amruta absl corp | AF5: 0 | AH5: amruta absl corp | AI5: 504576.06 | AK5: amruta absl corp | AL5: 509925 | AN5: amruta all debt funds | AO5: =2528607.77+760000 -> 3288607.8 | AQ5: amruta all debt funds | AR5: =512239.74+1006366.14+764716.63+1025576.59 -> 3308899.1 | AT5: amruta all debt funds | AU5: =3327559.24 -> 3327559.2 | AW5: amruta all debt funds | AX5: =3350253 -> 3350253 | AZ5: amruta all debt funds | BA5: 3366751 | BC5: amruta all debt funds | BD5: 3375222 | BF5: amruta all debt funds | BG5: 0 | BI5: hdfc midcap | BJ5: 898979
A6: uti liquid | B6: 3489132.5 | D6: uti liquid | E6: 3510938.9 | G6: uti liquid | H6: 3530497.6 | J6: uti liquid | K6: 3552097.4 | M6: uti liquid | N6: 3593855.3 | P6: uti liquid | Q6: 3616708 | S6: uti liquid | T6: 3635204.7 | V6: uti liquid | W6: 3657159.7 | Y6: uti liquid | Z6: 3678943.7 | AB6: uti liquid | AC6: 3699012.8 | AE6: uti liquid | AF6: 3725155.6 | AH6: uti liquid | AI6: 3747212.5 | AK6: uti liquid | AL6: 3766172 | AN6: uti liquid | AO6: 3786903.5 | AQ6: uti liquid | AR6: 3805488.2 | AT6: uti liquid | AU6: 3842143.8 | AW6: uti liquid | AX6: 3860813.8 | AZ6: uti liquid | BA6: 3879432.8 | BC6: uti liquid | BD6: 3902964.6 | BF6: uti liquid | BG6: 3935452 | BI6: hdfc index | BJ6: 3914849
A7: sbi liquid | B7: 5119373.7 | D7: sbi liquid | E7: 5151139.7 | G7: sbi liquid | H7: 5179527 | J7: sbi liquid | K7: 5211161.5 | M7: sbi liquid | N7: 5271991.9 | P7: sbi liquid | Q7: 4304060 | S7: sbi liquid | T7: 4325818.9 | V7: sbi liquid | W7: 4351589.1 | Y7: sbi liquid | Z7: 4377218.1 | AB7: sbi liquid | AC7: 4401073.6 | AE7: sbi liquid | AF7: 4431262.7 | AH7: sbi liquid | AI7: 4457128.4 | AK7: sbi liquid | AL7: 4480023 | AN7: sbi liquid | AO7: 4504517.1 | AQ7: sbi liquid | AR7: 4526261.5 | AT7: sbi liquid | AU7: 4568910.5 | AW7: sbi liquid | AX7: 4590800 | AZ7: sbi liquid | BA7: 4612900.3 | BC7: sbi liquid | BD7: 4640403.4 | BF7: sbi liquid | BG7: 4678503 | BI7: icici index | BJ7: 3887785
A8: sbi savings | B8: 2503512.2 | D8: sbi savings | E8: 2519163.8 | G8: sbi savings | H8: 2534384.8 | J8: sbi savings | K8: 2551082.3 | M8: sbi savings | N8: 2582502.4 | P8: sbi savings | Q8: 2598548 | S8: sbi savings | T8: 2613122.7 | V8: sbi savings | W8: 2629100.4 | Y8: sbi savings | Z8: 2644432 | AB8: sbi savings | AC8: 2659653 | AE8: sbi savings | AF8: 2682650.5 | AH8: sbi savings | AI8: 2706097.1 | AK8: sbi savings | AL8: 2724664 | AN8: sbi savings | AO8: 2742217.6 | AQ8: sbi savings | AR8: 2758029.2 | AT8: sbi savings | AU8: 2784385.9 | AW8: sbi savings | AX8: 2798567.1 | AZ8: sbi savings | BA8: 2813179 | BC8: sbi savings | BD8: 2829027.4 | BF8: sbi savings | BG8: 2851292 | BI8: Zerodha Cash (Aniket+Amruta) | BJ8: 152000
A9: Total funds | B9: =SUM(B2:B8) -> 15057181 | D9: Total funds | E9: =SUM(E2:E8) -> 15139809 | G9: Total funds | H9: =SUM(H2:H8) -> 15403544 | J9: Total funds | K9: =SUM(K2:K8) -> 15493073 | M9: Total funds | N9: =SUM(N2:N8) -> 13264118 | P9: Total funds | Q9: =SUM(Q2:Q8) -> 12341537 | S9: Total funds | T9: =SUM(T2:T8) -> 12439618 | V9: Total funds | W9: =SUM(W2:W8) -> 12509694 | Y9: Total funds | Z9: =SUM(Z2:Z8) -> 12579027 | AB9: Total funds | AC9: =SUM(AC2:AC8) -> 12644054 | AE9: Total funds | AF9: =SUM(AF2:AF8) -> 12764758 | AH9: Total funds | AI9: =SUM(AI2:AI8) -> 14356104 | AK9: Total funds | AL9: =SUM(AL2:AL8) -> 14435794 | AM9: =AL9-AI9 -> 79689.85 | AN9: Total funds | AO9: =SUM(AO2:AO8) -> 16271734 | AP9: =AO9-AL9 -> 1835940.5 | AQ9: Total funds | AR9: =SUM(AR2:AR8) -> 16354511 | AS9: =AR9-AO9 -> 82776.28 | AT9: Total funds | AU9: =SUM(AU2:AU8) -> 16489566 | AV9: =AU9-AR9 -> 135055.07 | AW9: Total funds | AX9: =SUM(AX2:AX8) -> 16572735 | AY9: =AX9-AU9 -> 83169.36 | AZ9: Total funds | BA9: =SUM(BA2:BA8) -> 16650060 | BB9: =BA9-AX9 -> 77324.85 | BC9: Total funds | BD9: =SUM(BD2:BD8) -> 16876351 | BE9: =BD9-BA9 -> 226290.65 | BF9: Total funds | BG9: =SUM(BG2:BG8) -> 13603478 | BI9: Sbi | BJ9: 221432
BI10: Hdfc | BJ10: =193313 -> 193313
A11: Equity | B11: =B12+B13+B14 -> 7897295.6 | D11: Equity | E11: =E12+E13+E14 -> 7902790.5 | G11: Equity | H11: =H12+H13+H14 -> 8434569.9 | J11: Equity | K11: =K12+K13+K14 -> 8765467.6 | M11: Equity | N11: =N12+N13+N14 -> 9540736.5 | P11: Equity | Q11: =Q12+Q13+Q14 -> 9551827.4 | S11: Equity | T11: =T12+T13+T14 -> 9729093.5 | V11: Equity Total | W11: =W12+W13+W14 -> 9512605 | Y11: Equity Total | Z11: =Z12+Z13+Z14 -> 9455702.2 | AB11: Equity Total | AC11: =AC12+AC13+AC14 -> 8902654.4 | AE11: Equity Total | AF11: =AF12+AF13+AF14 -> 10361984 | AH11: Equity Total | AI11: =AI12+AI13+AI14 -> 10758562 | AK11: Equity Total | AL11: =AL12+AL13+AL14 -> 11024068 | AN11: Equity Total | AO11: =AO12+AO13+AO14 -> 11374078 | AQ11: Equity Total | AR11: =AR12+AR13+AR14 -> 11058343 | AT11: Equity Total | AU11: =AU12+AU15+AU16+AU13+AU14 -> 11349935 | AW11: Equity Total | AX11: =AX12+AX15+AX16+AX13+AX14 -> 11800330 | AZ11: Equity Total | BA11: =BA12+BA15+BA16+BA13+BA14 -> 11915366 | BC11: Equity Total | BD11: =BD12+BD15+BD16+BD13+BD14 -> 11854533 | BF11: Equity Total | BG11: =BG12+BG15+BG16+BG13+BG14 -> 11428468 | BI11: Amruta HDFC | BJ11: 103000
A12: niftybees | B12: 1133271.9 | D12: niftybees | E12: 1138211.8 | G12: niftybees | H12: 1215890.3 | J12: niftybees | K12: 1261391.6 | M12: niftybees+bajaj | N12: =1306484.96+32731.3+425646 -> 1764862.3 | P12: niftybees+bajaj | Q12: 1647170.3 | S12: niftybees+bajajhfl | T12: 1846333.6 | V12: niftybees+bajajhfl | W12: =1204333.68+585861.5 -> 1790195.2 | Y12: niftybees+stocks | Z12: =1188335.72+530416.76+51072 -> 1769824.5 | AB12: niftybees+stocks | AC12: =1126609.88+498727.5+37060 -> 1662397.4 | AE12: niftybees+stocks | AF12: =1183939+560409+38772+1000000 -> 2783120 | AH12: niftybees+bajajhfl+anantraj+amrutastocks | AI12: =1828679.9+969341 -> 2798020.9 | AK12: niftybees+bajajhfl+anantraj+amrutastocks+amrutazerodhacash | AL12: =1864148+1019266+7834 -> 2891248 | AN12: niftybees+bajajhfl+anantraj+amrutastocks+amrutazerodhacash | AO12: =1902627.96+1082498.45+5777 -> 2990903.4 | AQ12: niftybees+bajajhfl+anantraj+amrutastocks+amrutazerodhacash | AR12: =1013107.65+1820130.84+75000 -> 2908238.5 | AT12: aniketstocks+amrutastocks+amrutazerodhacash | AU12: =567109.42+1473252.4 -> 2040361.8 | AW12: aniketstocks+amrutastocks+amrutazerodhacash | AX12: =557158.5+1497436.09 -> 2054594.6 | AZ12: aniketstocks+amrutastocks+amrutazerodhacash | BA12: =525053+1482138 -> 2007191 | BC12: aniketstocks+amrutastocks+amrutazerodhacash | BD12: =487057.4+1507227.3 -> 1994284.7 | BF12: aniketstocks+amrutastocks+amrutazerodhacash | BG12: =441521+1415595.78 -> 1857116.8 | BI12: crypto | BJ12: 0
A13: hdfc index | B13: 3380314.3 | D13: hdfc index | E13: 3380481.9 | G13: hdfc index | H13: 3607298.6 | J13: hdfc index | K13: 3749945.8 | M13: hdfc index | N13: 3885675.2 | P13: hdfc index | Q13: 4252946.1 | S13: hdfc index | T13: 4241222.8 | V13: hdfc index | W13: 4154869.6 | Y13: hdfc index | Z13: 4135250 | AB13: hdfc index | AC13: 3895492.1 | AE13: hdfc index | AF13: 4077846.8 | AH13: hdfc index | AI13: 4283437.8 | AK13: hdfc index | AL13: 4376134 | AN13: hdfc index | AO13: 4510752.7 | AQ13: hdfc index | AR13: 4385311.7 | AT13: MO midcap | AU13: 951058.7 | AW13: MO midcap | AX13: 1002795.5 | AZ13: MO midcap | BA13: 997849.75 | BC13: MO midcap | BD13: 956939.7 | BF13: MO midcap | BG13: 869738
A14: icici index | B14: 3383709.5 | D14: icici index | E14: 3384096.8 | G14: icici index | H14: 3611381 | J14: icici index | K14: 3754130.3 | M14: icici index | N14: 3890199 | P14: icici index | Q14: 3651710.9 | S14: icici index | T14: 3641537.1 | V14: icici index | W14: 3567540.2 | Y14: icici index | Z14: 3550627.7 | AB14: icici index | AC14: 3344764.9 | AE14: icici index | AF14: 3501017.5 | AH14: icici index | AI14: 3677102.9 | AK14: icici index | AL14: 3756686 | AN14: icici index | AO14: 3872421.9 | AQ14: icici index | AR14: 3764793 | AT14: hdfc midcap | AU14: 839420.1 | AW14: hdfc midcap | AX14: 878070.85 | AZ14: hdfc midcap | BA14: 896086.2 | BC14: hdfc midcap | BD14: 898313.84 | BF14: hdfc midcap | BG14: 898979
A15: Zerodha Cash | B15: 228388.64 | D15: Zerodha Cash | E15: 661661.17 | G15: Zerodha Cash | H15: 811000 | J15: Zerodha Cash | K15: 496612.21 | M15: Zerodha Cash | N15: 16000 | P15: Zerodha Cash | Q15: 88000 | S15: Zerodha Cash | T15: 238126 | V15: Zerodha Cash | W15: 437579.32 | Y15: Zerodha Cash | Z15: 500000 | AB15: Zerodha Cash | AC15: 600000 | AE15: Zerodha Cash | AF15: 675000 | AH15: Zerodha Cash | AI15: 413934 | AK15: Zerodha Cash | AL15: 567264 | AN15: Zerodha Cash | AO15: 65000 | AQ15: Zerodha Cash | AR15: 250000 | AT15: hdfc index | AU15: 3772585.2 | AW15: hdfc index | AX15: 3946120.4 | AZ15: hdfc index | BA15: 4021020.2 | BC15: hdfc index | BD15: 4016339.8 | BF15: hdfc index | BG15: 3914849
A16: Sbi | B16: 641244 | D16: Sbi | E16: 745656 | G16: Sbi | H16: 883516 | J16: Sbi | K16: 934309 | M16: Sbi | N16: 232186 | P16: Sbi | Q16: 343077 | S16: Sbi | T16: 724365 | V16: Sbi | W16: 688648.09 | Y16: Sbi | Z16: 1006347 | AB16: Sbi | AC16: 1309157 | AE16: Sbi | AF16: 567173 | AH16: Sbi | AI16: 400936 | AK16: Sbi | AL16: 561112 | AN16: Sbi | AO16: 19792 | AQ16: Sbi | AR16: 240500 | AT16: icici index | AU16: 3746509.6 | AW16: icici index | AX16: 3918749.2 | AZ16: icici index | BA16: 3993218.9 | BC16: icici index | BD16: 3988655 | BF16: icici index | BG16: 3887785
A17: Hdfc | B17: 300 | D17: Hdfc | E17: 300 | G17: Hdfc | H17: 400 | J17: Hdfc | K17: 880878 | M17: Hdfc | N17: 4682 | P17: Hdfc | Q17: 500 | S17: Hdfc | T17: 706 | V17: Hdfc | W17: 1006 | Y17: Hdfc | Z17: 790.4 | AB17: Hdfc | AC17: 2060 | AE17: Hdfc | AF17: 6094 | AH17: Hdfc | AI17: 6287 | AK17: Hdfc | AL17: 755 | AN17: Hdfc | AO17: 32602 | AQ17: Hdfc | AR17: 1600 | AT17: Zerodha Cash | AU17: 236000 | AW17: Zerodha Cash | AX17: 340000 | AZ17: Zerodha Cash | BA17: 126000 | BC17: Zerodha Cash | BD17: 173000 | BF17: Zerodha Cash | BG17: 152000 | BI17: Equity | BJ17: =BJ2+BJ3+BJ6+BJ7+BJ4+BJ5 -> 11428468
A18: Citi | B18: 102530 | D18: Citi | E18: 102530 | G18: Citi | H18: 102000 | J18: Axis | K18: 102484 | M18: Axis | N18: 102245 | P18: Axis | Q18: 101998 | S18: Axis | T18: 101998 | V18: Axis | W18: 102759 | Y18: Axis | Z18: 102757 | AB18: Axis | AC18: 102607 | AE18: Axis | AF18: 102475 | AH18: Axis | AI18: 102475 | AK18: Axis | AL18: 102475 | AN18: Axis | AO18: 103185 | AQ18: Axis | AR18: 102000 | AT18: Sbi | AU18: 129248 | AW18: Sbi | AX18: 661449 | AZ18: Sbi | BA18: 96883 | BC18: Sbi | BD18: 4000 | BF18: Sbi | BG18: 221432 | BI18: PF | BJ18: =651717+358128 -> 1009845
A19: crypto | B19: 480000 | D19: crypto | E19: 480000 | G19: crypto | H19: 480000 | J19: crypto | K19: 480000 | M19: crypto | N19: 480000 | P19: crypto | Q19: 480000 | S19: crypto | T19: 0 | V19: crypto | W19: 0 | Y19: crypto | Z19: 0 | AB19: crypto | AC19: 0 | AE19: crypto | AF19: 0 | AH19: crypto | AI19: 0 | AK19: crypto | AL19: 0 | AN19: crypto | AO19: 0 | AQ19: crypto | AR19: 0 | AT19: Hdfc | AU19: 290404 | AW19: Hdfc | AX19: 900 | AZ19: Hdfc | BA19: 800 | BC19: Hdfc | BD19: =386626-447905-235000 -> -296279 | BF19: Hdfc | BG19: 193301 | BI19: Free | BJ19: =BJ8+BJ9+BJ10+BJ11 -> 669745
A20: given by parents | B20: =8075000+70000+3700000 -> 11845000 | C20: =B20*7% -> 829150 | D20: given by parents | E20: =8075000+70000+3700000 -> 11845000 | G20: given by parents | H20: =8075000+70000+3700000 -> 11845000 | J20: given by parents | K20: =8075000+70000+3700000+1550000 -> 13395000 | M20: given by mummy | N20: =8075000+70000+3700000+1550000-2000000-1550000 -> 9845000 | P20: given by mummy | Q20: =8075000+70000+3700000+1550000-2000000-1550000 -> 9845000 | S20: given by mummy | T20: =8075000+70000+3700000+1550000-2000000-1550000 -> 9845000 | V20: given by mummy | W20: =8075000+70000+3700000+1550000-2000000-1550000 -> 9845000 | Y20: given by mummy | Z20: =8075000+70000+3700000+1550000-2000000-1550000 -> 9845000 | AB20: given by mummy | AC20: =8075000+70000+3700000+1550000-2000000-1550000 -> 9845000 | AE20: given by mummy | AF20: =8075000+70000+3700000+1550000-2000000-1550000 -> 9845000 | AH20: given by mummy | AI20: =8075000+70000+3700000+1550000-2000000-1550000 -> 9845000 | AK20: given by mummy | AL20: =8075000+70000+3700000+1550000-2000000-1550000 -> 9845000 | AN20: given by mummy | AO20: =8075000+70000+3700000+1550000-2000000-1550000 -> 9845000 | AQ20: given by mummy | AR20: =8075000+70000+3700000+1550000-2000000-1550000 -> 9845000 | AT20: Axis | AU20: 75900 | AW20: Axis | AX20: 75700 | AZ20: Axis | BA20: 75000 | BC20: Axis | BD20: 75000 | BF20: Amruta HDFC | BG20: 146392 | BI20: Kohinoor flat | BJ20: 5932760
A21: My Total | B21: =SUM(B9:B19)-B20-B12-B13-B14 -> 12561939 | D21: My Total | E21: =SUM(E9:E19)-E20-E12-E13-E14 -> 13187747 | G21: My Total | H21: =SUM(H9:H19)-H20-H12-H13-H14 -> 14270030 | J21: My Total | K21: =SUM(K9:K19)-K20-K12-K13-K14 -> 13757824 | M21: My Total | N21: =SUM(N9:N19)-N20-N12-N13-N14 -> 13794967 | P21: My Total | Q21: =SUM(Q9:Q19)-Q20-Q12-Q13-Q14 -> 13061939 | S21: My Total | T21: =SUM(T9:T19)-T20-T12-T13-T14 -> 13388907 | V21: My Total | W21: =SUM(W9:W19)-W20-W12-W13-W14 -> 13407292 | Y21: My Total | Z21: =SUM(Z9:Z19)-Z20-Z12-Z13-Z14 -> 13799623 | AB21: My Total | AC21: =SUM(AC9:AC19)-AC20-AC12-AC13-AC14 -> 13715533 | AE21: My Total | AF21: =SUM(AF9:AF19)-AF20-AF12-AF13-AF14 -> 14632484 | AH21: My Total | AI21: =SUM(AI9:AI19)-AI20-AI12-AI13-AI14 -> 16193298 | AK21: My Total | AL21: =SUM(AL9:AL19)-AL20-AL12-AL13-AL14 -> 16846468 | AN21: My Total | AO21: =SUM(AO9:AO19)-AO20-AO12-AO13-AO14 -> 18021391 | AQ21: My Total | AR21: =SUM(AR9:AR19)-AR20-AR12-AR13-AR14 -> 18161954 | AT21: crypto | AU21: 0 | AW21: crypto | AX21: 0 | AZ21: crypto | BA21: 0 | BC21: crypto | BD21: 0 | BF21: crypto | BG21: 0 | BI21: A6 401 | BJ21: 17800000
AT22: given by mummy | AU22: =8075000+70000+3700000+1550000-2000000-1550000 -> 9845000 | AW22: given by mummy | AX22: =8075000+70000+3700000+1550000-2000000-1550000 -> 9845000 | AZ22: given by mummy | BA22: =8075000+70000+3700000+1550000-2000000-1550000 -> 9845000 | BC22: given by mummy | BD22: =8075000+70000+3700000+1550000-2000000-1550000 -> 9845000 | BF22: given by mummy | BG22: 0 | BI22: India Total | BJ22: =SUM(BJ17:BJ21) -> 36840818
A23: aniket pf | B23: 578013 | C23: amruta pf | D23: 287311 | E23: 45749 | F23: total | G23: =B23+D23 -> 865324 | V23: Equity | W23: =W11 -> 9512605 | Y23: Equity | Z23: =Z11 -> 9455702.2 | AB23: Equity | AC23: =AC11 -> 8902654.4 | AE23: Equity | AF23: =AF11 -> 10361984 | AH23: Equity | AI23: =AI11 -> 10758562 | AK23: Equity | AL23: =AL11 -> 11024068 | AN23: Equity | AO23: =AO11 -> 11374078 | AQ23: Equity | AR23: =AR11 -> 11058343 | AT23: My Total | AU23: =SUM(AU9:AU21)-AU22-AU12-AU15-AU16-AU13-AU14 -> 18726053 | AW23: My Total | AX23: =SUM(AX9:AX21)-AX22-AX12-AX15-AX16-AX13-AX14 -> 19606115 | AZ23: My Total | BA23: =SUM(BA9:BA21)-BA22-BA12-BA15-BA16-BA13-BA14 -> 19019109 | BC23: My Total | BD23: =SUM(BD9:BD21)-BD22-BD12-BD15-BD16-BD13-BD14 -> 18841605 | BF23: My Total | BG23: =SUM(BG9:BG21)-BG22-BG12-BG15-BG16-BG13-BG14 -> 25745071
V24: Fixed Income | W24: =W9-W20 -> 2664694.2 | Y24: Fixed Income | Z24: =Z9-Z20 -> 2734026.7 | AB24: Fixed Income | AC24: =AC9-AC20 -> 2799054.5 | AE24: Fixed Income | AF24: =AF9-AF20 -> 2919758.2 | AH24: Fixed Income | AI24: =AI9-AI20 -> 4511104.1 | AK24: Fixed Income | AL24: =AL9-AL20 -> 4590794 | AN24: Fixed Income | AO24: =AO9-AO20 -> 6426734.5 | AQ24: Fixed Income | AR24: =AR9-AR20 -> 6509510.7
A25: T-bills - Received Rs. 750000 (invested 701475) which is Rs 48525 profit (7500 * (100 - 93.53)) on 2 Nov 2023 | V25: Free | W25: =W15+W16+W17+W18 -> 1229992.4 | Y25: Free | Z25: =Z15+Z16+Z17+Z18 -> 1609894.4 | AB25: Free | AC25: =AC15+AC16+AC17+AC18 -> 2013824 | AE25: Free | AF25: =AF15+AF16+AF17+AF18 -> 1350742 | AH25: Free | AI25: =AI15+AI16+AI17+AI18 -> 923632 | AK25: Free | AL25: =AL15+AL16+AL17+AL18 -> 1231606 | AN25: Free | AO25: =AO15+AO16+AO17+AO18 -> 220579 | AQ25: Free | AR25: =AR15+AR16+AR17+AR18 -> 594100 | AT25: Equity | AU25: =AU11 -> 11349935 | AW25: Equity | AX25: =AX11 -> 11800330 | AZ25: Equity | BA25: =BA11 -> 11915366 | BC25: Equity | BD25: =BD11 -> 11854533 | BF25: Equity | BG25: =BG11 -> 11428468
A26: Bond - Received Rs. 940000 (9400 * 100) on Maturity 27 June 2024. Interest received on Dec 27 and June 27 of Rs 31443 each. Loss was 11450 (951450 - 940000) | V26: Real estate | W26: 3330645 | Y26: Real estate | Z26: 3330645 | AB26: Real estate | AC26: 3330645 | AE26: Real estate | AF26: 3330645 | AH26: Real estate | AI26: 3330645 | AK26: Real estate | AL26: 3330645 | AN26: Real estate | AO26: 3330645 | AQ26: Real estate | AR26: 3330645 | AT26: Fixed Income | AU26: =AU9-AU22 -> 6644565.8 | AW26: Fixed Income | AX26: =AX9-AX22 -> 6727735.2 | AZ26: Fixed Income | BA26: =BA9-BA22 -> 6805060 | BC26: Fixed Income | BD26: =BD9-BD22 -> 7031350.7 | BF26: Fixed Income | BG26: =BG9 -> 13603478
V27: Total | W27: =SUM(W23:W26) -> 16737937 | Y27: Total | Z27: =SUM(Z23:Z26) -> 17130268 | AB27: Total | AC27: =SUM(AC23:AC26) -> 17046178 | AE27: Total | AF27: =SUM(AF23:AF26) -> 17963129 | AH27: Total | AI27: =SUM(AI23:AI26) -> 19523943 | AK27: Total | AL27: =SUM(AL23:AL26) -> 20177113 | AN27: Total | AO27: =SUM(AO23:AO26) -> 21352036 | AQ27: Total | AR27: =SUM(AR23:AR26) -> 21492599 | AT27: Free | AU27: =AU17+AU18+AU19+AU20 -> 731552 | AW27: Free | AX27: =AX17+AX18+AX19+AX20 -> 1078049 | AZ27: Free | BA27: =BA17+BA18+BA19+BA20 -> 298683 | BC27: Free | BD27: =BD17+BD18+BD19+BD20 -> -44279 | BF27: Free | BG27: =BG17+BG18+BG19+BG20 -> 713125 | BI27: UAE Total | BJ27: =1*25 -> 25
A28: Date | B28: Total funds | C28: tata mmf | D28: amruta tata | E28: amruta absl | F28: uti liquid | G28: sbi liquid | H28: sbi savings | I28: increase per day | AT28: Real estate | AU28: 3330645 | AW28: Real estate | AX28: 3330645 | AZ28: Real estate | BA28: 4589045 | BC28: Real estate | BD28: 5484855 | BF28: Kohinoor flat | BG28: 5932760
A29: 45139 | B29: =SUM(C29:H29) -> 10372881 | D29: 1350658 | E29: 861632 | F29: 3307408 | G29: 4853183 | M29: Amruta: | AT29: Total | AU29: =SUM(AU25:AU28) -> 22056698 | AW29: Total | AX29: =SUM(AX25:AX28) -> 22936760 | AZ29: Total | BA29: =SUM(BA25:BA28) -> 23608154 | BC29: Total | BD29: =SUM(BD25:BD28) -> 24326460 | BF29: A6 401 | BG29: 17800000 | BI29: Total | BJ29: =BJ22+BJ27 -> 36840843
A30: 45143 | B30: =SUM(C30:H30) -> 10380708 | D30: 1351582 | E30: 862216 | F30: 3309974 | G30: 4856936 | I30: =(B30-B$29)/(A30-A$29) -> 1956.75 | M30: CTC | N30: 1451566 | AI30: Flexi cap | AJ30: Mid cap | AK30: Hybrid | BF30: Total | BG30: =SUM(BG25:BG29) -> 49477831
A31: 45145 | B31: =SUM(C31:H31) -> 10384397 | D31: 1352041 | E31: 862512 | F31: 3311171 | G31: 4858673 | I31: =(B31-B$29)/(A31-A$29) -> 1919.3333 | M31: PF | N31: 41328 | AI31: PP | AJ31: MO | AK31: HDFC Balanced Advantage | AN31: Flexi cap rolling returns
A32: 45149 | B32: =SUM(C32:H32) -> 10391027 | D32: 1352964 | E32: 863102 | F32: 3313236 | G32: 4861725 | I32: =(B32-B$29)/(A32-A$29) -> 1814.6 | M32: Gratuity | N32: 16566 | AI32: HDFC | AJ32: HDFC | AK32: SBI Equity Hybrid | AN32: https://www.advisorkhoj.com/mutual-funds-research/rolling-returns?category=Equity:%20Flexi%20Cap&schemes=Parag%20Parikh%20Flexi%20Cap%20Dir%20Gr,HDFC%20Flexi%20Cap%20Dir%20Gr,JM%20Flexi%20Cap%20Dir%20Gr,Motilal%20Oswal%20Flexi%20Cap%20Fund%20Dir%20Gr&start_date=10-09-2020&period=3%20Year
A33: 45155 | B33: =SUM(C33:H33) -> 10402237 | D33: 1354406 | E33: 864019 | F33: 3316859 | G33: 4866953 | I33: =(B33-B$29)/(A33-A$29) -> 1834.75 | M33: CTC-above | N33: =N30-N31-N32 -> 1393672 | P33: =N33-1200000 -> 193672 | Q33: =287000 -> 287000 | AI33: JM | AJ33: Nippon | AK33: Kotak Arbitrage
A34: 45160 | B34: =SUM(C34:H34) -> 10411575 | D34: 1355633 | E34: 864804 | F34: 3319866 | G34: 4871272 | I34: =(B34-B$29)/(A34-A$29) -> 1842.5714 | M34: Tax | N34: =90000+P34 -> 128734.4 | P34: =20%*P33 -> 38734.4 | Q34: =Q33*120% -> 344400 | AI34: MO | AJ34: Kotak | AK34: ICICI Balanced Advantage | AN34: Mid cap rolling returns
A35: 45169 | B35: =SUM(C35:H35) -> 10429162 | D35: 1357870 | E35: 866225 | F35: 3325457 | G35: 4879610 | I35: =(B35-B$29)/(A35-A$29) -> 1876.0333 | J35: =B35-B29 -> 56281 | M35: After Tax Yearly | N35: =N33-N34 -> 1264937.6 | Q35: =Q34-Q33 -> 57400 | AJ35: Edelweiss | AK35: SBI Arbitrage | AN35: https://www.advisorkhoj.com/mutual-funds-research/rolling-returns?category=Equity:%20Mid%20Cap&schemes=Edelweiss%20MidCap%20Dir%20Gr,Motilal%20Oswal%20Midcap%20Fund%20Dir%20Gr,HDFC%20Mid%20Cap%20Fund%20Gr%20Dir&start_date=10-09-2020&period=3%20Year
A36: 45170 | B36: =SUM(C36:H36) -> 10981184 | D36: 1358117 | E36: 866384 | F36: 3326115 | G36: 4880568 | H36: 550000 | M36: Monthly | N36: =N35/12 -> 105411.47 | Q36: =Q35/12 -> 4783.3333
A37: 45188 | B37: =SUM(C37:H37) -> 11019366 | D37: 1362764 | E37: 869345 | F37: 3337831 | G37: 4897726 | H37: 551700 | I37: =(B37-B$36)/(A37-A$36) -> 2121.2222 | J37: =B37-B36 -> 38182 | M37: Average Monthly with excess incentive | N37: =N36+Q36 -> 110194.8
A38: 45197 | B38: =SUM(C38:H38) -> 11035850 | D38: 1364761 | E38: 870618 | F38: 3342849 | G38: 4905013 | H38: 552609 | I38: =(B38-B$36)/(A38-A$36) -> 2024.6667 | J38: =B38-B36 -> 54666 | BG38: profit | BH38: tax | BI38: percent tax of capital
A39: 45199 | B39: =SUM(C39:H39) -> 11040837 | D39: 1365273 | E39: 870940 | F39: 3344436 | G39: 4907300 | H39: 552888 | I39: =(B39-B$36)/(A39-A$36) -> 2057 | J39: =B39-B36 -> 59653 | M39: Aniket | BD39: Antariksh bank | BE39: 2500000 | BH39: 0
A40: 45215 | B40: =SUM(C40:H40) -> 12424047 | D40: 1369317 | E40: 873501 | F40: 3354349 | G40: 4921779 | H40: 1905101 | N40: 3256546 | P40: Income tax slabs (Rs) | Q40: Income tax rate (%) | BD40: antariksh mf | BE40: 1591575 | BG40: -8400 | BH40: 0 | BI40: =BH40/BE40 -> 0 | BK40: yellow sum | BL40: my debt funds tax | BM40: others tax
A41: 45230 | B41: =SUM(C41:H41) -> 12458582 | D41: 1373094 | E41: 875903 | F41: 3363563 | G41: 4935361 | H41: 1910661 | I41: =(B41-B$40)/(A41-A$40) -> 2302.3333 | M41: Tax upto 24L | N41: 300000 | P41: From 0 to 4,00,000 | Q41: 0 | BD41: mummy debt | BE41: =1106000+2245000+1111000-1000000 -> 3462000 | BG41: =77000+138000+82000 -> 297000 | BH41: =BG41*30% -> 89100 | BI41: =BH41/BE41 -> 0.025736568 | BK41: =BE39+BE48+BE58+BE60+BE45+BE65+BE64+BE63+BE62+BE50+BE51+BE52+BE66 -> 17658849 | BL41: =BH46+BH47 -> 403500 | BM41: =BH48+BH50+BH51+BH52+BH58+BH60+BH62+BH63+BH64+BH65 -> 88470
A42: 45231 | B42: =SUM(C42:H42) -> 12460983 | D42: 1373346 | E42: 876064 | F42: 3364228 | G42: 4936284 | H42: 1911061 | I42: =(B42-B$40)/(A42-A$40) -> 2308.5 | M42: Tax after 24L | N42: =(N40-2400000)*30/100 -> 256963.8 | P42: From 4,00,001 to 8,00,000 | Q42: 5 | R42: =Q42*400000/100 -> 20000 | BD42: mummy mf | BE42: =991000+1009000 -> 2000000 | BG42: 0 | BH42: 0 | BI42: =BH42/BE42 -> 0
A43: 45237 | B43: =SUM(C43:H43) -> 12975928 | D43: 1374861 | E43: 877024 | F43: 3368169 | G43: 4942076 | H43: 2413798 | M43: Total tax | N43: =N41+N42 -> 556963.8 | P43: From 8,00,001 to 12,00,000 | Q43: 10 | R43: =Q43*400000/100 -> 40000 | BD43: Nana | BE43: 0 | BH43: 0 | BK43: taking from mummy and antariksh
A44: 45251 | B44: =SUM(C44:H44) -> 13010142 | D44: 1378414 | E44: 879288 | F44: 3377095 | G44: 4955062 | H44: 2420283 | M44: After tax yearly | N44: =N40-N43 -> 2699582.2 | P44: From 12,00,001 to 16,00,000 | Q44: 15 | R44: =Q44*400000/100 -> 60000 | BD44: Aajji | BE44: 0 | BH44: 0 | BK44: =BE39+BE40+BE41+BE42+BE50+BE51 -> 11613575
A45: 45263 | B45: =SUM(C45:H45) -> 13038553 | D45: 1381463 | E45: 881236 | F45: 3384746 | G45: 4966187 | H45: 2424921 | M45: Monthly income | N45: =N44/12 -> 224965.18 | P45: From 16,00,001 to 20,00,000 | Q45: 20 | R45: =Q45*400000/100 -> 80000 | BD45: amruta family | BE45: 900000 | BH45: 0
A46: 45271 | B46: =SUM(C46:H46) -> 13058186 | D46: 1383490.5 | E46: 882527.86 | F46: 3389958.9 | G46: 4973946 | H46: 2428262.7 | I46: =(B46-B$45)/(A46-A$45) -> 2454.1175 | P46: From 20,00,001 to 24,00,000 | Q46: 25 | R46: =Q46*400000/100 -> 100000 | S46: =R46+R45+R44+R43+R42 -> 300000 | BD46: uti liquid | BE46: 3902964.6 | BG46: 608000 | BH46: =BG46*30% -> 182400 | BI46: =BH46/BE46 -> 0.046733706 | BK46: my debt funds | BL46: profit
A47: 45288 | B47: =SUM(C47:H47) -> 13100485 | D47: 1387812 | E47: 885283 | F47: 3400727 | G47: 4989664 | H47: 2436999 | I47: =(B47-B$45)/(A47-A$45) -> 2477.28 | J47: =I47*30 -> 74318.4 | P47: From 24,00,001 and above | Q47: 30 | BD47: sbi liquid | BE47: 4640403.4 | BG47: 737000 | BH47: =BG47*30% -> 221100 | BI47: =BH47/BE47 -> 0.04764672 | BK47: =BE46+BE47 -> 8543368 | BL47: =BG46+BG47 -> 1345000
A48: 45323 | B48: =SUM(C48:H48) -> 13192134 | D48: 1396778.8 | E48: 890996.59 | F48: 3425040.4 | G48: 5025202.9 | H48: 2454114.9 | I48: =(B48-B$47)/(A48-A$47) -> 2618.5294 | J48: =I48*30 -> 78555.882 | BD48: amruta debt | BE48: 3375222 | BF48: 1000000 | BG48: 114000 | BH48: =BG48*30% -> 34200 | BI48: =BH48/BE48 -> 0.010132667
A49: 45352 | B49: =SUM(C49:H49) -> 13269435 | D49: 1404083.8 | E49: 895646.72 | F49: 3445230.1 | G49: 5054935 | H49: 2469538.9 | I49: =(B49-B$48)/(A49-A$48) -> 2665.5533 | J49: =I49*30 -> 79966.6 | BD49: amruta equity | BE49: 1450000 | BG49: -80000 | BH49: 0 | BI49: =BH49/BE49 -> 0
A50: 45380 | B50: =SUM(C50:H50) -> 13348687 | D50: 1411205.3 | E50: 900180.56 | F50: 3465504 | G50: 5085099.6 | H50: 2486697.8 | I50: =(B50-B$49)/(A50-A$49) -> 2830.4529 | J50: =B50-B49 -> 79252.68 | BD50: antariksh fd | BE50: 1030000 | BF50: 1000000 | BH50: 8708 | BI50: =BH50/BE50 -> 0.0084543689
A51: 45413 | B51: =SUM(C51:H51) -> 13437203 | D51: 1419634.1 | E51: 905550.14 | F51: 3489132.5 | G51: 5119373.7 | H51: 2503512.2 | I51: =(B51-B$50)/(A51-A$50) -> 2682.2865 | J51: =B51-B50 -> 88515.455 | BD51: antariksh fd | BE51: 1030000 | BF51: 1000000 | BH51: 8800 | BI51: =BH51/BE51 -> 0.0085436893
A52: 45445 | B52: =SUM(C52:H52) -> 13519831 | D52: 1427820.6 | E52: 910768.4 | F52: 3510938.9 | G52: 5151139.7 | H52: 2519163.8 | I52: =(B52-B$51)/(A52-A$51) -> 2582.1467 | J52: =B52-B51 -> 82628.695 | BD52: antariksh fd | BE52: 1030000 | BF52: 1000000 | BH52: 9000 | BI52: =BH52/BE52 -> 0.0087378641
A53: 45474 | B53: =SUM(C53:H53) -> 14595540 | C53: 1000350 | D53: 1435262.6 | E53: 915518 | F53: 3530497.6 | G53: 5179527 | H53: 2534384.8 | I53: =(B53-B$52)/(A53-A$52) -> 37093.4 | J53: =B53-B52 -> 1075708.6 | BD53: antariksh fd | BE53: 3107000 | BH53: 31562 | BI53: =BH53/BE53 -> 0.010158352
A54: 45505 | B54: =SUM(C54:H54) -> 14685065 | C54: 1007126.1 | D54: 1443090.3 | E54: 920507.89 | F54: 3552097.4 | G54: 5211161.5 | H54: 2551082.3 | I54: =(B54-B$53)/(A54-A$53) -> 2887.9166 | J54: =B54-B53 -> 89525.414 | BD54: antariksh fd | BE54: 1565000 | BH54: 21800 | BI54: =BH54/BE54 -> 0.013929712
A55: 45540 | B55: =SUM(C55:H55) -> 12402873 | C55: 1013923.6 | D55: 0 | E55: 0 | F55: 3575533.1 | G55: 5245383.9 | H55: 2568032 | BD55: antariksh fd | BE55: 2045000 | BH55: 29623 | BI55: =BH55/BE55 -> 0.014485575
A56: 45566 | B56: =SUM(C56:H56) -> 12468048 | C56: 1019698.2 | D56: 0 | E56: 0 | F56: 3593855.3 | G56: 5271991.9 | H56: 2582502.4 | I56: =(B56-B$55)/(A56-A$55) -> 2506.7337 | J56: =B56-B55 -> 65175.076 | BD56: antariksh fd | BE56: 1770000 | BH56: 21200 | BI56: =BH56/BE56 -> 0.011977401
A57: 45597 | B57: =SUM(C57:H57) -> 11545467 | C57: 1026151 | D57: 0 | E57: 0 | F57: 3616708 | G57: 4304060 | H57: 2598548 | I57: =(B57-B56)/(A57-A56) -> -29760.67 | J57: =B57-B56 -> -922580.77 | BD57: antariksh fd | BE57: 680000 | BH57: 8100 | BI57: =BH57/BE57 -> 0.011911765
A58: 45627 | B58: =SUM(C58:H58) -> 11606246 | C58: 1032099.8 | D58: 0 | E58: 0 | F58: 3635204.7 | G58: 4325818.9 | H58: 2613122.7 | I58: =(B58-B57)/(A58-A57) -> 2025.9697 | J58: =B58-B57 -> 60779.09 | BD58: pravin | BE58: 2718227 | BH58: 11593 | BI58: =BH58/BE58 -> 0.0042649124
A59: 45658 | B59: =SUM(C59:H59) -> 11676322 | C59: 1038473.1 | D59: 0 | E59: 0 | F59: 3657159.7 | G59: 4351589.1 | H59: 2629100.4 | I59: =(B59-B58)/(A59-A58) -> 2260.5197 | J59: =B59-B58 -> 70076.11 | BD59: pravin | BE59: 2306921 | BH59: 28316 | BI59: =BH59/BE59 -> 0.012274369
A60: 45689 | B60: =SUM(C60:H60) -> 11745655 | C60: 1045060.9 | D60: 0 | E60: 0 | F60: 3678943.7 | G60: 4377218.1 | H60: 2644432 | I60: =(B60-B59)/(A60-A59) -> 2236.5323 | J60: =B60-B59 -> 69332.5 | BD60: pravin | BE60: 2326000 | BH60: 8736 | BI60: =BH60/BE60 -> 0.003755804
A61: 45717 | B61: =SUM(C61:H61) -> 11810682 | C61: 1050943.1 | D61: 0 | E61: 0 | F61: 3699012.8 | G61: 4401073.6 | H61: 2659653 | I61: =(B61-B60)/(A61-A60) -> 2322.4196 | J61: =B61-B60 -> 65027.75 | BD61: Nana | BE61: 518000 | BH61: 3117 | BI61: =BH61/BE61 -> 0.0060173745
A62: 45748 | B62: =SUM(C62:H62) -> 11899434 | C62: 1060365.4 | D62: 0 | E62: 0 | F62: 3725155.6 | G62: 4431262.7 | H62: 2682650.5 | I62: =(B62-B61)/(A62-A61) -> 2862.9594 | J62: =B62-B61 -> 88751.74 | BD62: Nana | BE62: 768800 | BF62: =BE62+BE63+BE64+BE65 -> 2449400 | BH62: 2708 | BI62: =BH62/BE62 -> 0.0035223725
A63: 45779 | B63: =SUM(C63:H63) -> 13490780 | C63: 1069730.5 | D63: 1006035.5 | E63: 504576.06 | F63: 3747212.5 | G63: 4457128.4 | H63: 2706097.1 | I63: =(B63-B62)/(A63-A62) -> 51333.741 | J63: =B63-B62 -> 1591346 | BD63: Nana | BE63: 640600 | BF63: =BF62-1960000 -> 489400 | BH63: 2256 | BI63: =BH63/BE63 -> 0.0035216984
B64: =SUM(C64:H64) -> 12244759 | C64: 1000350 | D64: 0 | E64: 0 | F64: 3530497.6 | G64: 5179527 | H64: 2534384.8 | I64: =(B64-B63)/(A64-A63) -> 27.218173 | J64: =B64-B63 -> -1246020.8 | BD64: nana | BE64: 640000 | BH64: 2469 | BI64: =BH64/BE64 -> 0.0038578125
B65: =SUM(C65:H65) -> 12244759 | C65: 1000350 | D65: 0 | E65: 0 | F65: 3530497.6 | G65: 5179527 | H65: 2534384.8 | I65: =(B65-B64)/(A65-A64) -> #DIV/0! | J65: =B65-B64 -> 0 | BD65: nana savings | BE65: 400000 | BH65: 0 | BI65: =BH65/BE65 -> 0
B66: =SUM(C66:H66) -> 12244759 | C66: 1000350 | D66: 0 | E66: 0 | F66: 3530497.6 | G66: 5179527 | H66: 2534384.8 | I66: =(B66-B65)/(A66-A65) -> #DIV/0! | J66: =B66-B65 -> 0 | BD66: aniket | BE66: 300000 | BH66: 0 | BI66: =BH66/BE66 -> 0
B67: =SUM(C67:H67) -> 12244759 | C67: 1000350 | D67: 0 | E67: 0 | F67: 3530497.6 | G67: 5179527 | H67: 2534384.8 | I67: =(B67-B66)/(A67-A66) -> #DIV/0! | J67: =B67-B66 -> 0 | BD67: aajji savings | BE67: 326000 | BH67: 0 | BI67: =BH67/BE67 -> 0
B68: =SUM(C68:H68) -> 12244759 | C68: 1000350 | D68: 0 | E68: 0 | F68: 3530497.6 | G68: 5179527 | H68: 2534384.8 | I68: =(B68-B67)/(A68-A67) -> #DIV/0! | J68: =B68-B67 -> 0 | AU68: Dragon Mart, International City
B69: =SUM(C69:H69) -> 12244759 | C69: 1000350 | D69: 0 | E69: 0 | F69: 3530497.6 | G69: 5179527 | H69: 2534384.8 | I69: =(B69-B68)/(A69-A68) -> #DIV/0! | J69: =B69-B68 -> 0 | AU69: IKEA
AU70: Home Centre | AZ70: Online | BC70: Total taken | BD70: cash
AU71: Homebox | AZ71: 46042 | BA71: Antariksh | BB71: 1000000 | BC71: =SUM(BB71:BB77)+BE75+BE76 -> 6120000 | BD71: nana | BE71: 970000 | BG71: 16725000
AU72: Ajman used furniture market, Al Jurf 2 | AZ72: 46042 | BA72: Antariksh | BB72: 500000 | BD72: aajji | BE72: 990000 | BG72: 135000
AU73: Royal Furniture (Factory Outlet) in Ajman | AZ73: 46056 | BA73: Antariksh | BB73: 1000000 | BD73: amruta | BE73: 200000 | BG73: 750000 | BH73: sdr
AU74: Pan home al barsha or sharjah | AZ74: 46057 | BA74: Antariksh | BB74: 1000000 | BD74: aniket | BE74: 980000 | BG74: =SUM(BG71:BG73) -> 17610000 | BH74: total needed
AU75: Ajman China Mall | AZ75: 46058 | BA75: Antariksh | BB75: 1000000 | BD75: mummy | BE75: 990000
AZ76: 46059 | BA76: Antariksh | BB76: 100000 | BD76: home mummy | BE76: 250000
AZ77: 46059 | BA77: Mummy | BB77: 280000 | BD77: pravin | BE77: 800000 | BG77: 16725000
BD78: amruta family | BE78: 900000 | BG78: 134875
AZ79: 46056 | BA79: Pravin | BB79: 1000000 | BC79: =SUM(BB79:BB83)+BE77 -> 5800000 | BG79: =SUM(BG77:BG78) -> 16859875 | BH79: 10800000
AZ80: 46057 | BA80: Pravin | BB80: 1000000 | BE80: =SUM(BE71:BE79) -> 6080000 | BF80: =BE80-BE78 -> 5180000 | BH80: =BG79-BH79 -> 6059875
AZ81: 46058 | BA81: Pravin | BB81: 1000000
AZ82: 46059 | BA82: Pravin | BB82: 1000000
AZ83: 46060 | BA83: Pravin | BB83: 1000000
AX84: Funds I will withdraw | AY84: Free
AX85: =4680810.84+3937371.57+1128760.99 -> 9746943.4 | AY85: 700000 | AZ85: 46059 | BA85: Nana | BB85: =389472-25196 -> 364276 | BC85: =BB85+BE72+BE71+235000 -> 2559276
BG86: AED for INR 9L
AX87: Nana+Pravin | BA87: Amruta family | BC87: =BE45 -> 900000 | BE87: Lulu | BF87: App - Lulu Money or https://luluexchange.com/currency-converter/aed-to-inr/ | BG87: 36251.99
AX88: =BC79+BC85 -> 8359276 | BE88: Remitly | BF88: https://www.remitly.com/ae/en/india | BG88: 36175.39
BE89: Al Ansari | BF89: https://alansariexchange.com/ | BG89: 36369.99
AX90: Remaining | BE90: Emirates NBD | BF90: https://www.emiratesnbd.com/en/foreign-exchange | BG90: 36360
AX91: =AX85-AX88+AY85 -> 2087667.4
AX93: Mummy Remaining to Give | BB93: =SUM(BB71:BB92) -> 10244276 | BC93: =SUM(BC71:BC92) -> 15379276
AX94: =BC71-AX91 -> 4032332.6

Sheet month wise 2025-26
B1: April | D1: 21000000 | L1: June | N1: 21000000 | V1: August | X1: 21000000 | AG1: October | AI1: 21000000 | AQ1: December | AS1: 21000000 | BA1: February | BC1: 21000000
B2: week1 | D2: =C2*100/D$1 -> 0 | E2: =SUM(C2:C6) -> 42778 | F2: =E2*100/D1 -> 0.20370476 | G2: ani sal | H2: 161000 | L2: week1 | N2: =M2*100/N$1 -> 0 | O2: =SUM(M2:M6) -> 14334 | P2: =O2*100/N1 -> 0.068257143 | Q2: ani sal | R2: 0 | V2: week1 | W2: 1600 | X2: =W2*100/X$1 -> 0.0076190476 | Y2: =SUM(W2:W6) -> 22902 | Z2: =Y2*100/X1 -> 0.10905714 | AA2: ani sal | AB2: 209000 | AG2: week1 | AI2: =AH2*100/AI$1 -> 0 | AJ2: =SUM(AH2:AH6) -> 10330 | AK2: =AJ2*100/AI1 -> 0.049190476 | AL2: ani sal | AM2: 209000 | AQ2: week1 | AS2: =AR2*100/AS$1 -> 0 | AT2: =SUM(AR2:AR6) -> 20400 | AU2: =AT2*100/AS1 -> 0.097142857 | AV2: ani sal | AW2: 209000 | BA2: week1 | BC2: =BB2*100/BC$1 -> 0 | BD2: =SUM(BB2:BB6) -> -297120 | BE2: =BD2*100/BC1 -> -1.4148571 | BF2: ani sal | BG2: 209000
C3: 25900 | D3: =C3*100/D$1 -> 0.12333333 | G3: amr sal | H3: 170000 | M3: 6700 | N3: =M3*100/N$1 -> 0.031904762 | Q3: amr sal | R3: 90000 | W3: 7676 | X3: =W3*100/X$1 -> 0.036552381 | AA3: amr sal | AB3: 86000 | AI3: =AH3*100/AI$1 -> 0 | AL3: amr sal | AM3: 86000 | AR3: 10000 | AS3: =AR3*100/AS$1 -> 0.047619048 | AV3: amr sal | AW3: 86000 | BB3: 5792 | BC3: =BB3*100/BC$1 -> 0.027580952 | BF3: amr sal | BG3: 86000
D4: =C4*100/D$1 -> 0 | G4: p | H4: =C29 -> -633525 | N4: =M4*100/N$1 -> 0 | Q4: p | R4: =M29 -> -17601 | X4: =W4*100/X$1 -> 0 | AA4: p | AB4: =W29 -> 98079 | AI4: =AH4*100/AI$1 -> 0 | AL4: p | AM4: =AH29 -> 103759 | AR4: 3500 | AS4: =AR4*100/AS$1 -> 0.016666667 | AV4: p | AW4: =AR29 -> 130435 | BB4: =-315659-853 -> -316512 | BC4: =BB4*100/BC$1 -> -1.5072 | BF4: p | BG4: =BB29 -> -226120
C5: 16878 | D5: =C5*100/D$1 -> 0.080371429 | G5: nf strategy | H5: =0 -> 0 | M5: 7634 | N5: =M5*100/N$1 -> 0.036352381 | Q5: nf strategy | R5: 34368 | W5: 12147 | X5: =W5*100/X$1 -> 0.057842857 | AA5: nf strategy | AB5: 0 | AH5: 10330 | AI5: =AH5*100/AI$1 -> 0.049190476 | AL5: nf strategy | AM5: 0 | AR5: 6900 | AS5: =AR5*100/AS$1 -> 0.032857143 | AV5: nf strategy | AW5: 0 | BB5: 13600 | BC5: =BB5*100/BC$1 -> 0.064761905 | BF5: nf strategy | BG5: 0
D6: =C6*100/D$1 -> 0 | G6: int | H6: 80700 | I6: market total | J6: =H4+H5+H6 -> -552825 | N6: =M6*100/N$1 -> 0 | Q6: int | R6: 65000 | S6: market total | T6: =R4+R5+R6 -> 81767 | W6: 1479 | X6: =W6*100/X$1 -> 0.0070428571 | AA6: int | AB6: 65000 | AC6: market total | AD6: =AB4+AB5+AB6 -> 163079 | AI6: =AH6*100/AI$1 -> 0 | AL6: int | AM6: 65000 | AN6: market total | AO6: =AM4+AM5+AM6 -> 168759 | AS6: =AR6*100/AS$1 -> 0 | AV6: int | AW6: 65000 | AX6: market total | AY6: =AW4+AW5+AW6 -> 195435 | BC6: =BB6*100/BC$1 -> 0 | BF6: int | BG6: 65000 | BH6: market total | BI6: =BG4+BG5+BG6 -> -161120
B7: week2 | D7: =C7*100/D$1 -> 0 | E7: =SUM(C7:C11) -> -746763 | F7: =E7*100/D1 -> -3.5560143 | G7: total | H7: =SUM(H2:H6) -> -221825 | L7: week2 | N7: =M7*100/N$1 -> 0 | O7: =SUM(M7:M11) -> 13640 | P7: =O7*100/N1 -> 0.064952381 | Q7: total | R7: =SUM(R2:R6) -> 171767 | V7: week2 | X7: =W7*100/X$1 -> 0 | Y7: =SUM(W7:W11) -> 24952 | Z7: =Y7*100/X1 -> 0.11881905 | AA7: total | AB7: =SUM(AB2:AB6) -> 458079 | AG7: week2 | AI7: =AH7*100/AI$1 -> 0 | AJ7: =SUM(AH7:AH11) -> 25349 | AK7: =AJ7*100/AI1 -> 0.12070952 | AL7: total | AM7: =SUM(AM2:AM6) -> 463759 | AQ7: week2 | AR7: =9738-258 -> 9480 | AS7: =AR7*100/AS$1 -> 0.045142857 | AT7: =SUM(AR7:AR11) -> 45825 | AU7: =AT7*100/AS1 -> 0.21821429 | AV7: total | AW7: =SUM(AW2:AW6) -> 490435 | BA7: week2 | BC7: =BB7*100/BC$1 -> 0 | BD7: =SUM(BB7:BB11) -> 24700 | BE7: =BD7*100/BC1 -> 0.11761905 | BF7: total | BG7: =SUM(BG2:BG6) -> 133880
C8: -764031 | D8: =C8*100/D$1 -> -3.6382429 | M8: 6577 | N8: =M8*100/N$1 -> 0.031319048 | W8: 13250 | X8: =W8*100/X$1 -> 0.063095238 | AH8: 12283 | AI8: =AH8*100/AI$1 -> 0.058490476 | AR8: 20000 | AS8: =AR8*100/AS$1 -> 0.095238095 | BB8: 15700 | BC8: =BB8*100/BC$1 -> 0.074761905
C9: 17268 | D9: =C9*100/D$1 -> 0.082228571 | N9: =M9*100/N$1 -> 0 | X9: =W9*100/X$1 -> 0 | AI9: =AH9*100/AI$1 -> 0 | AR9: 4300 | AS9: =AR9*100/AS$1 -> 0.02047619 | BC9: =BB9*100/BC$1 -> 0
D10: =C10*100/D$1 -> 0 | M10: 7063 | N10: =M10*100/N$1 -> 0.033633333 | W10: 11702 | X10: =W10*100/X$1 -> 0.05572381 | AH10: 13066 | AI10: =AH10*100/AI$1 -> 0.062219048 | AR10: 12300 | AS10: =AR10*100/AS$1 -> 0.058571429 | BB10: 9000 | BC10: =BB10*100/BC$1 -> 0.042857143
D11: =C11*100/D$1 -> 0 | N11: =M11*100/N$1 -> 0 | X11: =W11*100/X$1 -> 0 | AI11: =AH11*100/AI$1 -> 0 | AR11: -255 | AS11: =AR11*100/AS$1 -> -0.0012142857 | BC11: =BB11*100/BC$1 -> 0
B12: week3 | D12: =C12*100/D$1 -> 0 | E12: =SUM(C12:C16) -> 26299 | F12: =E12*100/D1 -> 0.12523333 | L12: week3 | N12: =M12*100/N$1 -> 0 | O12: =SUM(M12:M16) -> 23868 | P12: =O12*100/N1 -> 0.11365714 | V12: week3 | W12: 1022 | X12: =W12*100/X$1 -> 0.0048666667 | Y12: =SUM(W12:W16) -> 17975 | Z12: =Y12*100/X1 -> 0.085595238 | AG12: week3 | AI12: =AH12*100/AI$1 -> 0 | AJ12: =SUM(AH12:AH16) -> 23380 | AK12: =AJ12*100/AI1 -> 0.11133333 | AQ12: week3 | AS12: =AR12*100/AS$1 -> 0 | AT12: =SUM(AR12:AR16) -> 29000 | AU12: =AT12*100/AS1 -> 0.13809524 | BA12: week3 | BC12: =BB12*100/BC$1 -> 0 | BD12: =SUM(BB12:BB16) -> 23500 | BE12: =BD12*100/BC1 -> 0.11190476
C13: 18858 | D13: =C13*100/D$1 -> 0.0898 | M13: 13430 | N13: =M13*100/N$1 -> 0.063952381 | W13: 7100 | X13: =W13*100/X$1 -> 0.033809524 | AH13: 11600 | AI13: =AH13*100/AI$1 -> 0.055238095 | AN13: =C29 -> -633525 | AR13: 10000 | AS13: =AR13*100/AS$1 -> 0.047619048 | BB13: 14500 | BC13: =BB13*100/BC$1 -> 0.069047619
D14: =C14*100/D$1 -> 0 | N14: =M14*100/N$1 -> 0 | X14: =W14*100/X$1 -> 0 | AH14: 1800 | AI14: =AH14*100/AI$1 -> 0.0085714286 | AN14: =C61 -> 109427 | AS14: =AR14*100/AS$1 -> 0 | BC14: =BB14*100/BC$1 -> 0
C15: 7441 | D15: =C15*100/D$1 -> 0.035433333 | M15: 10438 | N15: =M15*100/N$1 -> 0.049704762 | W15: 9853 | X15: =W15*100/X$1 -> 0.046919048 | AH15: 9980 | AI15: =AH15*100/AI$1 -> 0.04752381 | AN15: =M29 -> -17601 | AR15: 10000 | AS15: =AR15*100/AS$1 -> 0.047619048 | BB15: 9000 | BC15: =BB15*100/BC$1 -> 0.042857143
D16: =C16*100/D$1 -> 0 | N16: =M16*100/N$1 -> 0 | X16: =W16*100/X$1 -> 0 | AI16: =AH16*100/AI$1 -> 0 | AN16: =M61 -> 102823 | AR16: 9000 | AS16: =AR16*100/AS$1 -> 0.042857143 | BC16: =BB16*100/BC$1 -> 0
B17: week4 | D17: =C17*100/D$1 -> 0 | E17: =SUM(C17:C21) -> 26044 | F17: =E17*100/D1 -> 0.12401905 | L17: week4 | N17: =M17*100/N$1 -> 0 | O17: =SUM(M17:M21) -> -69443 | P17: =O17*100/N1 -> -0.33068095 | V17: week4 | W17: 4504 | X17: =W17*100/X$1 -> 0.021447619 | Y17: =SUM(W17:W21) -> 32250 | Z17: =Y17*100/X1 -> 0.15357143 | AG17: week4 | AH17: 8850 | AI17: =AH17*100/AI$1 -> 0.042142857 | AJ17: =SUM(AH17:AH21) -> 19650 | AK17: =AJ17*100/AI1 -> 0.093571429 | AN17: =W29 -> 98079 | AQ17: week4 | AS17: =AR17*100/AS$1 -> 0 | AT17: =SUM(AR17:AR21) -> 24080 | AU17: =AT17*100/AS1 -> 0.11466667 | BA17: week4 | BC17: =BB17*100/BC$1 -> 0 | BD17: =SUM(BB17:BB21) -> 22800 | BE17: =BD17*100/BC1 -> 0.10857143
C18: 10621 | D18: =C18*100/D$1 -> 0.05057619 | M18: =11645-114 -> 11531 | N18: =M18*100/N$1 -> 0.054909524 | W18: 10608 | X18: =W18*100/X$1 -> 0.050514286 | AI18: =AH18*100/AI$1 -> 0 | AN18: =W61 -> 107266 | AR18: 10600 | AS18: =AR18*100/AS$1 -> 0.05047619 | BB18: 14000 | BC18: =BB18*100/BC$1 -> 0.066666667
D19: =C19*100/D$1 -> 0 | N19: =M19*100/N$1 -> 0 | X19: =W19*100/X$1 -> 0 | AI19: =AH19*100/AI$1 -> 0 | AN19: =AH29 -> 103759 | AR19: 6300 | AS19: =AR19*100/AS$1 -> 0.03 | BC19: =BB19*100/BC$1 -> 0
C20: 15423 | D20: =C20*100/D$1 -> 0.073442857 | M20: -80974 | N20: =M20*100/N$1 -> -0.38559048 | W20: 17138 | X20: =W20*100/X$1 -> 0.081609524 | AH20: 10800 | AI20: =AH20*100/AI$1 -> 0.051428571 | AN20: =AH61 -> 86250 | AR20: 7180 | AS20: =AR20*100/AS$1 -> 0.034190476 | BB20: 8800 | BC20: =BB20*100/BC$1 -> 0.041904762
D21: =C21*100/D$1 -> 0 | N21: =M21*100/N$1 -> 0 | X21: =W21*100/X$1 -> 0 | AI21: =AH21*100/AI$1 -> 0 | AN21: =AR29 -> 130435 | AS21: =AR21*100/AS$1 -> 0 | AX21: 1000 | AY21: 2.5 | AZ21: =AX21*AY21 -> 2500 | BC21: =BB21*100/BC$1 -> 0
B22: week5 | D22: =C22*100/D$1 -> 0 | E22: =SUM(C22:C26) -> 18117 | F22: =E22*100/D1 -> 0.086271429 | L22: week5 | N22: =M22*100/N$1 -> 0 | O22: =SUM(M22:M26) -> 0 | P22: =O22*100/N1 -> 0 | V22: week5 | X22: =W22*100/X$1 -> 0 | Y22: =SUM(W22:W26) -> 0 | Z22: =Y22*100/X1 -> 0 | AG22: week5 | AI22: =AH22*100/AI$1 -> 0 | AJ22: =SUM(AH22:AH26) -> 25050 | AK22: =AJ22*100/AI1 -> 0.11928571 | AN22: =AR61 -> 103599 | AQ22: week5 | AS22: =AR22*100/AS$1 -> 0 | AT22: =SUM(AR22:AR26) -> 11130 | AU22: =AT22*100/AS1 -> 0.053 | AX22: 600 | AY22: 3.5 | AZ22: =AX22*AY22 -> 2100 | BA22: week5 | BC22: =BB22*100/BC$1 -> 0 | BD22: =SUM(BB22:BB26) -> 0 | BE22: =BD22*100/BC1 -> 0
C23: 7476 | D23: =C23*100/D$1 -> 0.0356 | N23: =M23*100/N$1 -> 0 | X23: =W23*100/X$1 -> 0 | AH23: 16000 | AI23: =AH23*100/AI$1 -> 0.076190476 | AN23: =BB29 -> -226120 | AR23: =1080+2220+1620+1350+4860 -> 11130 | AS23: =AR23*100/AS$1 -> 0.053 | AX23: 600 | AY23: 3.35 | AZ23: =AX23*AY23 -> 2010 | BC23: =BB23*100/BC$1 -> 0
C24: 10641 | D24: =C24*100/D$1 -> 0.050671429 | N24: =M24*100/N$1 -> 0 | X24: =W24*100/X$1 -> 0 | AH24: 1200 | AI24: =AH24*100/AI$1 -> 0.0057142857 | AN24: =BB61 -> 23540 | AS24: =AR24*100/AS$1 -> 0 | AX24: 1000 | AY24: 2.3 | AZ24: =AX24*AY24 -> 2300 | BC24: =BB24*100/BC$1 -> 0
D25: =C25*100/D$1 -> 0 | N25: =M25*100/N$1 -> 0 | X25: =W25*100/X$1 -> 0 | AH25: 7850 | AI25: =AH25*100/AI$1 -> 0.037380952 | AS25: =AR25*100/AS$1 -> 0 | AZ25: =SUM(AZ21:AZ24)-106 -> 8804 | BC25: =BB25*100/BC$1 -> 0
D26: =C26*100/D$1 -> 0 | N26: =M26*100/N$1 -> 0 | X26: =W26*100/X$1 -> 0 | AI26: =AH26*100/AI$1 -> 0 | AN26: =SUM(AN13:AN25) -> -12068 | AS26: =AR26*100/AS$1 -> 0 | BC26: =BB26*100/BC$1 -> 0
C29: =SUM(C2:C27) -> -633525 | M29: =SUM(M2:M27) -> -17601 | W29: =SUM(W2:W27) -> 98079 | AH29: =SUM(AH2:AH27) -> 103759 | AR29: =SUM(AR2:AR27) -> 130435 | BB29: =SUM(BB2:BB27) -> -226120
B30: % return | C30: =C29*100/D$1 -> -3.0167857 | L30: % return | M30: =M29*100/N$1 -> -0.083814286 | V30: % return | W30: =W29*100/X$1 -> 0.46704286 | AG30: % return | AH30: =AH29*100/AI$1 -> 0.49409048 | AQ30: % return | AR30: =AR29*100/AS$1 -> 0.62111905 | BA30: % return | BB30: =BB29*100/BC$1 -> -1.0767619
B31: % return with others | C31: =((C29*100)+(H5*100)+(H6*100))/D$1 -> -2.6325 | L31: % return with others | M31: =((M29*100)+(R5*100)+(R6*100))/N$1 -> 0.38936667 | V31: % return with others | W31: =((W29*100)+(AB5*100)+(AB6*100))/X$1 -> 0.77656667 | AG31: % return with others | AH31: =((AH29*100)+(AM5*100)+(AM6*100))/AI$1 -> 0.80361429 | AQ31: % return with others | AR31: =((AR29*100)+(AW5*100)+(AW6*100))/AS$1 -> 0.93064286 | BA31: % return with others | BB31: =((BB29*100)+(BG5*100)+(BG6*100))/BC$1 -> -0.7672381
B33: May | D33: 21000000 | L33: July | N33: 21000000 | V33: September | X33: 21000000 | AG33: November | AI33: 21000000 | AQ33: January | AS33: 21000000 | BA33: March | BC33: 21000000
B34: week1 | D34: =C34*100/D$33 -> 0 | E34: =SUM(C34:C38) -> 23308 | F34: =E34*100/D33 -> 0.11099048 | G34: ani sal | H34: 119607 | L34: week1 | N34: =M34*100/N$33 -> 0 | O34: =SUM(M34:M38) -> 25640 | P34: =O34*100/N33 -> 0.12209524 | Q34: ani sal | R34: 194000 | V34: week1 | X34: =W34*100/X$33 -> 0 | Y34: =SUM(W34:W38) -> 18364 | Z34: =Y34*100/X33 -> 0.087447619 | AA34: ani sal | AB34: 194000 | AG34: week1 | AI34: =AH34*100/AI$33 -> 0 | AJ34: =SUM(AH34:AH38) -> 23000 | AK34: =AJ34*100/AI33 -> 0.10952381 | AL34: ani sal | AM34: 194000 | AQ34: week1 | AS34: =AR34*100/AS$33 -> 0 | AT34: =SUM(AR34:AR38) -> 3050 | AU34: =AT34*100/AS33 -> 0.01452381 | AV34: ani sal | AW34: 194000 | BA34: week1 | BC34: =BB34*100/BC$33 -> 0 | BD34: =SUM(BB34:BB38) -> 23540 | BE34: =BD34*100/BC33 -> 0.11209524 | BF34: ani sal | BG34: 194000
C35: 10308 | D35: =C35*100/D$33 -> 0.049085714 | G35: amr sal | H35: 96000 | M35: 12000 | N35: =M35*100/N$33 -> 0.057142857 | Q35: amr sal | R35: 83000 | W35: 9458 | X35: =W35*100/X$33 -> 0.045038095 | AA35: amr sal | AB35: 83000 | AH35: 13800 | AI35: =AH35*100/AI$33 -> 0.065714286 | AL35: amr sal | AM35: 83000 | AS35: =AR35*100/AS$33 -> 0 | AV35: amr sal | AW35: 83000 | BB35: 11000 | BC35: =BB35*100/BC$33 -> 0.052380952 | BF35: amr sal | BG35: 83000
D36: =C36*100/D$33 -> 0 | G36: p | H36: =C61 -> 109427 | N36: =M36*100/N$33 -> 0 | Q36: p | R36: =M61 -> 102823 | X36: =W36*100/X$33 -> 0 | AA36: p | AB36: =W61 -> 107266 | AI36: =AH36*100/AI$33 -> 0 | AL36: p | AM36: =AH61 -> 86250 | AS36: =AR36*100/AS$33 -> 0 | AV36: p | AW36: =AR61 -> 103599 | BC36: =BB36*100/BC$33 -> 0 | BF36: p | BG36: =BB61 -> 23540
C37: 13000 | D37: =C37*100/D$33 -> 0.061904762 | G37: nf strategy | H37: -16113 | M37: 11100 | N37: =M37*100/N$33 -> 0.052857143 | Q37: nf strategy | R37: 0 | W37: 8906 | X37: =W37*100/X$33 -> 0.042409524 | AA37: nf strategy | AB37: 0 | AH37: 9200 | AI37: =AH37*100/AI$33 -> 0.043809524 | AL37: nf strategy | AM37: 0 | AR37: 3050 | AS37: =AR37*100/AS$33 -> 0.01452381 | AV37: nf strategy | AW37: 0 | BB37: 12540 | BC37: =BB37*100/BC$33 -> 0.059714286 | BF37: nf strategy | BG37: 0
D38: =C38*100/D$33 -> 0 | G38: int | H38: 79690 | I38: market total | J38: =H36+H37+H38 -> 173004 | M38: 2540 | N38: =M38*100/N$33 -> 0.012095238 | Q38: int | R38: 61000 | S38: market total | T38: =R36+R37+R38 -> 163823 | X38: =W38*100/X$33 -> 0 | AA38: int | AB38: 61000 | AC38: market total | AD38: =AB36+AB37+AB38 -> 168266 | AI38: =AH38*100/AI$33 -> 0 | AL38: int | AM38: 61000 | AN38: market total | AO38: =AM36+AM37+AM38 -> 147250 | AS38: =AR38*100/AS$33 -> 0 | AV38: int | AW38: 61000 | AX38: market total | AY38: =AW36+AW37+AW38 -> 164599 | BC38: =BB38*100/BC$33 -> 0 | BF38: int | BG38: 61000 | BH38: market total | BI38: =BG36+BG37+BG38 -> 84540
B39: week2 | D39: =C39*100/D$33 -> 0 | E39: =SUM(C39:C43) -> 9695 | F39: =E39*100/D33 -> 0.046166667 | G39: total | H39: =SUM(H34:H38) -> 388611 | L39: week2 | M39: 1200 | N39: =M39*100/N$33 -> 0.0057142857 | O39: =SUM(M39:M43) -> 14409 | P39: =O39*100/N33 -> 0.068614286 | Q39: total | R39: =SUM(R34:R38) -> 440823 | V39: week2 | X39: =W39*100/X$33 -> 0 | Y39: =SUM(W39:W43) -> 20600 | Z39: =Y39*100/X33 -> 0.098095238 | AA39: total | AB39: =SUM(AB34:AB38) -> 445266 | AG39: week2 | AI39: =AH39*100/AI$33 -> 0 | AJ39: =SUM(AH39:AH43) -> 21190 | AK39: =AJ39*100/AI33 -> 0.10090476 | AL39: total | AM39: =SUM(AM34:AM38) -> 424250 | AQ39: week2 | AS39: =AR39*100/AS$33 -> 0 | AT39: =SUM(AR39:AR43) -> 24258 | AU39: =AT39*100/AS33 -> 0.11551429 | AV39: total | AW39: =SUM(AW34:AW38) -> 441599 | BA39: week2 | BC39: =BB39*100/BC$33 -> 0 | BD39: =SUM(BB39:BB43) -> 0 | BE39: =BD39*100/BC33 -> 0 | BF39: total | BG39: =SUM(BG34:BG38) -> 361540
C40: 10990 | D40: =C40*100/D$33 -> 0.052333333 | M40: 6229 | N40: =M40*100/N$33 -> 0.029661905 | W40: 12000 | X40: =W40*100/X$33 -> 0.057142857 | AH40: 12000 | AI40: =AH40*100/AI$33 -> 0.057142857 | AR40: 7858 | AS40: =AR40*100/AS$33 -> 0.037419048 | BC40: =BB40*100/BC$33 -> 0
D41: =C41*100/D$33 -> 0 | N41: =M41*100/N$33 -> 0 | X41: =W41*100/X$33 -> 0 | AI41: =AH41*100/AI$33 -> 0 | AR41: 7780 | AS41: =AR41*100/AS$33 -> 0.037047619 | BC41: =BB41*100/BC$33 -> 0
C42: -1295 | D42: =C42*100/D$33 -> -0.0061666667 | M42: 6980 | N42: =M42*100/N$33 -> 0.033238095 | W42: 8600 | X42: =W42*100/X$33 -> 0.040952381 | AH42: 9190 | AI42: =AH42*100/AI$33 -> 0.043761905 | AR42: 8620 | AS42: =AR42*100/AS$33 -> 0.041047619 | BC42: =BB42*100/BC$33 -> 0
D43: =C43*100/D$33 -> 0 | N43: =M43*100/N$33 -> 0 | X43: =W43*100/X$33 -> 0 | AI43: =AH43*100/AI$33 -> 0 | AS43: =AR43*100/AS$33 -> 0 | BC43: =BB43*100/BC$33 -> 0
B44: week3 | C44: 9082 | D44: =C44*100/D$33 -> 0.043247619 | E44: =SUM(C44:C48) -> 50816 | F44: =E44*100/D33 -> 0.24198095 | L44: week3 | N44: =M44*100/N$33 -> 0 | O44: =SUM(M44:M48) -> 14610 | P44: =O44*100/N33 -> 0.069571429 | V44: week3 | X44: =W44*100/X$33 -> 0 | Y44: =SUM(W44:W48) -> 20782 | Z44: =Y44*100/X33 -> 0.098961905 | AG44: week3 | AI44: =AH44*100/AI$33 -> 0 | AJ44: =SUM(AH44:AH48) -> 20270 | AK44: =AJ44*100/AI33 -> 0.09652381 | AQ44: week3 | AS44: =AR44*100/AS$33 -> 0 | AT44: =SUM(AR44:AR48) -> 23786 | AU44: =AT44*100/AS33 -> 0.11326667 | BA44: week3 | BC44: =BB44*100/BC$33 -> 0 | BD44: =SUM(BB44:BB48) -> 0 | BE44: =BD44*100/BC33 -> 0
C45: 11041 | D45: =C45*100/D$33 -> 0.05257619 | M45: 10340 | N45: =M45*100/N$33 -> 0.049238095 | W45: 11932 | X45: =W45*100/X$33 -> 0.056819048 | AH45: 11570 | AI45: =AH45*100/AI$33 -> 0.055095238 | AR45: 16000 | AS45: =AR45*100/AS$33 -> 0.076190476 | BC45: =BB45*100/BC$33 -> 0
C46: 11227 | D46: =C46*100/D$33 -> 0.053461905 | M46: -2100 | N46: =M46*100/N$33 -> -0.01 | X46: =W46*100/X$33 -> 0 | AI46: =AH46*100/AI$33 -> 0 | AS46: =AR46*100/AS$33 -> 0 | BC46: =BB46*100/BC$33 -> 0
C47: 19466 | D47: =C47*100/D$33 -> 0.092695238 | M47: 6370 | N47: =M47*100/N$33 -> 0.030333333 | W47: 8850 | X47: =W47*100/X$33 -> 0.042142857 | AH47: 8700 | AI47: =AH47*100/AI$33 -> 0.041428571 | AR47: =7987-201 -> 7786 | AS47: =AR47*100/AS$33 -> 0.03707619 | BC47: =BB47*100/BC$33 -> 0
D48: =C48*100/D$33 -> 0 | N48: =M48*100/N$33 -> 0 | X48: =W48*100/X$33 -> 0 | AI48: =AH48*100/AI$33 -> 0 | AS48: =AR48*100/AS$33 -> 0 | BC48: =BB48*100/BC$33 -> 0
B49: week4 | D49: =C49*100/D$33 -> 0 | E49: =SUM(C49:C53) -> 25608 | F49: =E49*100/D33 -> 0.12194286 | L49: week4 | N49: =M49*100/N$33 -> 0 | O49: =SUM(M49:M53) -> 18447 | P49: =O49*100/N33 -> 0.087842857 | V49: week4 | X49: =W49*100/X$33 -> 0 | Y49: =SUM(W49:W53) -> 27080 | Z49: =Y49*100/X33 -> 0.12895238 | AG49: week4 | AI49: =AH49*100/AI$33 -> 0 | AJ49: =SUM(AH49:AH53) -> 21790 | AK49: =AJ49*100/AI33 -> 0.1037619 | AQ49: week4 | AR49: -13405 | AS49: =AR49*100/AS$33 -> -0.063833333 | AT49: =SUM(AR49:AR53) -> 21655 | AU49: =AT49*100/AS33 -> 0.10311905 | BA49: week4 | BC49: =BB49*100/BC$33 -> 0 | BD49: =SUM(BB49:BB53) -> 0 | BE49: =BD49*100/BC33 -> 0
C50: 12194 | D50: =C50*100/D$33 -> 0.058066667 | M50: 8710 | N50: =M50*100/N$33 -> 0.04147619 | W50: 12280 | X50: =W50*100/X$33 -> 0.05847619 | AH50: 13500 | AI50: =AH50*100/AI$33 -> 0.064285714 | AR50: 8400 | AS50: =AR50*100/AS$33 -> 0.04 | BC50: =BB50*100/BC$33 -> 0
D51: =C51*100/D$33 -> 0 | N51: =M51*100/N$33 -> 0 | X51: =W51*100/X$33 -> 0 | AI51: =AH51*100/AI$33 -> 0 | AS51: =AR51*100/AS$33 -> 0 | BC51: =BB51*100/BC$33 -> 0
C52: 13414 | D52: =C52*100/D$33 -> 0.06387619 | M52: 9737 | N52: =M52*100/N$33 -> 0.046366667 | W52: 14800 | X52: =W52*100/X$33 -> 0.07047619 | AH52: 8290 | AI52: =AH52*100/AI$33 -> 0.03947619 | AR52: 26660 | AS52: =AR52*100/AS$33 -> 0.12695238 | BC52: =BB52*100/BC$33 -> 0
D53: =C53*100/D$33 -> 0 | H53: 112254 | N53: =M53*100/N$33 -> 0 | X53: =W53*100/X$33 -> 0 | AI53: =AH53*100/AI$33 -> 0 | AS53: =AR53*100/AS$33 -> 0 | BC53: =BB53*100/BC$33 -> 0
B54: week5 | D54: =C54*100/D$33 -> 0 | E54: =SUM(C54:C58) -> 0 | F54: =E54*100/D33 -> 0 | H54: 102254 | L54: week5 | N54: =M54*100/N$33 -> 0 | O54: =SUM(M54:M58) -> 29717 | P54: =O54*100/N33 -> 0.14150952 | V54: week5 | X54: =W54*100/X$33 -> 0 | Y54: =SUM(W54:W58) -> 20440 | Z54: =Y54*100/X33 -> 0.097333333 | AG54: week5 | AI54: =AH54*100/AI$33 -> 0 | AJ54: =SUM(AH54:AH58) -> 0 | AK54: =AJ54*100/AI33 -> 0 | AQ54: week5 | AS54: =AR54*100/AS$33 -> 0 | AT54: =SUM(AR54:AR58) -> 30850 | AU54: =AT54*100/AS33 -> 0.14690476 | BA54: week5 | BC54: =BB54*100/BC$33 -> 0 | BD54: =SUM(BB54:BB58) -> 0 | BE54: =BD54*100/BC33 -> 0
D55: =C55*100/D$33 -> 0 | H55: 102254 | M55: 14817 | N55: =M55*100/N$33 -> 0.070557143 | W55: 20440 | X55: =W55*100/X$33 -> 0.097333333 | AI55: =AH55*100/AI$33 -> 0 | AR55: 22500 | AS55: =AR55*100/AS$33 -> 0.10714286 | BC55: =BB55*100/BC$33 -> 0
D56: =C56*100/D$33 -> 0 | H56: 131906 | N56: =M56*100/N$33 -> 0 | X56: =W56*100/X$33 -> 0 | AI56: =AH56*100/AI$33 -> 0 | AS56: =AR56*100/AS$33 -> 0 | BC56: =BB56*100/BC$33 -> 0
D57: =C57*100/D$33 -> 0 | H57: 106490 | M57: 14900 | N57: =M57*100/N$33 -> 0.070952381 | X57: =W57*100/X$33 -> 0 | AI57: =AH57*100/AI$33 -> 0 | AR57: 8350 | AS57: =AR57*100/AS$33 -> 0.039761905 | BC57: =BB57*100/BC$33 -> 0
D58: =C58*100/D$33 -> 0 | H58: 106490 | N58: =M58*100/N$33 -> 0 | X58: =W58*100/X$33 -> 0 | AI58: =AH58*100/AI$33 -> 0 | AS58: =AR58*100/AS$33 -> 0 | BC58: =BB58*100/BC$33 -> 0
H59: 106385
H60: 106385
C61: =SUM(C34:C59) -> 109427 | H61: 106385 | M61: =SUM(M34:M59) -> 102823 | W61: =SUM(W34:W59) -> 107266 | AH61: =SUM(AH34:AH59) -> 86250 | AR61: =SUM(AR34:AR59) -> 103599 | BB61: =SUM(BB34:BB59) -> 23540
B62: % return | C62: =C61*100/D$33 -> 0.52108095 | H62: 106385 | L62: % return | M62: =M61*100/N$33 -> 0.48963333 | V62: % return | W62: =W61*100/X$33 -> 0.51079048 | AG62: % return | AH62: =AH61*100/AI$33 -> 0.41071429 | AQ62: % return | AR62: =AR61*100/AS$33 -> 0.49332857 | BA62: % return | BB62: =BB61*100/BC$33 -> 0.11209524
B63: % return with others | C63: =((C61*100)+(H37*100)+(H38*100))/D$33 -> 0.82382857 | H63: 106385 | L63: % return with others | M63: =((M61*100)+(R37*100)+(R38*100))/N$33 -> 0.78010952 | V63: % return with others | W63: =((W61*100)+(AB37*100)+(AB38*100))/X$33 -> 0.80126667 | AG63: % return with others | AH63: =((AH61*100)+(AM37*100)+(AM38*100))/AI$33 -> 0.70119048 | AQ63: % return with others | AR63: =((AR61*100)+(AW37*100)+(AW38*100))/AS$33 -> 0.78380476 | BA63: % return with others | BB63: =((BB61*100)+(BG37*100)+(BG38*100))/BC$33 -> 0.40257143
H64: 102254
W66: Total capital | X66: 22000000
W67: Premium for return | AA67: nifty | AB67: 26200
W68: 0.001 | X68: 0.002 | Y68: 0.003 | AA68: lot size | AB68: 75
Q69: slabs | R69: lot size | S69: total lots | T69: qty per slab | U69: Total qty | V69: Instru | W69: =X66*W68 -> 22000 | X69: =X66*X68 -> 44000 | Y69: =X66*Y68 -> 66000 | AA69: contract size | AB69: =AB67*AB68 -> 1965000 | AC69: capital invested | AD69: 7420338 | AE69: lots | AF69: =AD69/AB69 -> 3.7762534 | AG69: qty | AH69: =AB68*AF69 -> 283.21901
Q70: 4 | R70: 75 | S70: =T70/R70 -> 42 | T70: =U70/Q70 -> 3150 | U70: 12600 | V70: MIDCP | W70: =W69/U70 -> 1.7460317 | X70: =X69/U70 -> 3.4920635 | Y70: =Y69/U70 -> 5.2380952 | AA70: niftybees | AB70: 218.5 | AU70: palace towers 1 and 2
G71: 110525 | H71: =SUM(H53:H70) -> 1295827 | I71: 1187713 | Q71: 4 | R71: 40 | S71: =T71/R71 -> 40 | T71: =U71/Q71 -> 1600 | U71: 6400 | V71: FNF | W71: =W69/U71 -> 3.4375 | X71: =X69/U71 -> 6.875 | Y71: =Y69/U71 -> 10.3125 | AA71: qty niftybees | AB71: =AB69/AB70 -> 8993.135 | AU71: Spring Oasis
H72: =H71+G71 -> 1406352 | Q72: 4 | R72: 15 | S72: =T72/R72 -> 45 | T72: =U72/Q72 -> 675 | U72: 2700 | V72: BNF | W72: =W69/U72 -> 8.1481481 | X72: =X69/U72 -> 16.296296 | Y72: =Y69/U72 -> 24.444444 | AA72: niftybees value | AB72: =AB71*AB70 -> 1965000 | AU72: Al Manal Residence 1
H73: 1406352 | I73: =H73-I71 -> 218639 | Q73: 4 | R73: 50 | S73: =T73/R73 -> 30 | T73: =U73/Q73 -> 1500 | U73: 6000 | V73: NF | W73: =W69/U73 -> 3.6666667 | X73: =X69/U73 -> 7.3333333 | Y73: =Y69/U73 -> 11 | AU73: axis 5
H74: 1683727 | I74: =H74-H73 -> 277375 | Q74: 4 | R74: 10 | S74: =T74/R74 -> 45 | T74: =U74/Q74 -> 450 | U74: 1800 | V74: SENSEX | W74: =W69/U74 -> 12.222222 | X74: =X69/U74 -> 24.444444 | Y74: =Y69/U74 -> 36.666667 | AU74: Al Manal Pearl
Q75: 4 | R75: 15 | S75: =T75/R75 -> 30 | T75: =U75/Q75 -> 450 | U75: 1800 | V75: BANKEX | W75: =W69/U75 -> 12.222222 | X75: =X69/U75 -> 24.444444 | Y75: =Y69/U75 -> 36.666667 | AA75: haircut | AB75: 0.08 | AC75: =AB72*AB75 -> 157200
AA76: niftybees value after haircut | AB76: =AB72-AC75 -> 1807800
E77: 2984000 | F77: 2640000 | V77: 0.35 | W77: 0.3 | AA77: monthly return assumed | AB77: 0.012 | AF77: nifty | AG77: 25000
F78: =E77-F77 -> 344000 | U78: 45352 | V78: 12000000 | W78: 12000000 | AA78: monthly profit | AB78: =AB76*AB77 -> 21693.6 | AF78: lot size | AG78: 25
F79: =F78/F77 -> 0.13030303 | U79: 45717 | V79: =V78+V78*V77 -> 16200000 | W79: =W78+W78*W77 -> 15600000 | AA79: actual monthly profit (considering haircut) | AB79: =AB78/AB72 -> 0.01104 | AC79: =AB79*AB72 -> 21693.6 | AF79: contract size | AG79: =AG77*AG78 -> 625000 | AH79: capital invested | AI79: 7420338 | AJ79: lots | AK79: =AI79/AG79 -> 11.872541 | AL79: qty | AM79: =AG78*AK79 -> 296.81352
U80: 46082 | V80: =V79+V79*V77 -> 21870000 | W80: =W79+W79*W77 -> 20280000 | AF80: niftybees | AG80: 218.5
E81: 2905431 | F81: 2568046 | U81: 46447 | V81: =V80+V80*V77 -> 29524500 | W81: =W80+W80*W77 -> 26364000 | AF81: qty niftybees | AG81: =AG79/AG80 -> 2860.4119
F82: =E81-F81 -> 337385 | U82: 46813 | V82: =V81+V81*V77 -> 39858075 | W82: =W81+W81*W77 -> 34273200 | AF82: niftybees value | AG82: =AG81*AG80 -> 625000
F83: =F82/F81 -> 0.1313781
B89: Sr. No.
C90: Section1 | D90: Transaction Date | E90: Status | F90: Date of | G90: Remarks** | H90: Amount | I90: Tax | J90: TDS
E91: of Booking* | F91: Booking | H91: Paid / | I91: Deducted## | J91: Deposited ( Rs. )
H92: Credited ( Rs. ) | I92: ( Rs. )
B94: 1 | C94: 192 | D94: 45716 | E94: F | F94: 45818 | G94: - | H94: 10105 | I94: 10105 | J94: 10105 | L94: 112254
B95: 2 | C95: 192 | D95: 45688 | E95: F | F95: 45818 | G95: - | H95: 116490 | I95: 10105 | J95: 10105 | K95: =H95-I95 -> 106385 | L95: 102254 | M95: =H102-I102 -> 102254
B96: 3 | C96: 192 | D96: 45658 | E96: F | F96: 45818 | G96: - | H96: 116490 | I96: 10105 | J96: 10105 | K96: =H96-I96 -> 106385 | L96: 102254 | M96: =H103-I103 -> 102254
B97: 4 | C97: 192 | D97: 45625 | E97: F | F97: 45697 | G97: - | H97: 116490 | I97: 10105 | J97: 10105 | K97: =H97-I97 -> 106385 | L97: 131906 | M97: =H101-I101 -> 131906
B98: 5 | C98: 192 | D98: 45589 | E98: F | F98: 45697 | G98: - | H98: 116490 | I98: 10105 | J98: 10105 | K98: =H98-I98 -> 106385 | L98: 106490 | M98: =H99-I99 -> 106490
B99: 6 | C99: 192 | D99: 45566 | E99: F | F99: 45697 | G99: - | H99: 116490 | I99: 10000 | J99: 10000 | K99: =H99-I99 -> 106490 | L99: 106490 | M99: =H100-I100 -> 106490
B100: 7 | C100: 192 | D100: 45534 | E100: F | F100: 45604 | G100: - | H100: 116490 | I100: 10000 | J100: 10000 | K100: =H100-I100 -> 106490 | L100: 106385 | M100: =H95-I95 -> 106385
B101: 8 | C101: 192 | D101: 45505 | E101: F | F101: 45604 | G101: - | H101: 141906 | I101: 10000 | J101: 10000 | K101: =H101-I101 -> 131906 | L101: 106385 | M101: =H96-I96 -> 106385
B102: 9 | C102: 192 | D102: 45475 | E102: F | F102: 45604 | G102: - | H102: 112254 | I102: 10000 | J102: 10000 | K102: =H102-I102 -> 102254 | L102: 106385 | M102: =H97-I97 -> 106385
B103: 10 | C103: 192 | D103: 45443 | E103: F | F103: 45515 | G103: - | H103: 112254 | I103: 10000 | J103: 10000 | K103: =H103-I103 -> 102254 | L103: 106385 | M103: =H98-I98 -> 106385
B104: 11 | C104: 192 | D104: 45412 | E104: F | F104: 45515 | G104: - | H104: 112254 | I104: 10000 | J104: 10000 | K104: =H104-I104 -> 102254 | L104: 106385
L105: 102254 | M105: =H104-I104 -> 102254

Sheet Agreement
M1: Plot: | R1: Aniket | S1: Mummy | AO1: 20% with indexation | AR1: 12.5% without indexation | AU1: 20% with indexation | AX1: 12.5% without indexation | BA1: 20% with indexation | BD1: 12.5% without indexation | BJ1: 12.5% without indexation | BM1: 12.5% without indexation
C2: Agreement | D2: 8531524 | G2: TDS | H2: 8531 | I2: Paid till now: | J2: Paid to builder | M2: Cleaning | N2: 40000 | P2: Mummy salary | R2: 3750 | Z2: Agreement | AA2: 8531532 | AI2: CG | AJ2: 19092500 | AL2: CG | AM2: 19092500 | AO2: CG | AP2: 19092500 | AR2: CG | AS2: 19750000 | AU2: CG | AV2: 19092500 | AX2: CG | AY2: 19750000 | BA2: CG | BB2: 19092500 | BD2: CG | BE2: 19750000 | BJ2: CG | BK2: 19750000 | BM2: CG | BN2: 19750000
C3: GST | D3: 426576 | E3: 0.05 | G3: Aniket | H3: =H2/2 -> 4265.5 | I3: =D4+D5 -> 541900 | M3: Fabricator for 2 boards | N3: =3000+4800 -> 7800 | P3: 215696 | R3: 1000 | T3: Exemption=CG*investment/netSaleConsideration | Z3: GST | AA3: =AA2*AB3 -> 426576.6 | AB3: 0.05 | AI3: Investment | AJ3: 13100000 | AL3: Investment | AM3: 4102000 | AO3: Land | AP3: 4102000 | AR3: Land | AS3: 4102000 | AU3: Land | AV3: 4102000 | AX3: Land | AY3: 4102000 | BA3: Land | BB3: 4102000 | BD3: Land | BE3: 4102000 | BJ3: Land | BK3: 4102400 | BM3: Land | BN3: 4102400
C4: Stamp duty | D4: 511900 | E4: 0.06 | G4: Amruta | H4: =H2/2 -> 4265.5 | I4: 16000 | M4: Painter for 2 boards | N4: 3600 | P4: 218696 | R4: 2000 | Z4: Stamp duty | AA4: =AA2*AB4 -> 511891.92 | AB4: 0.06 | AD4: Ready reckoner 4L per guntha | AI4: NetSaleConsideration | AJ4: 20000000 | AL4: NetSaleConsideration | AM4: 20000000 | AO4: Flat | AP4: 13100000 | AR4: Flat | AS4: 13100000 | AU4: Flat | AV4: 12811000 | AX4: Flat | AY4: 12811000 | BA4: Flat | BB4: 14500000 | BD4: Flat | BE4: 14500000 | BJ4: Flat | BK4: 12811000 | BM4: Flat | BN4: 12811000
C5: Registration | D5: 30000 | I5: 85315 | M5: Tempo for boards | N5: =700+600 -> 1300 | P5: 213296 | T5: CG | U5: 19092500 | W5: CG | X5: 19455500 | Z5: Registration | AA5: 30000 | AD5: Total 32L baazarbhaav | AI5: Exemption | AJ5: =AJ2*AJ3/AJ4 -> 12505588 | AL5: Exemption | AM5: =AM2*AM3/AM4 -> 3915871.8 | AO5: Total Invested | AP5: =AP4+AP3 -> 17202000 | AR5: Total Invested | AS5: =AS4+AS3 -> 17202000 | AU5: Total Invested | AV5: =AV4+AV3 -> 16913000 | AX5: Total Invested | AY5: =AY4+AY3 -> 16913000 | BA5: Total Invested | BB5: =BB4+BB3 -> 18602000 | BD5: Total Invested | BE5: =BE4+BE3 -> 18602000 | BJ5: Proportion | BK5: =BK2*BK4/20000000 -> 12650862 | BM5: Proportion | BN5: =BN2*BN4/20000000 -> 12650862
C6: Total | D6: =SUM(D2:D5) -> 9500000 | I6: 1511835 | P6: 215276 | T6: Investment | U6: 17500000 | W6: Investment | X6: 17500000 | Z6: Total | AA6: =SUM(AA2:AA5) -> 9500000.5 | AO6: Proportion | AP6: =AP2*AP5/20000000 -> 16421459 | AR6: Proportion | AS6: =AS2*AS5/20000000 -> 16986975 | AU6: Proportion | AV6: =AV2*AV5/20000000 -> 16145573 | AX6: Proportion | AY6: =AY2*AY5/20000000 -> 16701588 | BA6: Proportion | BB6: =BB2*BB5/20000000 -> 17757934 | BD6: Proportion | BE6: =BE2*BE5/20000000 -> 18369475 | BJ6: Total Invested | BK6: =BK5+BK3 -> 16753262 | BM6: Total Invested | BN6: =BN5+BN3 -> 16753262
I7: 25594 | N7: =SUM(N2:N5) -> 52700 | P7: 257852 | T7: NetSaleConsideration | U7: 20000000 | W7: NetSaleConsideration | X7: 20000000 | AI7: Total Exempt | AJ7: =AJ5+AM5 -> 16421459 | AO7: Remaining | AP7: =AP2-AP6 -> 2671040.8 | AR7: Remaining | AS7: =AS2-AS6 -> 2763025 | AU7: Remaining | AV7: =AV2-AV6 -> 2946927.4 | AX7: Remaining | AY7: =AY2-AY6 -> 3048412.5 | BA7: Remaining | BB7: =BB2-BB6 -> 1334565.8 | BD7: Remaining | BE7: =BE2-BE6 -> 1380525 | BJ7: Remaining | BK7: =BK2-BK6 -> 2996737.5 | BM7: Remaining | BN7: =BN2-BN6 -> 2996737.5
C8: Legal fees | D8: 16000 | I8: 600000 | P8: 289324 | Q8: =297+190 -> 487 | T8: Exemption | U8: =U5*U6/U7 -> 16705938 | W8: Exemption | X8: =X5*X6/X7 -> 17023562 | AI8: Remaining | AJ8: =AJ2-AJ7 -> 2671040.8 | AO8: Tax | AP8: =AP7*20% -> 534208.15 | AR8: Tax | AS8: =AS7*12.5% -> 345378.12 | AU8: Tax | AV8: =AV7*20% -> 589385.47 | AX8: Tax | AY8: =AY7*12.5% -> 381051.56 | BA8: Tax | BB8: =BB7*20% -> 266913.15 | BD8: Tax | BE8: =BE7*12.5% -> 172565.62 | BJ8: Tax | BK8: =BK7*12.5% -> 374592.19 | BM8: Tax | BN8: =BN7*12.5% -> 374592.19
I9: 400000 | P9: 2080 | T9: RemainingFromSale | U9: =U7-U8 -> 3294062.5 | W9: RemainingFromSale | X9: =X7-X8 -> 2976437.5 | Z9: TDS | AA9: =AA2*AB9 -> 85315.32 | AB9: 0.01 | AD9: Mama sells vrindavan flat for 80L | AL9: =19750000-AJ7 -> 3328540.8
D10: Amount | E10: GST | F10: TDS | G10: Amount without TDS | I10: 75000 | P10: 1560 | Y10: =X5*12500000/X7 -> 12159688 | Z10: Balance agreement | AA10: =AA2-AA9 -> 8446216.7 | AD10: I sell PI flat to Mama for 80L. Balance 30L to receive from Mama/Nana | AL10: =AJ8*20% -> 534208.15 | AO10: Invest in Bonds | AP10: 2675000 | AR10: Invest in Bonds | AS10: 2770000 | AU10: Invest in Bonds | AV10: 2960000 | AX10: Invest in Bonds | AY10: 3065000 | BA10: Invest in Bonds | BB10: 1340000 | BD10: Invest in Bonds | BE10: 1390000 | BJ10: Invest in Bonds | BK10: 2996737.5 | BM10: Invest in Bonds | BN10: 2996737.5
C11: 0.1 | D11: 853152 | E11: 42658 | F11: 8532 | G11: =D11+E11-F11 -> 887278 | I11: 75000 | K11: Nyati emerald | L11: K pune | M11: Pristine O2 | O11: VJ Balewadi | P11: 182 | Q11: =16500+1500-150-1196+3000 -> 19654 | T11: CG | U11: 19092500 | W11: CG | X11: 19455500 | Y11: =15400000/X5*X7 -> 15830999 | AD11: We buy Loni Kalbhor plot for 32L. Balance 28L to give to Mama/Nana | AL11: =AL9*12.5% -> 416067.59 | AO11: Interest 5.25% for 5 years | AP11: =AP10*5.25%*5 -> 702187.5 | AR11: Interest 5.25% for 5 years | AS11: =AS10*5.25%*5 -> 727125 | AU11: Interest 5.25% for 5 years | AV11: =AV10*5.25%*5 -> 777000 | AX11: Interest 5.25% for 5 years | AY11: =AY10*5.25%*5 -> 804562.5 | BA11: Interest 5.25% for 5 years | BB11: =BB10*5.25%*5 -> 351750 | BD11: Interest 5.25% for 5 years | BE11: =BE10*5.25%*5 -> 364875 | BJ11: Interest 5.25% for 5 years | BK11: =BK10*5.25%*5 -> 786643.59 | BM11: Interest 5.25% for 5 years | BN11: =BN10*5.25%*5 -> 786643.59
C12: 0.2 | D12: 1706305 | E12: 85315 | F12: 17063 | G12: =D12+E12-F12 -> 1774557 | I12: 1258401 | K12: =101.64+11.07 -> 112.71 | L12: =92.74+10.96 -> 103.7 | M12: =92.04 -> 92.04 | O12: 104.47 | P12: =SUM(P3:P11) -> 1413962 | T12: Investment | U12: 4100000 | W12: Investment | X12: 4100000 | AD12: Nana gives 2L to Mummy as gift | AO12: Tax 20% | AP12: =AP11*20% -> 140437.5 | AR12: Tax 20% | AS12: =AS11*20% -> 145425 | AU12: Tax 20% | AV12: =AV11*20% -> 155400 | AX12: Tax 20% | AY12: =AY11*20% -> 160912.5 | BA12: Tax 20% | BB12: =BB11*20% -> 70350 | BD12: Tax 20% | BE12: =BE11*20% -> 72975 | BJ12: Tax 20% | BK12: =BK11*20% -> 157328.72 | BM12: Tax 20% | BN12: =BN11*20% -> 157328.72
C13: Total 30% with GST | D13: =SUM(D11:D12)+E11+E12 -> 2687430 | F13: =SUM(F11:F12) -> 25595 | G13: =SUM(G11:G12) -> 2661835 | I13: 447905 | K13: =K12*10.7639 -> 1213.1992 | L13: =L12*10.7639 -> 1116.2164 | M13: =M12*10.7639 -> 990.70936 | O13: =O12*10.7639 -> 1124.5046 | T13: NetSaleConsideration | U13: 20000000 | W13: NetSaleConsideration | X13: 20000000 | Z13: 0.3 | AA13: =AA10*Z13 -> 2533865 | AO13: Net Interest | AP13: =AP11-AP12 -> 561750 | AR13: Net Interest | AS13: =AS11-AS12 -> 581700 | AU13: Net Interest | AV13: =AV11-AV12 -> 621600 | AX13: Net Interest | AY13: =AY11-AY12 -> 643650 | BA13: Net Interest | BB13: =BB11-BB12 -> 281400 | BD13: Net Interest | BE13: =BE11-BE12 -> 291900 | BJ13: Net Interest | BK13: =BK11-BK12 -> 629314.88 | BM13: Net Interest | BN13: =BN11-BN12 -> 629314.88
C14: Paid before agreement | D14: 1150000 | G14: 1150000 | I14: 447905 | Q14: 1299 | T14: Exemption | U14: =U11*U12/U13 -> 3913962.5 | W14: Exemption | X14: =X11*X12/X13 -> 3988377.5 | Z14: -150000 | AA14: =AA13+Z14 -> 2383865 | AD14: Mama sells vrindavan flat for 80L | AO14: Total Value | AP14: =AP10+AP13 -> 3236750 | AR14: Total Value | AS14: =AS10+AS13 -> 3351700 | AU14: Total Value | AV14: =AV10+AV13 -> 3581600 | AX14: Total Value | AY14: =AY10+AY13 -> 3708650 | BA14: Total Value | BB14: =BB10+BB13 -> 1621400 | BD14: Total Value | BE14: =BE10+BE13 -> 1681900 | BJ14: Total Value | BK14: =BK10+BK13 -> 3626052.4 | BM14: Total Value | BN14: =BN10+BN13 -> 3626052.4
C15: Remaining after agreement | D15: =D13-D14 -> 1537430 | G15: =G13-G14 -> 1511835 | I15: 447905 | K15: =13711350+959800+30000 -> 14701150 | L15: =9000000+630000+3000 -> 9633000 | M15: =11000000+770000+30000 -> 11800000 | N15: T5 301 | O15: =15044600+1053200+30000 -> 16127800 | Q15: 799 | T15: RemainingFromSale | U15: =U13-U14 -> 16086038 | W15: RemainingFromSale | X15: =X13-X14 -> 16011622 | Z15: GST | AA15: =AA14*AB3 -> 119193.25 | AD15: I sell PI flat to Mama for 82L. Balance 28L to receive from Mama/Nana
C16: Demanded | D16: 1537429 | G16: 1537429 | O16: =15223200+1065700+30000 -> 16318900 | Q16: 329 | Z16: First Installment | AA16: =AA14+AA15 -> 2503058.3 | AD16: We buy Loni Kalbhor plot for 32L. Balance 28L to give to Mama/Nana | AO16: FD after tax | AP16: =AP7-AP8 -> 2136832.6 | AR16: FD after tax | AS16: =AS7-AS8 -> 2417646.9 | AU16: FD after tax | AV16: =AV7-AV8 -> 2357541.9 | AX16: FD after tax | AY16: =AY7-AY8 -> 2667360.9 | BA16: FD after tax | BB16: =BB7-BB8 -> 1067652.6 | BD16: FD after tax | BE16: =BE7-BE8 -> 1207959.4 | BJ16: FD after tax | BK16: =BK7-BK8 -> 2622145.3 | BM16: FD after tax | BN16: =BN7-BN8 -> 2622145.3
K17: =13169643+921900+30000 -> 14121543 | L17: =11100000+777000+30000 -> 11907000 | M17: =11179462+782600+30000 -> 11992062 | N17: T5 1304 | O17: =14687500+1028200+30000 -> 15745700 | Q17: 1527 | T17: CG | U17: 19850000 | Y17: =180+31+7 -> 218 | Z17: SD + R | AA17: =AA4+AA5 -> 541891.92 | AD17: Balances offset | AO17: Interest 6.9% for 5 years | AP17: =AP16*6.9%*5 -> 737207.25 | AR17: Interest 6.9% for 5 years | AS17: =AS16*6.9%*5 -> 834088.17 | AU17: Interest 6.9% for 5 years | AV17: =AV16*6.9%*5 -> 813351.96 | AX17: Interest 6.9% for 5 years | AY17: =AY16*6.9%*5 -> 920239.52 | BA17: Interest 6.9% for 5 years | BB17: =BB16*6.9%*5 -> 368340.15 | BD17: Interest 6.9% for 5 years | BE17: =BE16*6.9%*5 -> 416745.98 | BJ17: Simple Interest 6.9% for 5 years | BK17: =BK16*6.9%*5 -> 904640.13 | BM17: Compound Interest 6.9% for 5 years
A18: CG | B18: 19500000 | G18: 1146550 | Q18: 299 | T18: Investment | U18: 17500000 | W18: Agreement | X18: 3841500 | AO18: Total Value | AP18: =AP16+AP17 -> 2874039.8 | AR18: Total Value | AS18: =AS16+AS17 -> 3251735 | AU18: Total Value | AV18: =AV16+AV17 -> 3170893.9 | AX18: Total Value | AY18: =AY16+AY17 -> 3587600.5 | BA18: Total Value | BB18: =BB16+BB17 -> 1435992.7 | BD18: Total Value | BE18: =BE16+BE17 -> 1624705.4 | BJ18: Tax 0% | BK18: =BK17*0% -> 0 | BM18: Tax 0% | BN18: =BN17*0% -> 0
A19: Land | B19: Bonds | C19: Flat (proportion) | D19: Flat (agreement value) | L19: =124.76+16.02 -> 140.78 | M19: =102.47 -> 102.47 | O19: =99.55+8.36 -> 107.91 | Q19: 569 | T19: NetSaleConsideration | U19: 20000000 | W19: SDR | X19: 262490 | Y19: =31*4.5% -> 1.395 | Z19: Total | AA19: =AA16+AA17 -> 3044950.2 | BJ19: Net Interest | BK19: =BK17-BK18 -> 904640.13 | BM19: Net Interest | BN19: =BN17-BN18 -> 0
A20: 4102000 | B20: 5000000 | C20: 10900000 | D20: 11400000 | L20: =L19*10.7639 -> 1515.3418 | M20: =M19*10.7639 -> 1102.9768 | O20: =O19*10.7639 -> 1161.5324 | Q20: 199 | T20: Exemption | U20: =U17*U18/U19 -> 17368750 | W20: Total | X20: =X19+X18 -> 4103990 | Y20: =5.25*15% -> 0.7875 | AO20: Difference Bonds vs FD | AP20: =AP14-AP18 -> 362710.15 | AR20: Difference Bonds vs FD | AS20: =AS14-AS18 -> 99964.953 | AU20: Difference Bonds vs FD | AV20: =AV14-AV18 -> 410706.14 | AX20: Difference Bonds vs FD | AY20: =AY14-AY18 -> 121049.54 | BA20: Difference Bonds vs FD | BB20: =BB14-BB18 -> 185407.25 | BD20: Difference Bonds vs FD | BE20: =BE14-BE18 -> 57194.641 | BJ20: Total Value | BK20: =BK16+BK19 -> 3526785.4 | BM20: Total Value | BN20: 3660540
A21: 4102000 | B21: 3250000 | C21: 12650000 | D21: 13000000 | G21: 746900 | H21: Total Cost to me till now | I21: =SUM(I3:I20) -> 5932760 | Q21: =SUM(Q14:Q20) -> 5021 | R21: =SUM(R2:R20) -> 6750 | S21: =SUM(S2:S20) -> 0 | T21: RemainingFromSale | U21: =U19-U20 -> 2631250 | Y21: =9620000+5000000+4000000 -> 18620000
A22: 4102000 | B22: 0 | C22: 15400000 | D22: 15840000 | G22: =426078+200 -> 426278 | H22: Paid to builder till now | I22: =I21-I3-I4 -> 5374860 | L22: =16537000+1157600+30000 -> 17724600 | M22: =13116964+787100+30000 -> 13934064 | O22: =15223200+1065700+30000 -> 16318900 | S22: =S21+R21 -> 6750 | Y22: =U26+X26 -> 16973735 | BJ22: Difference Bonds vs FD | BK22: =BK14-BK20 -> 99266.93 | BM22: Difference Bonds vs FD | BN22: =BN14-BN20 -> -34487.625
A23: Bonds - REC or PFC. NHAI is discontinued | G23: 240000 | H23: Total to be paid to builder (A+B) | I23: =8531524+426576 -> 8958100 | T23: CG | U23: 19850000 | W23: CG | X23: 19850000 | AK23: ✅ Comparison With and Without Indexation
G24: =G21-G22-G23 -> 80622 | H24: Pending to be paid to builder | I24: =I23-I22 -> 3583240 | L24: =15779000+1104600+30000 -> 16913600 | M24: =13822321+967600+30000 -> 14819921 | O24: 887278 | P24: 3839186 | Q24: =853152+42658 -> 895810 | R24: 8532 | T24: Investment | U24: 4102000 | W24: Investment | X24: 13000000
O25: 1774557 | P25: 191959 | Q25: =1706305+85315 -> 1791620 | R25: 17063 | T25: NetSaleConsideration | U25: 20000000 | W25: NetSaleConsideration | X25: 20000000 | AK25: Basis | AL25: Capital Gain | AM25: Exemption (Sec 54) | AN25: Taxable Gain | AO25: Tax Rate | AP25: Tax (with cess)
L26: =16008000+1120600+30000 -> 17158600 | O26: 1330918 | P26: =SUM(P24:P25) -> 4031145 | Q26: =1279729+63986 -> 1343715 | R26: 12797 | T26: Exemption | U26: =U23*U24/U25 -> 4071235 | W26: Exemption | X26: =X23*X24/X25 -> 12902500 | AK26: With Indexation | AL26: 19092500 | AM26: 17102000 | AN26: 1990500 | AO26: 0.2 | AP26: ₹4,14,024 ✅
N27: =P26-O27 -> 38392 | O27: =SUM(O24:O26) -> 3992753 | Q27: =SUM(Q24:Q26) -> 4031145 | R27: =SUM(R24:R26) -> 38392 | T27: RemainingFromSale | U27: =U25-U26 -> 15928765 | W27: RemainingFromSale | X27: =X25-X26 -> 7097500 | AK27: Without Indexation | AL27: 19750000 | AM27: 17102000 | AN27: 2648000 | AO27: 0.125 | AP27: ₹3,71,400 ✅
BI29: salary
AK30: Invest 20 Lakhs in 54EC bonds | BI30: 215696
AK31: Option | AL31: Maturity Amount (5 Years) | BI31: 218696
AK32: 54EC Bonds (5.25%, 20% tax) | AL32: ₹24,20,000 ✅ | BI32: 213296
AK33: FD at 6.90% after paying LTCG tax | AL33: 2209132 | BI33: 215276
AK34: Net Advantage of 54EC Bonds | AL34: 210868 | BI34: 257852
BI35: 289324
BI36: 19512
BH37: total salary | BI37: =SUM(BI30:BI36) -> 1429652
AK38: Flat ₹1.31 Cr + Land ₹41.02L = ₹1,72,02,000 Reinvested
BI39: 26AS:
AK40: Exemption=₹1,90,92,500×(1,72,02,0002,00,00,000)=₹1,90,92,500×0.8601≈₹1,64,31,543\text{Exemption} = ₹1,90,92,500 × \left( \frac{1,72,02,000}{2,00,00,000} \right) = ₹1,90,92,500 × 0.8601 ≈ ₹1,64,31,543Exemption=₹1,90,92,500×(2,00,00,0001,72,02,000​)=₹1,90,92,500×0.8601≈₹1,64,31,543 | BI40: salary before tax | BJ40: tax | BK40: net tax
BI41: 1962230 | BJ41: 426000 | BK41: =1962230-426000 -> 1536230
AK42: Taxable LTCG = ₹1,90,92,500 – ₹1,64,31,543 = ₹26,60,957
BI43: tax till 15 lakhs | BJ43: 140000
AK44: 54EC investment = ₹26,60,957 | BI44: above 15 lakhs | BJ44: =BI41-1500000 -> 462230
BI45: 0.3 | BJ45: =BJ44*30% -> 138669
AK46: 54EC Bonds @ 5.25% for 5 Years (Simple Interest) | BI46: expected tax | BJ46: =BJ43+BJ45 -> 278669
BI47: excess tax paid | BJ47: =BJ41-BJ46 -> 147331
AK48: Annual interest: ₹1,39,701
BI49: expected CG tax | BJ49: =375000 -> 375000
AK50: Total 5-year interest: ₹6,98,507 | BI50: remaining tax | BJ50: =BJ49-BJ47 -> 227669
BI51: 4% cess | BJ51: =BJ50*4% -> 9106.76
AK52: Tax @20%: ₹1,39,701
AK54: Post-tax interest: ₹5,58,806
AK56: Maturity = ₹26,60,957 + ₹5,58,806 = ₹32,19,763
C58: 45790 | D58: 300000 | F58: legal charges | G58: 10000
C59: 45818 | D59: 720900 | AK59: Flat ₹1.28 Cr + Land ₹41.02L = ₹1.69 cr Reinvested
C60: 45827 | D60: 115145
C61: 45834 | D61: 1000000 | AK61: Exemption=₹1,90,92,500×(2,00,00,0001,69,02,000​)≈₹1,90,92,500×0.8451≈₹1,61,28,947
C62: 45835 | D62: 1000000
C63: 45838 | D63: 1000000 | AK63: Taxable LTCG = ₹1,90,92,500 – ₹1,61,28,947 = ₹29,63,553
C64: 45839 | D64: 766343
C65: 45839 | D65: 259074 | AK65: 54EC investment = ₹29,63,553
C66: 45840 | D66: 1000000
C67: 46010 | D67: 604507 | AK67: 54EC Bond Return (₹29,63,553 @ 5.25% Simple Interest)
AK69: Annual interest: ₹29,63,553 × 5.25% = ₹1,55,836
AK71: 5-year interest = ₹7,79,180
AK73: Tax @ 20% on interest = ₹1,55,836
AK75: Post-tax interest = ₹6,23,344
AK77: Maturity = ₹29,63,553 + ₹6,23,344 = ₹35,86,897
AK80: CAPITAL GAIN BONDS COMPARISON WITH FD
F81: mummy debt funds | G81: 4450000 | AK81: FD at 6.90% interest not taxable, but have to pay initial tax. Bonds have no initial tax but will have 20% tax as per slab on 5.25% interest
F82: antariksh fd | G82: 12000000 | AK82: Investment | AL82: Option | AM82: Maturity | AN82: Difference
C83: Total | D83: =SUM(D59:D82) -> 6465969 | G83: =SUM(G81:G82) -> 16450000 | AK83: ₹26.75L | AL83: 54EC Bonds | AM83: ₹32.37L | AN83: 2.5L
AL84: FD (post-tax) | AM84: ₹29.86L
AK85: ₹29.80L | AL85: 54EC Bonds | AM85: ₹36.06L | AN85: 2.78L
AL86: FD (post-tax) | AM86: ₹33.28L

Sheet Sheet2
A1: Building | D1: Building | F1: Building
A2: Al Manal Pearl | D2: Binghatti point | F2: The White Palace
A3: Al Manal Residence 1 | D3: Nova tower
A4: Al Manal Residence 2 | D4: ASB Tower | I4: silicon avenue
A5: Arabian Gate | D5: Axis 1 | I5: la vista 3
A6: Axis 5 | D6: S Residence (bad management)
A7: Axis 6 | D7: Axis 7
A8: Axis 8 | D8: Axis 4
A9: Binghatti Apartments | D9: Mirage 1
A10: Imperial Tower | D10: Le Presidium 1
A11: La Vista 1, 2, 3 | D11: Altia
A12: la vista 6
A13: Mirage 3 | D13: Le Presidium 2
A14: Oasis High Park | D14: Silicon arch | L14: 139748
A15: Palace Tower | D15: Al Thuraya | L15: 62000
A16: Ruby Residence | D16: Coral residence | L16: 43451
A17: Sapphire Residences | L17: =L14+L15-L16 -> 158297
A18: Silicon Avenue | D18: Palacio tower | L18: 448000
A19: Silicon Gate 1 | L19: =L17+L18 -> 606297
A20: SP Oasis | D20: Park Terrace
A21: Spring Oasis | D21: Lynx
A22: Silicon Star 2

Sheet Sheet1
A1: DA | B1: HRA | C1: Month | D1: Days | E1: PAY | F1: DA | G1: HRA | H1: CLA | I1: TA | J1: OTHER | K1: TOTAL
A2: 53 | B2: 30 | C2: Sep-2024 (from 4-Sep) | D2: 27 | E2: 164430 | F2: =E2*A2/100 -> 87147.9 | G2: =E2*B2/100 -> 49329 | H2: 216 | I2: 4860 | J2: 4050 | K2: =SUM(E2:J2) -> 310032.9
A3: 53 | B3: 30 | C3: 45566 | D3: 30 | E3: 182700 | F3: =E3*A3/100 -> 96831 | G3: =E3*B3/100 -> 54810 | H3: 240 | I3: 5400 | J3: 4500 | K3: =SUM(E3:J3) -> 344481
A4: 53 | B4: 30 | C4: 45597 | D4: 30 | E4: 182700 | F4: =E4*A4/100 -> 96831 | G4: =E4*B4/100 -> 54810 | H4: 240 | I4: 5400 | J4: 4500 | K4: =SUM(E4:J4) -> 344481
A5: 53 | B5: 30 | C5: 45627 | D5: 30 | E5: 182700 | F5: =E5*A5/100 -> 96831 | G5: =E5*B5/100 -> 54810 | H5: 240 | I5: 5400 | J5: 4500 | K5: =SUM(E5:J5) -> 344481
A6: 55 | B6: 30 | C6: 45658 | D6: 30 | E6: 188200 | F6: =E6*A6/100 -> 103510 | G6: =E6*B6/100 -> 56460 | H6: 240 | I6: 5400 | J6: 4500 | K6: =SUM(E6:J6) -> 358310
A7: 55 | B7: 30 | C7: 45689 | D7: 30 | E7: 188200 | F7: =E7*A7/100 -> 103510 | G7: =E7*B7/100 -> 56460 | H7: 240 | I7: 5400 | J7: 4500 | K7: =SUM(E7:J7) -> 358310
A8: 55 | B8: 30 | C8: 45717 | D8: 30 | E8: 188200 | F8: =E8*A8/100 -> 103510 | G8: =E8*B8/100 -> 56460 | H8: 240 | I8: 5400 | J8: 4500 | K8: =SUM(E8:J8) -> 358310
A9: 55 | B9: 30 | C9: 45748 | D9: 30 | E9: 188200 | F9: =E9*A9/100 -> 103510 | G9: =E9*B9/100 -> 56460 | H9: 240 | I9: 5400 | J9: 4500 | K9: =SUM(E9:J9) -> 358310
A10: 55 | B10: 30 | C10: 45778 | D10: 30 | E10: 188200 | F10: =E10*A10/100 -> 103510 | G10: =E10*B10/100 -> 56460 | H10: 240 | I10: 5400 | J10: 4500 | K10: =SUM(E10:J10) -> 358310
A11: 55 | B11: 30 | C11: 45809 | D11: 30 | E11: 188200 | F11: =E11*A11/100 -> 103510 | G11: =E11*B11/100 -> 56460 | H11: 240 | I11: 5400 | J11: 4500 | K11: =SUM(E11:J11) -> 358310
A12: 55 | B12: 30 | C12: Jul-2025 (1–16 Jul) | D12: 16 | E12: =E11*D12/D11 -> 100373.33 | F12: =E12*A12/100 -> 55205.333 | G12: =E12*B12/100 -> 30112 | H12: 128 | I12: 2880 | J12: 2400 | K12: =SUM(E12:J12) -> 191098.67
E13: =SUM(E2:E12) -> 1942103.3 | F13: =SUM(F2:F12) -> 1053906.2 | G13: =SUM(G2:G12) -> 582631 | H13: =SUM(H2:H12) -> 2504 | I13: =SUM(I2:I12) -> 56340 | J13: =SUM(J2:J12) -> 46950 | K13: =SUM(K2:K12) -> 3684434.6

Sheet Equity
A1: FOR KOHINOOR FLAT, MY PURCHASE COST IS RS. 42,65,762. IN FY 2024-25, RS. 23,77,210 WORTH DEBT FUNDS REDEMPTION WAS CLAIMED UNDER SECTION 54F EXEMPTION FOR LTCG ON THE DEBT FUNDS.
A2: REMAINING RS. 18,88,552 CAN STILL BE CLAIMED UNDER SECTION 54F AND ALL LTCG FROM THIS AMOUNT WILL BE EXEMPTED.
A3: NIFTYBEES SELL VALUE IS 1275077. HDFC NIFTY 50 INDEX FUND SELL VALUE IS 602749. TOTAL RS. 1877826 CAN BE CLAIMED UNDER SECTION 54F.
A4: MENTION DAY WISE ENTRIES WHILE ADDING LTCG ENTRIES AND ALSO SECTION 54F ENTRIES.
A6: LTCG:
A7: DATE | B7: BUY VALUE | C7: SELL VALUE | D7: P&L
A8: 45887 | B8: 436900 | C8: 562800 | D8: 125900 | E8: NIFTYBEES
A9: 45888 | B9: 553115.4 | C9: 712276.92 | D9: 159161.52 | E9: NIFTYBEES
A10: 45890 | B10: 492390.25 | C10: 602749.52 | D10: 110359.27 | E10: HDFC NIFTY 50 INDEX FUND
C11: =SUM(C8:C10) -> 1877826.4 | D11: =SUM(D8:D10) -> 395420.79
A13: NIFTYBEES TOTAL | N13: NIFTYBEES SELL ON 18-08-2025
A15: Symbol | B15: ISIN | C15: Entry Date | D15: Exit Date | E15: Quantity | F15: Buy Value | G15: Sell Value | H15: Profit | I15: Period of Holding | J15: Fair Market Value | K15: Taxable Profit | L15: Turnover | N15: Symbol | O15: ISIN | P15: Entry Date | Q15: Exit Date | R15: Quantity | S15: Buy Value | T15: Sell Value | U15: Profit | V15: Period of Holding | W15: Fair Market Value | X15: Taxable Profit | Y15: Turnover
A16: NIFTYBEES | B16: INF204KB14I2 | C16: 2023-11-24 | D16: 2025-08-18 | E16: 8 | F16: 1747.6 | G16: 2251.2 | H16: 503.6 | I16: 633 | J16: 0 | K16: 503.6 | L16: 0 | N16: NIFTYBEES | O16: INF204KB14I2 | P16: 2023-11-24 | Q16: 2025-08-18 | R16: 8 | S16: 1747.6 | T16: 2251.2 | U16: 503.6 | V16: 633 | W16: 0 | X16: 503.6 | Y16: 0
A17: NIFTYBEES | B17: INF204KB14I2 | C17: 2023-11-24 | D17: 2025-08-18 | E17: 2 | F17: 436.9 | G17: 562.8 | H17: 125.9 | I17: 633 | J17: 0 | K17: 125.9 | L17: 0 | N17: NIFTYBEES | O17: INF204KB14I2 | P17: 2023-11-24 | Q17: 2025-08-18 | R17: 2 | S17: 436.9 | T17: 562.8 | U17: 125.9 | V17: 633 | W17: 0 | X17: 125.9 | Y17: 0
A18: NIFTYBEES | B18: INF204KB14I2 | C18: 2023-11-24 | D18: 2025-08-18 | E18: 238 | F18: 51991.1 | G18: 66973.2 | H18: 14982.1 | I18: 633 | J18: 0 | K18: 14982.1 | L18: 0 | N18: NIFTYBEES | O18: INF204KB14I2 | P18: 2023-11-24 | Q18: 2025-08-18 | R18: 238 | S18: 51991.1 | T18: 66973.2 | U18: 14982.1 | V18: 633 | W18: 0 | X18: 14982.1 | Y18: 0
A19: NIFTYBEES | B19: INF204KB14I2 | C19: 2023-11-24 | D19: 2025-08-18 | E19: 60 | F19: 13107 | G19: 16884 | H19: 3777 | I19: 633 | J19: 0 | K19: 3777 | L19: 0 | N19: NIFTYBEES | O19: INF204KB14I2 | P19: 2023-11-24 | Q19: 2025-08-18 | R19: 60 | S19: 13107 | T19: 16884 | U19: 3777 | V19: 633 | W19: 0 | X19: 3777 | Y19: 0
A20: NIFTYBEES | B20: INF204KB14I2 | C20: 2023-11-24 | D20: 2025-08-18 | E20: 383 | F20: 83666.35 | G20: 107776.2 | H20: 24109.85 | I20: 633 | J20: 0 | K20: 24109.85 | L20: 0 | N20: NIFTYBEES | O20: INF204KB14I2 | P20: 2023-11-24 | Q20: 2025-08-18 | R20: 383 | S20: 83666.35 | T20: 107776.2 | U20: 24109.85 | V20: 633 | W20: 0 | X20: 24109.85 | Y20: 0
A21: NIFTYBEES | B21: INF204KB14I2 | C21: 2023-11-24 | D21: 2025-08-18 | E21: 95 | F21: 20752.75 | G21: 26733 | H21: 5980.25 | I21: 633 | J21: 0 | K21: 5980.25 | L21: 0 | N21: NIFTYBEES | O21: INF204KB14I2 | P21: 2023-11-24 | Q21: 2025-08-18 | R21: 95 | S21: 20752.75 | T21: 26733 | U21: 5980.25 | V21: 633 | W21: 0 | X21: 5980.25 | Y21: 0
A22: NIFTYBEES | B22: INF204KB14I2 | C22: 2023-11-24 | D22: 2025-08-18 | E22: 4 | F22: 873.8 | G22: 1125.6 | H22: 251.8 | I22: 633 | J22: 0 | K22: 251.8 | L22: 0 | N22: NIFTYBEES | O22: INF204KB14I2 | P22: 2023-11-24 | Q22: 2025-08-18 | R22: 4 | S22: 873.8 | T22: 1125.6 | U22: 251.8 | V22: 633 | W22: 0 | X22: 251.8 | Y22: 0
A23: NIFTYBEES | B23: INF204KB14I2 | C23: 2023-11-24 | D23: 2025-08-18 | E23: 320 | F23: 69904 | G23: 90048 | H23: 20144 | I23: 633 | J23: 0 | K23: 20144 | L23: 0 | N23: NIFTYBEES | O23: INF204KB14I2 | P23: 2023-11-24 | Q23: 2025-08-18 | R23: 320 | S23: 69904 | T23: 90048 | U23: 20144 | V23: 633 | W23: 0 | X23: 20144 | Y23: 0
A24: NIFTYBEES | B24: INF204KB14I2 | C24: 2023-11-24 | D24: 2025-08-18 | E24: 1 | F24: 218.45 | G24: 281.4 | H24: 62.95 | I24: 633 | J24: 0 | K24: 62.95 | L24: 0 | N24: NIFTYBEES | O24: INF204KB14I2 | P24: 2023-11-24 | Q24: 2025-08-18 | R24: 1 | S24: 218.45 | T24: 281.4 | U24: 62.95 | V24: 633 | W24: 0 | X24: 62.95 | Y24: 0
A25: NIFTYBEES | B25: INF204KB14I2 | C25: 2023-11-24 | D25: 2025-08-18 | E25: 178 | F25: 38884.1 | G25: 50089.2 | H25: 11205.1 | I25: 633 | J25: 0 | K25: 11205.1 | L25: 0 | N25: NIFTYBEES | O25: INF204KB14I2 | P25: 2023-11-24 | Q25: 2025-08-18 | R25: 178 | S25: 38884.1 | T25: 50089.2 | U25: 11205.1 | V25: 633 | W25: 0 | X25: 11205.1 | Y25: 0
A26: NIFTYBEES | B26: INF204KB14I2 | C26: 2023-11-24 | D26: 2025-08-18 | E26: 1 | F26: 218.45 | G26: 281.4 | H26: 62.95 | I26: 633 | J26: 0 | K26: 62.95 | L26: 0 | N26: NIFTYBEES | O26: INF204KB14I2 | P26: 2023-11-24 | Q26: 2025-08-18 | R26: 1 | S26: 218.45 | T26: 281.4 | U26: 62.95 | V26: 633 | W26: 0 | X26: 62.95 | Y26: 0
A27: NIFTYBEES | B27: INF204KB14I2 | C27: 2023-11-24 | D27: 2025-08-18 | E27: 1 | F27: 218.45 | G27: 281.4 | H27: 62.95 | I27: 633 | J27: 0 | K27: 62.95 | L27: 0 | N27: NIFTYBEES | O27: INF204KB14I2 | P27: 2023-11-24 | Q27: 2025-08-18 | R27: 1 | S27: 218.45 | T27: 281.4 | U27: 62.95 | V27: 633 | W27: 0 | X27: 62.95 | Y27: 0
... A40: NIFTYBEES | B40: INF204KB14I2 | C40: 2023-11-24 | D40: 2025-08-18 | E40: 70 | F40: 15291.5 | G40: 19698 | H40: 4406.5 | I40: 633 | J40: 0 | K40: 4406.5 | L40: 0 | N40: NIFTYBEES | O40: INF204KB14I2 | P40: 2023-11-24 | Q40: 2025-08-18 | R40: 70 | S40: 15291.5 | T40: 19698 | U40: 4406.5 | V40: 633 | W40: 0 | X40: 4406.5 | Y40: 0
A41: NIFTYBEES | B41: INF204KB14I2 | C41: 2023-11-24 | D41: 2025-08-19 | E41: 11 | F41: 2402.95 | G41: 3094.41 | H41: 691.46 | I41: 634 | J41: 0 | K41: 691.46 | L41: 0 | Q41: 18-08-2025 NIFTYBEES | S41: =SUM(S16:S40) -> 436900 | T41: =SUM(T16:T40) -> 562800 | U41: =SUM(U16:U40) -> 125900
A42: NIFTYBEES | B42: INF204KB14I2 | C42: 2023-11-24 | D42: 2025-08-19 | E42: 1 | F42: 218.45 | G42: 281.31 | H42: 62.86 | I42: 634 | J42: 0 | K42: 62.86 | L42: 0 | S42: Buy Value | T42: Sell Value | U42: P&L
A43: NIFTYBEES | B43: INF204KB14I2 | C43: 2023-11-24 | D43: 2025-08-19 | E43: 1 | F43: 218.45 | G43: 281.31 | H43: 62.86 | I43: 634 | J43: 0 | K43: 62.86 | L43: 0
A44: NIFTYBEES | B44: INF204KB14I2 | C44: 2023-11-24 | D44: 2025-08-19 | E44: 1 | F44: 218.45 | G44: 281.31 | H44: 62.86 | I44: 634 | J44: 0 | K44: 62.86 | L44: 0
A45: NIFTYBEES | B45: INF204KB14I2 | C45: 2023-11-24 | D45: 2025-08-19 | E45: 1 | F45: 218.45 | G45: 281.31 | H45: 62.86 | I45: 634 | J45: 0 | K45: 62.86 | L45: 0 | N45: NIFTYBEES SELL ON 19-08-2025
A46: NIFTYBEES | B46: INF204KB14I2 | C46: 2023-11-24 | D46: 2025-08-19 | E46: 1 | F46: 218.45 | G46: 281.31 | H46: 62.86 | I46: 634 | J46: 0 | K46: 62.86 | L46: 0
A47: NIFTYBEES | B47: INF204KB14I2 | C47: 2023-11-24 | D47: 2025-08-19 | E47: 1 | F47: 218.45 | G47: 281.31 | H47: 62.86 | I47: 634 | J47: 0 | K47: 62.86 | L47: 0 | N47: NIFTYBEES | O47: INF204KB14I2 | P47: 2023-11-24 | Q47: 2025-08-19 | R47: 11 | S47: 2402.95 | T47: 3094.41 | U47: 691.46 | V47: 634 | W47: 0 | X47: 691.46 | Y47: 0
A48: NIFTYBEES | B48: INF204KB14I2 | C48: 2023-11-24 | D48: 2025-08-19 | E48: 1 | F48: 218.45 | G48: 281.31 | H48: 62.86 | I48: 634 | J48: 0 | K48: 62.86 | L48: 0 | N48: NIFTYBEES | O48: INF204KB14I2 | P48: 2023-11-24 | Q48: 2025-08-19 | R48: 1 | S48: 218.45 | T48: 281.31 | U48: 62.86 | V48: 634 | W48: 0 | X48: 62.86 | Y48: 0
A49: NIFTYBEES | B49: INF204KB14I2 | C49: 2023-11-24 | D49: 2025-08-19 | E49: 1 | F49: 218.45 | G49: 281.31 | H49: 62.86 | I49: 634 | J49: 0 | K49: 62.86 | L49: 0 | N49: NIFTYBEES | O49: INF204KB14I2 | P49: 2023-11-24 | Q49: 2025-08-19 | R49: 1 | S49: 218.45 | T49: 281.31 | U49: 62.86 | V49: 634 | W49: 0 | X49: 62.86 | Y49: 0
A50: NIFTYBEES | B50: INF204KB14I2 | C50: 2023-11-24 | D50: 2025-08-19 | E50: 1 | F50: 218.45 | G50: 281.31 | H50: 62.86 | I50: 634 | J50: 0 | K50: 62.86 | L50: 0 | N50: NIFTYBEES | O50: INF204KB14I2 | P50: 2023-11-24 | Q50: 2025-08-19 | R50: 1 | S50: 218.45 | T50: 281.31 | U50: 62.86 | V50: 634 | W50: 0 | X50: 62.86 | Y50: 0
A51: NIFTYBEES | B51: INF204KB14I2 | C51: 2023-11-24 | D51: 2025-08-19 | E51: 12 | F51: 2621.4 | G51: 3375.72 | H51: 754.32 | I51: 634 | J51: 0 | K51: 754.32 | L51: 0 | N51: NIFTYBEES | O51: INF204KB14I2 | P51: 2023-11-24 | Q51: 2025-08-19 | R51: 1 | S51: 218.45 | T51: 281.31 | U51: 62.86 | V51: 634 | W51: 0 | X51: 62.86 | Y51: 0
A52: NIFTYBEES | B52: INF204KB14I2 | C52: 2023-11-24 | D52: 2025-08-19 | E52: 12 | F52: 2621.4 | G52: 3375.72 | H52: 754.32 | I52: 634 | J52: 0 | K52: 754.32 | L52: 0 | N52: NIFTYBEES | O52: INF204KB14I2 | P52: 2023-11-24 | Q52: 2025-08-19 | R52: 1 | S52: 218.45 | T52: 281.31 | U52: 62.86 | V52: 634 | W52: 0 | X52: 62.86 | Y52: 0
A53: NIFTYBEES | B53: INF204KB14I2 | C53: 2023-11-24 | D53: 2025-08-19 | E53: 128 | F53: 27961.6 | G53: 36007.68 | H53: 8046.08 | I53: 634 | J53: 0 | K53: 8046.08 | L53: 0 | N53: NIFTYBEES | O53: INF204KB14I2 | P53: 2023-11-24 | Q53: 2025-08-19 | R53: 1 | S53: 218.45 | T53: 281.31 | U53: 62.86 | V53: 634 | W53: 0 | X53: 62.86 | Y53: 0
A54: NIFTYBEES | B54: INF204KB14I2 | C54: 2023-11-24 | D54: 2025-08-19 | E54: 130 | F54: 28398.5 | G54: 36570.3 | H54: 8171.8 | I54: 634 | J54: 0 | K54: 8171.8 | L54: 0 | N54: NIFTYBEES | O54: INF204KB14I2 | P54: 2023-11-24 | Q54: 2025-08-19 | R54: 1 | S54: 218.45 | T54: 281.31 | U54: 62.86 | V54: 634 | W54: 0 | X54: 62.86 | Y54: 0
A55: NIFTYBEES | B55: INF204KB14I2 | C55: 2023-11-24 | D55: 2025-08-19 | E55: 13 | F55: 2839.85 | G55: 3657.03 | H55: 817.18 | I55: 634 | J55: 0 | K55: 817.18 | L55: 0 | N55: NIFTYBEES | O55: INF204KB14I2 | P55: 2023-11-24 | Q55: 2025-08-19 | R55: 1 | S55: 218.45 | T55: 281.31 | U55: 62.86 | V55: 634 | W55: 0 | X55: 62.86 | Y55: 0
A56: NIFTYBEES | B56: INF204KB14I2 | C56: 2023-11-24 | D56: 2025-08-19 | E56: 11 | F56: 2402.95 | G56: 3094.41 | H56: 691.46 | I56: 634 | J56: 0 | K56: 691.46 | L56: 0 | N56: NIFTYBEES | O56: INF204KB14I2 | P56: 2023-11-24 | Q56: 2025-08-19 | R56: 1 | S56: 218.45 | T56: 281.31 | U56: 62.86 | V56: 634 | W56: 0 | X56: 62.86 | Y56: 0
A57: NIFTYBEES | B57: INF204KB14I2 | C57: 2023-11-24 | D57: 2025-08-19 | E57: 9 | F57: 1966.05 | G57: 2531.79 | H57: 565.74 | I57: 634 | J57: 0 | K57: 565.74 | L57: 0 | N57: NIFTYBEES | O57: INF204KB14I2 | P57: 2023-11-24 | Q57: 2025-08-19 | R57: 12 | S57: 2621.4 | T57: 3375.72 | U57: 754.32 | V57: 634 | W57: 0 | X57: 754.32 | Y57: 0
A58: NIFTYBEES | B58: INF204KB14I2 | C58: 2023-11-24 | D58: 2025-08-19 | E58: 17 | F58: 3713.65 | G58: 4782.27 | H58: 1068.62 | I58: 634 | J58: 0 | K58: 1068.62 | L58: 0 | N58: NIFTYBEES | O58: INF204KB14I2 | P58: 2023-11-24 | Q58: 2025-08-19 | R58: 12 | S58: 2621.4 | T58: 3375.72 | U58: 754.32 | V58: 634 | W58: 0 | X58: 754.32 | Y58: 0
... A117: NIFTYBEES | B117: INF204KB14I2 | C117: 2023-11-24 | D117: 2025-08-19 | E117: 9 | F117: 1966.05 | G117: 2531.79 | H117: 565.74 | I117: 634 | J117: 0 | K117: 565.74 | L117: 0 | N117: NIFTYBEES | O117: INF204KB14I2 | P117: 2023-11-24 | Q117: 2025-08-19 | R117: 430 | S117: 93933.5 | T117: 120963.3 | U117: 27029.8 | V117: 634 | W117: 0 | X117: 27029.8 | Y117: 0
D118: Total Niftybees | F118: =SUM(F16:F117) -> 990015.4 | G118: =SUM(G16:G117) -> 1275076.9 | H118: =SUM(H16:H117) -> 285061.52 | N118: NIFTYBEES | O118: INF204KB14I2 | P118: 2023-11-24 | Q118: 2025-08-19 | R118: 8 | S118: 1747.6 | T118: 2250.48 | U118: 502.88 | V118: 634 | W118: 0 | X118: 502.88 | Y118: 0
F119: Buy Value | G119: Sell Value | H119: P&L | N119: NIFTYBEES | O119: INF204KB14I2 | P119: 2023-11-24 | Q119: 2025-08-19 | R119: 8 | S119: 1747.6 | T119: 2250.48 | U119: 502.88 | V119: 634 | W119: 0 | X119: 502.88 | Y119: 0
N120: NIFTYBEES | O120: INF204KB14I2 | P120: 2023-11-24 | Q120: 2025-08-19 | R120: 8 | S120: 1747.6 | T120: 2250.48 | U120: 502.88 | V120: 634 | W120: 0 | X120: 502.88 | Y120: 0
A121: HDFC SELL ON 21-08-2025 | N121: NIFTYBEES | O121: INF204KB14I2 | P121: 2023-11-24 | Q121: 2025-08-19 | R121: 84 | S121: 18349.8 | T121: 23630.04 | U121: 5280.24 | V121: 634 | W121: 0 | X121: 5280.24 | Y121: 0
N122: NIFTYBEES | O122: INF204KB14I2 | P122: 2023-11-24 | Q122: 2025-08-19 | R122: 88 | S122: 19223.6 | T122: 24755.28 | U122: 5531.68 | V122: 634 | W122: 0 | X122: 5531.68 | Y122: 0
A123: Symbol | B123: Quantity | C123: Buy Value | D123: Sell Value | E123: Realized P&L | N123: NIFTYBEES | O123: INF204KB14I2 | P123: 2023-11-24 | Q123: 2025-08-19 | R123: 9 | S123: 1966.05 | T123: 2531.79 | U123: 565.74 | V123: 634 | W123: 0 | X123: 565.74 | Y123: 0
A124: HDFC INDEX NIFTY 50 PLAN - DIRECT PLAN | B124: 2475.15 | C124: 492390.25 | D124: 602749.52 | E124: 110359.27 | Q124: 19-08-2025 NIFTYBEES | S124: =SUM(S47:S123) -> 553115.4 | T124: =SUM(T47:T123) -> 712276.92 | U124: =SUM(U47:U123) -> 159161.52
S125: Buy Value | T125: Sell Value | U125: P&L

Sheet Debt funds
A1: Debt funds: | B1: UPDATE 20 AUG 2025 - IMPORTANT: SBI LIQUID FUND BOUGHT ON 13 MAR 2023 (REMAINING 31.140 UNITS FROM THE DAY-SEE COIN/CONSOLE) ELIGIBLE FOR LTCG 12.5%. ALL OTHER DEBT FUND UNITS WILL BE TAXED AT SLAB RATE AS THEY WERE BOUGHT AFTER 1 APR 2023
A2: Symbol | B2: ISIN | C2: Trade Date | D2: Exchange | E2: Segment | F2: Series | G2: Trade Type | H2: Auction | I2: Quantity | J2: Price | K2: Trade ID | L2: Order ID | M2: Order Execution Time
Q3: https://freefincal.com/budget-2024-faq-on-capital-gains-taxation | X3: https://freefincal.com/budget-2024-capital-gains-taxation-guide
A4: AXIS OVERNIGHT FUND - DIRECT PLAN | B4: INF846K01N65 | C4: 2021-12-14 | D4: BSE | E4: MF | G4: buy | H4: FALSE | I4: 89.882 | J4: 1112.5091 | K4: 339356160 | L4: 339356160 | M4: 2021-12-14T00:00:00 | O4: ='Debt funds'!I4*'Debt funds'!J4 -> 99994.543 | Q4: FY 2024-25 (downloaded from "Tax P&L" page for financial year) | Y4: https://www.youtube.com/shorts/e-GhGb7-5ek
A5: AXIS OVERNIGHT FUND - DIRECT PLAN | B5: INF846K01N65 | C5: 2021-12-15 | D5: BSE | E5: MF | G5: buy | H5: FALSE | I5: 130.318 | J5: 1112.6082 | K5: 340893986 | L5: 340893986 | M5: 2021-12-15T00:00:00 | O5: ='Debt funds'!I5*'Debt funds'!J5 -> 144992.88 | Q5: Symbol | R5: Quantity | S5: Buy Value | T5: Sell Value | U5: Realized P&L
A6: AXIS OVERNIGHT FUND - DIRECT PLAN | B6: INF846K01N65 | C6: 2022-01-31 | D6: BSE | E6: MF | G6: buy | H6: FALSE | I6: 894.647 | J6: 1117.7033 | K6: 366357093 | L6: 366357093 | M6: 2022-01-31T00:00:00 | O6: ='Debt funds'!I6*'Debt funds'!J6 -> 999949.9 | Q6: AXIS OVERNIGHT FUND - DIRECT PLAN | R6: 1114.847 | S6: 1244937.3 | T6: 1451204.7 | U6: 206267.38
A7: Total | I7: =SUM(I4:I6) -> 1114.847 | O7: =SUM(O4:O6) -> 1244937.3 | Q7: SBI LIQUID FUND - DIRECT PLAN | R7: 254 | S7: 890690.91 | T7: 998969.12 | U7: 108278.21
Q8: NIPPON INDIA OVERNIGHT FUND - DIRECT PLAN | R8: 7005.318 | S8: 799959.99 | T8: 926005.67 | U8: 126045.67
A9: AXIS OVERNIGHT FUND - DIRECT PLAN | B9: INF846K01N65 | C9: 2024-08-30 | D9: BSE | E9: MF | G9: sell | H9: FALSE | I9: 1114.847 | J9: 1301.7075 | K9: 1338237118 | L9: 1338237118 | M9: 2024-08-30T00:00:00 | O9: ='Debt funds'!I9*'Debt funds'!J9 -> 1451204.7
N10: Profit | O10: =O9-O7 -> 206267.38 | Q10: Mutual Funds
A12: NIPPON INDIA OVERNIGHT FUND - DIRECT PLAN | B12: INF204KB1R31 | C12: 2022-04-06 | D12: BSE | E12: MF | G12: buy | H12: FALSE | I12: 87.582 | J12: 114.1731 | K12: 409232356 | L12: 409232356 | M12: 2022-04-06T00:00:00 | O12: =I12*J12 -> 9999.5084 | Q12: Symbol | R12: ISIN | S12: Entry Date | T12: Exit Date | U12: Quantity | V12: Buy Value | W12: Sell Value | X12: Profit | Y12: Period of Holding | Z12: Fair Market Value | AA12: Long Term Profit | AB12: Taxable Profit | AC12: Turnover | AE12: buy value | AF12: sell value
A13: NIPPON INDIA OVERNIGHT FUND - DIRECT PLAN | B13: INF204KB1R31 | C13: 2022-04-08 | D13: BSE | E13: MF | G13: buy | H13: FALSE | I13: 6917.736 | J13: 114.1935 | K13: 410647903 | L13: 410647903 | M13: 2022-04-08T00:00:00 | O13: =I13*J13 -> 789960.49 | Q13: AXIS OVERNIGHT FUND - DIRECT PLAN | R13: INF846K01N65 | S13: 2021-12-14 | T13: 2024-08-30 | U13: 89.882 | V13: 99994.543 | W13: 117000.07 | X13: 17005.531 | Y13: 990 | Z13: 0 | AA13: 17005.531 | AB13: 17005.531 | AC13: 0 | AD13: LTCG | AE13: 2044897 | AF13: 2377210
A14: Total | I14: =SUM(I12:I13) -> 7005.318 | O14: =SUM(O12:O13) -> 799959.99 | Q14: AXIS OVERNIGHT FUND - DIRECT PLAN | R14: INF846K01N65 | S14: 2021-12-15 | T14: 2024-08-30 | U14: 130.318 | V14: 144992.88 | W14: 169635.92 | X14: 24643.043 | Y14: 989 | Z14: 0 | AA14: 24643.043 | AB14: 24643.043 | AC14: 0 | AD14: LTCG
Q15: AXIS OVERNIGHT FUND - DIRECT PLAN | R15: INF846K01N65 | S15: 2022-01-31 | T15: 2024-08-30 | U15: 894.647 | V15: 999949.9 | W15: 1164568.7 | X15: 164618.81 | Y15: 942 | Z15: 0 | AA15: 164618.81 | AB15: 164618.81 | AC15: 0 | AD15: LTCG
A16: NIPPON INDIA OVERNIGHT FUND - DIRECT PLAN | B16: INF204KB1R31 | C16: 2024-09-03 | D16: BSE | E16: MF | G16: sell | H16: FALSE | I16: 7005.318 | J16: 132.1861 | K16: 1347289347 | L16: 1347289347 | M16: 2024-09-03T00:00:00 | O16: ='Debt funds'!I16*'Debt funds'!J16 -> 926005.67 | P16: =O9+O16 -> 2377210.4 | Q16: NIPPON INDIA OVERNIGHT FUND - DIRECT PLAN | R16: INF204KB1R31 | S16: 2022-04-06 | T16: 2024-09-03 | U16: 87.582 | V16: 9999.5084 | W16: 11577.123 | X16: 1577.6146 | Y16: 881 | Z16: 0 | AA16: 1577.6146 | AB16: 1577.6146 | AC16: 0 | AD16: LTCG
N17: Profit | O17: =O16-O14 -> 126045.67 | Q17: NIPPON INDIA OVERNIGHT FUND - DIRECT PLAN | R17: INF204KB1R31 | S17: 2022-04-08 | T17: 2024-09-03 | U17: 6917.736 | V17: 789960.49 | W17: 914428.54 | X17: 124468.06 | Y17: 879 | Z17: 0 | AA17: 124468.06 | AB17: 124468.06 | AC17: 0 | AD17: LTCG
Q18: SBI LIQUID FUND - DIRECT PLAN | R18: INF200K01UT4 | S18: 2023-03-08 | T18: 2024-10-23 | U18: 28.531 | V18: 99996.019 | W18: 112210.98 | X18: 12214.957 | Y18: 595 | Z18: 0 | AA18: 12214.957 | AB18: 12214.957 | AC18: 0 | AD18: STCG | AE18: 890690.91 | AF18: 998969.12
A19: SBI LIQUID FUND - DIRECT PLAN | B19: INF200K01UT4 | C19: 2023-03-08 | D19: BSE | E19: MF | G19: buy | H19: FALSE | I19: 28.531 | J19: 3504.82 | K19: 649485281 | L19: 649485281 | M19: 2023-03-08T00:00:00 | O19: ='Debt funds'!I19*'Debt funds'!J19 -> 99996.019 | Q19: SBI LIQUID FUND - DIRECT PLAN | R19: INF200K01UT4 | S19: 2023-03-09 | T19: 2024-10-23 | U19: 57.051 | V19: 199989.09 | W19: 224378.69 | X19: 24389.599 | Y19: 594 | Z19: 0 | AA19: 24389.599 | AB19: 24389.599 | AC19: 0 | AD19: STCG
A20: SBI LIQUID FUND - DIRECT PLAN | B20: INF200K01UT4 | C20: 2023-03-09 | D20: BSE | E20: MF | G20: buy | H20: FALSE | I20: 57.051 | J20: 3505.4441 | K20: 651803682 | L20: 651803682 | M20: 2023-03-09T00:00:00 | O20: ='Debt funds'!I20*'Debt funds'!J20 -> 199989.09 | Q20: SBI LIQUID FUND - DIRECT PLAN | R20: INF200K01UT4 | S20: 2023-03-10 | T20: 2024-10-23 | U20: 85.559 | V20: 299984.18 | W20: 336499.21 | X20: 36515.033 | Y20: 593 | Z20: 0 | AA20: 36515.033 | AB20: 36515.033 | AC20: 0 | AD20: STCG
A21: SBI LIQUID FUND - DIRECT PLAN | B21: INF200K01UT4 | C21: 2023-03-10 | D21: BSE | E21: MF | G21: buy | H21: FALSE | I21: 85.559 | J21: 3506.1674 | K21: 654835097 | L21: 654835097 | M21: 2023-03-10T00:00:00 | O21: ='Debt funds'!I21*'Debt funds'!J21 -> 299984.18 | Q21: SBI LIQUID FUND - DIRECT PLAN | R21: INF200K01UT4 | S21: 2023-03-13 | T21: 2024-10-23 | U21: 82.859 | V21: 290721.62 | W21: 325880.25 | X21: 35158.623 | Y21: 590 | Z21: 0 | AA21: 35158.623 | AB21: 35158.623 | AC21: 0 | AD21: STCG
A22: SBI LIQUID FUND - DIRECT PLAN | B22: INF200K01UT4 | C22: 2023-03-13 | D22: BSE | E22: MF | G22: buy | H22: FALSE | I22: 113.999 | J22: 3508.6306 | K22: 656446502 | L22: 656446502 | M22: 2023-03-13T00:00:00 | O22: ='Debt funds'!I22*'Debt funds'!J22 -> 399980.38
A23: SBI LIQUID FUND - DIRECT PLAN | B23: INF200K01UT4 | C23: 2023-04-05 | D23: BSE | E23: MF | G23: buy | H23: FALSE | I23: 113.428 | J23: 3526.2771 | K23: 675569509 | L23: 675569509 | M23: 2023-04-05T00:00:00 | O23: ='Debt funds'!I23*'Debt funds'!J23 -> 399978.56 | Q23: For debt funds: If you have purchased units on or before March 31st 2023, and sold after July 23rd 2024, you will be taxed at 12.5% without indexation if the duration of holding is > 2Y.
A24: SBI LIQUID FUND - DIRECT PLAN | B24: INF200K01UT4 | C24: 2023-05-03 | D24: BSE | E24: MF | G24: buy | H24: FALSE | I24: 56.419 | J24: 3544.7173 | K24: 699224127 | L24: 699224127 | M24: 2023-05-03T00:00:00 | O24: ='Debt funds'!I24*'Debt funds'!J24 -> 199989.41 | Q24: LTCG | R24: =O10+O17 -> 332313.05 | S24: STCG | T24: =P31 -> 108278.21 | V24: Total Withdrawn | W24: =O9+O16+O31 -> 3376179.5
A25: SBI LIQUID FUND - DIRECT PLAN | B25: INF200K01UT4 | C25: 2023-06-06 | D25: BSE | E25: MF | G25: buy | H25: FALSE | I25: 70.064 | J25: 3568.009 | K25: 730139385 | L25: 730139385 | M25: 2023-06-06T00:00:00 | O25: ='Debt funds'!I25*'Debt funds'!J25 -> 249988.98 | Q25: Tax Rate | R25: 0.125 | S25: Tax Rate | T25: 0.3
A26: SBI LIQUID FUND - DIRECT PLAN | B26: INF200K01UT4 | C26: 2023-07-03 | D26: BSE | E26: MF | G26: buy | H26: FALSE | I26: 278.904 | J26: 3585.2899 | K26: 756008118 | L26: 756008118 | M26: 2023-07-03T00:00:00 | O26: ='Debt funds'!I26*'Debt funds'!J26 -> 999951.69 | Q26: Tax | R26: =R24*R25 -> 41539.131 | S26: Tax | T26: =T24*T25 -> 32483.464 | U26: Total Tax | V26: =R26+T26 -> 74022.595
A27: SBI LIQUID FUND - DIRECT PLAN | B27: INF200K01UT4 | C27: 2023-07-04 | D27: BSE | E27: MF | G27: buy | H27: FALSE | I27: 278.823 | J27: 3586.3204 | K27: 757050809 | L27: 757050809 | M27: 2023-07-04T00:00:00 | O27: ='Debt funds'!I27*'Debt funds'!J27 -> 999948.61 | R27: AXIS+NIPPON | T27: SBI
A28: SBI LIQUID FUND - DIRECT PLAN | B28: INF200K01UT4 | C28: 2023-07-31 | D28: BSE | E28: MF | G28: buy | H28: FALSE | I28: 138.725 | J28: 3604.0747 | K28: 782283371 | L28: 782283371 | M28: 2023-07-31T00:00:00 | O28: ='Debt funds'!I28*'Debt funds'!J28 -> 499975.26
A29: SBI LIQUID FUND - DIRECT PLAN | B29: INF200K01UT4 | C29: 2023-08-01 | D29: BSE | E29: MF | G29: buy | H29: FALSE | I29: 124.829 | J29: 3604.7451 | K29: 785053360 | L29: 785053360 | M29: 2023-08-01T00:00:00 | O29: ='Debt funds'!I29*'Debt funds'!J29 -> 449976.73
I30: =SUM(I19:I29) -> 1346.332 | O30: =SUM(O19:O29) -> 4799758.9
A31: SBI LIQUID FUND - DIRECT PLAN | B31: INF200K01UT4 | C31: 2024-10-23 | D31: BSE | E31: MF | G31: sell | H31: FALSE | I31: 254 | J31: 3932.9493 | K31: 1445384151 | L31: 1445384151 | M31: 2024-10-23T00:00:00 | O31: =I31*J31 -> 998969.12 | P31: 108278.21
A34: UTI LIQUID FUND - CASH PLAN - DIRECT PLAN | B34: INF789F01XQ6 | C34: 2023-07-03 | D34: BSE | E34: MF | G34: buy | H34: FALSE | I34: 0.133 | J34: 3754.5897 | K34: 756008808 | L34: 756008808 | M34: 2023-07-03T00:00:00 | O34: ='Debt funds'!I34*'Debt funds'!J34 -> 499.36043
A35: UTI LIQUID FUND - CASH PLAN - DIRECT PLAN | B35: INF789F01XQ6 | C35: 2023-07-10 | D35: BSE | E35: MF | G35: buy | H35: FALSE | I35: 239.348 | J35: 3760.0253 | K35: 766280383 | L35: 766280383 | M35: 2023-07-10T00:00:00 | O35: ='Debt funds'!I35*'Debt funds'!J35 -> 899954.54
A36: UTI LIQUID FUND - CASH PLAN - DIRECT PLAN | B36: INF789F01XQ6 | C36: 2023-07-19 | D36: BSE | E36: MF | G36: buy | H36: FALSE | I36: 265.502 | J36: 3766.2552 | K36: 773862615 | L36: 773862615 | M36: 2023-07-19T00:00:00 | O36: ='Debt funds'!I36*'Debt funds'!J36 -> 999948.29
A37: UTI LIQUID FUND - CASH PLAN - DIRECT PLAN | B37: INF789F01XQ6 | C37: 2023-07-26 | D37: BSE | E37: MF | G37: buy | H37: FALSE | I37: 265.165 | J37: 3771.0425 | K37: 779704671 | L37: 779704671 | M37: 2023-07-26T00:00:00 | O37: ='Debt funds'!I37*'Debt funds'!J37 -> 999948.48
A38: UTI LIQUID FUND - CASH PLAN - DIRECT PLAN | B38: INF789F01XQ6 | C38: 2023-08-01 | D38: BSE | E38: MF | G38: buy | H38: FALSE | I38: 105.951 | J38: 3775.1541 | K38: 785052145 | L38: 785052145 | M38: 2023-08-01T00:00:00 | O38: ='Debt funds'!I38*'Debt funds'!J38 -> 399981.35
I39: =SUM(I34:I38) -> 876.099 | O39: =SUM(O34:O38) -> 3300332
A42: SBI SAVINGS FUND - DIRECT PLAN | B42: INF200K01SZ5 | C42: 2023-09-01 | D42: BSE | E42: MF | G42: buy | H42: FALSE | I42: 14191.301 | J42: 38.7542 | K42: 817615373 | L42: 817615373 | M42: 2023-09-01T00:00:00 | O42: ='Debt funds'!I42*'Debt funds'!J42 -> 549972.52
A43: SBI SAVINGS FUND - DIRECT PLAN | B43: INF200K01SZ5 | C43: 2023-10-03 | D43: BSE | E43: MF | G43: buy | H43: FALSE | I43: 8975.913 | J43: 38.9913 | K43: 853777826 | L43: 853777826 | M43: 2023-10-03T00:00:00 | O43: ='Debt funds'!I43*'Debt funds'!J43 -> 349982.52
A44: SBI SAVINGS FUND - DIRECT PLAN | B44: INF200K01SZ5 | C44: 2023-10-09 | D44: BSE | E44: MF | G44: buy | H44: FALSE | I44: 2561.741 | J44: 39.034 | K44: 862004684 | L44: 862004684 | M44: 2023-10-09T00:00:00 | O44: ='Debt funds'!I44*'Debt funds'!J44 -> 99994.998
A45: SBI SAVINGS FUND - DIRECT PLAN | B45: INF200K01SZ5 | C45: 2023-10-12 | D45: BSE | E45: MF | G45: buy | H45: FALSE | I45: 23043.272 | J45: 39.055 | K45: 866938730 | L45: 866938730 | M45: 2023-10-12T00:00:00 | O45: ='Debt funds'!I45*'Debt funds'!J45 -> 899954.99
A46: SBI SAVINGS FUND - DIRECT PLAN | B46: INF200K01SZ5 | C46: 2023-11-03 | D46: BSE | E46: MF | G46: buy | H46: FALSE | I46: 12751.374 | J46: 39.2095 | K46: 889695877 | L46: 889695877 | M46: 2023-11-03T00:00:00 | O46: ='Debt funds'!I46*'Debt funds'!J46 -> 499975
I47: =SUM(I42:I46) -> 61523.601 | O47: =SUM(O42:O46) -> 2399880
A50: TATA MONEY MARKET FUND - DIRECT PLAN | B50: INF277K01PR6 | C50: 2024-06-28 | D50: BSE | E50: MF | G50: buy | H50: FALSE | I50: 224.829 | J50: 4447.5966 | K50: 1232134886 | L50: 1232134886 | M50: 2024-06-28T00:00:00 | O50: ='Debt funds'!I50*'Debt funds'!J50 -> 999948.7

Sheet covered call
A1: Slab | B1: Date | C1: Instru | D1: Qty | E1: Entry | F1: Nifty at Entry | G1: Amount invested | I1: Date | J1: Equity Profit | L1: Expiry | M1: CC P&L | N1: Put Bfly P&L | O1: Total | P1: Cum CC P&L | Q1: Equity booked P&L | R1: Cum Total PnL | S1: Total Invested | T1: Current Value
A2: 1 | B2: 45254.438 | C2: NIFTYBEES | D2: 4532 | E2: 218.45 | F2: 19800 | G2: =D2*E2 -> 990015.4 | I2: 45887 | J2: 285061.52 | L2: 45288 | M2: -116595 | N2: 0 | O2: =M2+N2 -> -116595 | P2: =SUM(O2:O46) -> 94650.45 | Q2: =SUM(J2:J24) -> 395420.79 | R2: =P2+Q2+S26 -> 1716804.4 | S2: =D25 -> 9831365.4 | T2: =S6*U6+S7*U7+S8*U8+S9*U9+S10*U10 -> 9624124.8
A3: 2 | B3: 45265.646 | C3: HDFC Index Nifty 50 Plan | D3: 5202.483 | E3: 198.9335 | F3: 20850 | G3: =D3*E3 -> 1034948.2 | I3: 45890 | J3: 110359.27 | L3: 45292 | M3: 71662.5 | N3: 0 | O3: =M3+N3 -> 71662.5 | X3: 45590
A4: 3 | B4: 45289.646 | C4: HDFC Index Nifty 50 Plan | D4: 5234.832 | E4: 207.2551 | F4: 21750 | G4: =D4*E4 -> 1084945.6 | L4: 45323 | M4: 600 | N4: -4532.55 | O4: =M4+N4 -> -3932.55 | R4: Nifty P&L (only nifty, not CC and P-bfly) | X4: nifty | Y4: hdfc | AA4: icici | AC4: niftybees
A5: 4 | B5: 45309.646 | C5: HDFC Index Nifty 50 Plan | D5: 5227.692 | E5: 204.669 | F5: 21450 | G5: =D5*E5 -> 1069946.5 | L5: 45352 | M5: 25648 | N5: -692.5 | O5: =M5+N5 -> 24955.5 | R5: fund | S5: qty | T5: Entry | U5: LTP | V5: pnl | X5: 24118.25 | Y5: 234.501 | Z5: =Y5/X5 -> 0.0097229691 | AA5: 253.519 | AB5: =AA5/X5 -> 0.010511501 | AC5: 269.2 | AD5: =AC5/X5 -> 0.011161672
A6: 5 | B6: 45315.646 | C6: ICICI Prudential Nifty 50 Index Fund | D6: 4836.062 | E6: 221.2847 | F6: 21400 | G6: =D6*E6 -> 1070146.5 | L6: 45365 | M6: -1090 | N6: 0 | O6: =M6+N6 -> -1090 | R6: hdfc index | S6: 15791 | T6: 209.45 | U6: 245.922 | V6: =(U6-T6)*S6 -> 575929.35 | X6: 24399.4 | Y6: 234.849 | Z6: =Y6/X6 -> 0.0096251957 | AA6: 253.895 | AB6: =AA6/X6 -> 0.010405789 | AC6: 272.12 | AD6: =AC6/X6 -> 0.011152733
A7: 6 | B7: 45323.646 | C7: ICICI Prudential Nifty 50 Index Fund | D7: 4845.491 | E7: 224 | F7: 21700 | G7: =D7*E7 -> 1085390 | L7: 45372 | M7: 69426 | N7: -5767.5 | O7: =M7+N7 -> 63658.5 | R7: icici index | S7: 14507.191 | T7: 223.34 | U7: 265.829 | V7: =(U7-T7)*S7 -> 616396.04 | X7: 24435.5 | Y7: 235.202 | Z7: =Y7/X7 -> 0.009625422 | AA7: 254.277 | AB7: =AA7/X7 -> 0.010406049 | AC7: 273.09 | AD7: =AC7/X7 -> 0.011175953
A8: 7 | B8: 45331.646 | C8: ICICI Prudential Nifty 50 Index Fund | D8: 4825.638 | E8: 224.8295 | F8: 21800 | G8: =D8*E8 -> 1084945.8 | L8: 45379 | M8: -23625 | N8: 0 | O8: =M8+N8 -> -23625 | R8: niftybees | S8: 0 | T8: 0 | U8: 0 | V8: =(U8-T8)*S8 -> 0 | X8: 24472.1 | Y8: 238.145 | Z8: =Y8/X8 -> 0.0097312858 | AA8: 257.457 | AB8: =AA8/X8 -> 0.010520429 | AC8: 273.56 | AD8: =AC8/X8 -> 0.011178444
A9: 8 | B9: 45589.646 | C9: HDFC Index Nifty 50 Plan | D9: 2601.143 | E9: 234.5006 | F9: 24400 | G9: =D9*E9 -> 609969.59 | L9: 45407 | M9: 57010 | O9: =M9+N9 -> 57010 | R9: MO Mid | S9: 8395.423 | T9: 119.11 | U9: 121.885 | V9: =(U9-T9)*S9 -> 23297.299 | X9: 24781.1 | Y9: 238.85 | Z9: =Y9/X9 -> 0.0096383938 | AA9: 258.219 | AB9: =AA9/X9 -> 0.010419997 | AC9: 276.47 | AD9: =AC9/X9 -> 0.011156486
A10: 9 | C10: Motilal Oswal Midcap Fund | L10: 45442 | M10: 9403 | O10: =M10+N10 -> 9403 | R10: HDFC Mid | S10: 3963.773 | T10: 214.43 | U10: 217.233 | V10: =(U10-T10)*S10 -> 11110.456
A11: 10 | C11: HDFC Mid Cap Fund | L11: 45470 | M11: -172042.5 | N11: =45698-30919 -> 14779 | O11: =M11+N11 -> -157263.5
L12: 45498 | M12: 27431 | O12: =M12+N12 -> 27431
L13: 45533 | M13: -32483 | O13: =M13+N13 -> -32483
L14: 45561 | M14: -88411 | O14: =M14+N14 -> -88411
D15: Invested Amount | L15: 45596 | M15: 55588 | O15: =M15+N15 -> 55588
C16: NIFTYBEES | D16: 0 | L16: 45624 | M16: 1815 | O16: =M16+N16 -> 1815
C17: HDFC NIFTY50 INDEX FUND | D17: 3307420.2 | F17: SHOULD HAVE 50% ALLOCATION IN LARGE CAP(NIFTY 50) | L17: 45652 | M17: =-16703+14526 -> -2177 | O17: =M17+N17 -> -2177
C18: ICICI PRU NIFTY 50 INDEX FUND | D18: 3240037.5 | F18: AND 50% IN MID CAP | L18: 45687 | M18: 6787 | O18: =M18+N18 -> 6787 | R18: HDFC Profit | S18: =S6*(U6-T6) -> 575929.35
C19: Motilal Oswal Midcap Fund | D19: 999950.29 | L19: 45716 | M19: 19630 | O19: =M19+N19 -> 19630 | R19: ICICI Profit | S19: =S7*(U7-T7) -> 616396.04
C20: HDFC Mid Cap Fund | D20: 849957.39 | F20: LARGE CAP (50%) - NIFTY 50 INDEX FUND, PARAG PARIKH FLEXI, HDFC FLEXI | L20: 45743 | M20: -131 | O20: =M20+N20 -> -131 | R20: NFBEES Profit | S20: =S8*(U8-T8) -> 0
C21: Stocks | D21: 1434000 | F21: MID CAP (50%) - MIDCAP 150 INDEX FUND, MO MID, HDFC MID | L21: 45779 | M21: 0 | O21: =M21+N21 -> 0 | R21: MO Mid Profit | S21: =S9*(U9-T9) -> 23297.299
F22: CAN ALSO CONSIDER LARGE MIDCAP 250 TO DIVIDE BETWEEN LARGE CAP AND MIDCAP ALLOC | L22: 45796 | M22: -16113 | O22: =M22+N22 -> -16113 | R22: HDFC Mid Profit | S22: =S10*(U10-T10) -> 11110.456
L23: 45813 | M23: 34368 | O23: =M23+N23 -> 34368
L24: 45853 | M24: 42033 | O24: =M24+N24 -> 42033
C25: Invested | D25: =SUM(D16:D24) -> 9831365.4 | F25: Large cap | G25: =D17+D18 -> 6547457.7 | L25: 45861 | M25: -67132 | O25: =M25+N25 -> -67132
F26: Mid cap | G26: =D19+D20+D21 -> 3283907.7 | L26: 45868 | M26: 34650 | O26: =M26+N26 -> 34650 | R26: Index Profit | S26: =SUM(S18:S25) -> 1226733.1
L27: 45902 | M27: 31893 | O27: =M27+N27 -> 31893
L28: 45935 | M28: 16612 | O28: =M28+N28 -> 16612
L29: 45985 | M29: -3622 | O29: =M29+N29 -> -3622
L30: 45986 | M30: 5850 | O30: =M30+N30 -> 5850
L31: 45993 | M31: 12862 | O31: =M31+N31 -> 12862
L32: 46003 | M32: -19294 | O32: =M32+N32 -> -19294
L33: 46003 | M33: 22650 | O33: =M33+N33 -> 22650
L34: 46022 | M34: 16009 | O34: =M34+N34 -> 16009
L35: 46049 | M35: 25090 | O35: =M35+N35 -> 25090
L36: 46052 | M36: 5800 | O36: =M36+N36 -> 5800
L37: 46077 | M37: 13365 | O37: =M37+N37 -> 13365
L38: 46148 | M38: 27397 | O38: =M38+N38 -> 27397
O39: =M39+N39 -> 0
O40: =M40+N40 -> 0
O41: =M41+N41 -> 0
O42: =M42+N42 -> 0
O43: =M43+N43 -> 0
O44: =M44+N44 -> 0
O45: =M45+N45 -> 0
O46: =M46+N46 -> 0

Sheet month wise 2024-25
B1: April | D1: 22200000 | L1: June | N1: 22200000 | V1: August | X1: 22200000 | AG1: October | AI1: 21000000 | AQ1: December | AS1: 21000000 | BA1: February | BC1: 21000000
B2: week1 | C2: 11906 | D2: =C2*100/D$1 -> 0.053630631 | E2: =SUM(C2:C6) -> 36786 | F2: =E2*100/D1 -> 0.1657027 | G2: ani sal | H2: 172000 | L2: week1 | N2: =M2*100/N$1 -> 0 | O2: =SUM(M2:M6) -> 22421 | P2: =O2*100/N1 -> 0.1009955 | Q2: ani sal | R2: 172000 | V2: week1 | X2: =W2*100/X$1 -> 0 | Y2: =SUM(W2:W6) -> 11365 | Z2: =Y2*100/X1 -> 0.051193694 | AA2: ani sal | AB2: 192000 | AG2: week1 | AI2: =AH2*100/AI$1 -> 0 | AJ2: =SUM(AH2:AH6) -> 59807 | AK2: =AJ2*100/AI1 -> 0.28479524 | AL2: ani sal | AM2: 194000 | AQ2: week1 | AS2: =AR2*100/AS$1 -> 0 | AT2: =SUM(AR2:AR6) -> 12303 | AU2: =AT2*100/AS1 -> 0.058585714 | AV2: ani sal | AW2: 194000 | BA2: week1 | BB2: -2115 | BC2: =BB2*100/BC$1 -> -0.010071429 | BD2: =SUM(BB2:BB6) -> 19494 | BE2: =BD2*100/BC1 -> 0.092828571 | BF2: ani sal | BG2: 238000
C3: 5402 | D3: =C3*100/D$1 -> 0.024333333 | G3: amr sal | H3: 131000 | M3: 13104 | N3: =M3*100/N$1 -> 0.059027027 | Q3: amr sal | R3: 70000 | X3: =W3*100/X$1 -> 0 | AA3: amr sal | AB3: 70000 | AH3: 32543 | AI3: =AH3*100/AI$1 -> 0.15496667 | AL3: amr sal | AM3: 145000 | AS3: =AR3*100/AS$1 -> 0 | AV3: amr sal | AW3: 83000 | BB3: 10260 | BC3: =BB3*100/BC$1 -> 0.048857143 | BF3: amr sal | BG3: 86000
C4: 11065 | D4: =C4*100/D$1 -> 0.049842342 | G4: p | H4: =C29 -> 9920 | M4: -1768 | N4: =M4*100/N$1 -> -0.007963964 | Q4: p | R4: =M29 -> 163246 | X4: =W4*100/X$1 -> 0 | AA4: p | AB4: =W29 -> 117564 | AI4: =AH4*100/AI$1 -> 0 | AL4: p | AM4: =AH29 -> 182871 | AS4: =AR4*100/AS$1 -> 0 | AV4: p | AW4: =AR29 -> 108694 | BB4: 11349 | BC4: =BB4*100/BC$1 -> 0.054042857 | BF4: p | BG4: =BB29 -> 86164
C5: 1364 | D5: =C5*100/D$1 -> 0.0061441441 | G5: nf strategy | H5: 138157.92 | M5: 11085 | N5: =M5*100/N$1 -> 0.049932432 | Q5: nf strategy | R5: 455903.73 | W5: 11365 | X5: =W5*100/X$1 -> 0.051193694 | AA5: nf strategy | AB5: 243490.16 | AH5: =11453+8167 -> 19620 | AI5: =AH5*100/AI$1 -> 0.093428571 | AL5: nf strategy | AM5: 55588 | AR5: -3494 | AS5: =AR5*100/AS$1 -> -0.016638095 | AV5: nf strategy | AW5: -2177 | BC5: =BB5*100/BC$1 -> 0 | BF5: nf strategy | BG5: =5250+14380 -> 19630
C6: 7049 | D6: =C6*100/D$1 -> 0.031752252 | G6: int | H6: 79000 | I6: market total | J6: =H4+H5+H6 -> 227077.92 | N6: =M6*100/N$1 -> 0 | Q6: int | R6: 79000 | S6: market total | T6: =R4+R5+R6 -> 698149.73 | X6: =W6*100/X$1 -> 0 | AA6: int | AB6: 85000 | AC6: market total | AD6: =AB4+AB5+AB6 -> 446054.16 | AH6: 7644 | AI6: =AH6*100/AI$1 -> 0.0364 | AL6: int | AM6: 70000 | AN6: market total | AO6: =AM4+AM5+AM6 -> 308459 | AR6: 15797 | AS6: =AR6*100/AS$1 -> 0.07522381 | AV6: int | AW6: 70000 | AX6: market total | AY6: =AW4+AW5+AW6 -> 176517 | BC6: =BB6*100/BC$1 -> 0 | BF6: int | BG6: 65000 | BH6: market total | BI6: =BG4+BG5+BG6 -> 170794
B7: week2 | C7: 1243 | D7: =C7*100/D$1 -> 0.0055990991 | E7: =SUM(C7:C11) -> -55806 | F7: =E7*100/D1 -> -0.25137838 | G7: total | H7: =SUM(H2:H6) -> 530077.92 | L7: week2 | M7: 1330 | N7: =M7*100/N$1 -> 0.005990991 | O7: =SUM(M7:M11) -> 26892 | P7: =O7*100/N1 -> 0.12113514 | Q7: total | R7: =SUM(R2:R6) -> 940149.73 | V7: week2 | X7: =W7*100/X$1 -> 0 | Y7: =SUM(W7:W11) -> 27900 | Z7: =Y7*100/X1 -> 0.12567568 | AA7: total | AB7: =SUM(AB2:AB6) -> 708054.16 | AG7: week2 | AI7: =AH7*100/AI$1 -> 0 | AJ7: =SUM(AH7:AH11) -> 42913 | AK7: =AJ7*100/AI1 -> 0.20434762 | AL7: total | AM7: =SUM(AM2:AM6) -> 647459 | AQ7: week2 | AS7: =AR7*100/AS$1 -> 0 | AT7: =SUM(AR7:AR11) -> 35341 | AU7: =AT7*100/AS1 -> 0.16829048 | AV7: total | AW7: =SUM(AW2:AW6) -> 453517 | BA7: week2 | BC7: =BB7*100/BC$1 -> 0 | BD7: =SUM(BB7:BB11) -> 21040 | BE7: =BD7*100/BC1 -> 0.10019048 | BF7: total | BG7: =SUM(BG2:BG6) -> 494794
C8: 1135 | D8: =C8*100/D$1 -> 0.0051126126 | N8: =M8*100/N$1 -> 0 | W8: 2000 | X8: =W8*100/X$1 -> 0.009009009 | AI8: =AH8*100/AI$1 -> 0 | AS8: =AR8*100/AS$1 -> 0 | BB8: 10234 | BC8: =BB8*100/BC$1 -> 0.048733333
C9: 27760 | D9: =C9*100/D$1 -> 0.12504505 | M9: 25562 | N9: =M9*100/N$1 -> 0.11514414 | W9: 20000 | X9: =W9*100/X$1 -> 0.09009009 | AH9: 28330 | AI9: =AH9*100/AI$1 -> 0.13490476 | AS9: =AR9*100/AS$1 -> 0 | BC9: =BB9*100/BC$1 -> 0
D10: =C10*100/D$1 -> 0 | N10: =M10*100/N$1 -> 0 | W10: 7300 | X10: =W10*100/X$1 -> 0.032882883 | AH10: 6666 | AI10: =AH10*100/AI$1 -> 0.031742857 | AR10: 33356 | AS10: =AR10*100/AS$1 -> 0.1588381 | BB10: 10806 | BC10: =BB10*100/BC$1 -> 0.051457143
C11: -85944 | D11: =C11*100/D$1 -> -0.38713514 | N11: =M11*100/N$1 -> 0 | W11: -1400 | X11: =W11*100/X$1 -> -0.0063063063 | AH11: 7917 | AI11: =AH11*100/AI$1 -> 0.0377 | AR11: 1985 | AS11: =AR11*100/AS$1 -> 0.009452381 | BC11: =BB11*100/BC$1 -> 0
B12: week3 | C12: 1028 | D12: =C12*100/D$1 -> 0.0046306306 | E12: =SUM(C12:C16) -> 11623 | F12: =E12*100/D1 -> 0.052355856 | L12: week3 | M12: 10075 | N12: =M12*100/N$1 -> 0.045382883 | O12: =SUM(M12:M16) -> 37410 | P12: =O12*100/N1 -> 0.16851351 | V12: week3 | W12: 1000 | X12: =W12*100/X$1 -> 0.0045045045 | Y12: =SUM(W12:W16) -> 19124 | Z12: =Y12*100/X1 -> 0.086144144 | AG12: week3 | AI12: =AH12*100/AI$1 -> 0 | AJ12: =SUM(AH12:AH16) -> 19121 | AK12: =AJ12*100/AI1 -> 0.091052381 | AQ12: week3 | AS12: =AR12*100/AS$1 -> 0 | AT12: =SUM(AR12:AR16) -> 32064 | AU12: =AT12*100/AS1 -> 0.15268571 | BA12: week3 | BC12: =BB12*100/BC$1 -> 0 | BD12: =SUM(BB12:BB16) -> 22088 | BE12: =BD12*100/BC1 -> 0.10518095
C13: 18486 | D13: =C13*100/D$1 -> 0.08327027 | M13: 16088 | N13: =M13*100/N$1 -> 0.072468468 | W13: 1000 | X13: =W13*100/X$1 -> 0.0045045045 | AH13: 5576 | AI13: =AH13*100/AI$1 -> 0.026552381 | AS13: =AR13*100/AS$1 -> 0 | BB13: 12700 | BC13: =BB13*100/BC$1 -> 0.06047619
D14: =C14*100/D$1 -> 0 | M14: 4952 | N14: =M14*100/N$1 -> 0.022306306 | W14: 17124 | X14: =W14*100/X$1 -> 0.077135135 | AH14: 3261 | AI14: =AH14*100/AI$1 -> 0.015528571 | AS14: =AR14*100/AS$1 -> 0 | BC14: =BB14*100/BC$1 -> 0
C15: -7607 | D15: =C15*100/D$1 -> -0.034265766 | M15: 6295 | N15: =M15*100/N$1 -> 0.028355856 | X15: =W15*100/X$1 -> 0 | AH15: 2782 | AI15: =AH15*100/AI$1 -> 0.013247619 | AR15: 16363 | AS15: =AR15*100/AS$1 -> 0.077919048 | BB15: 9388 | BC15: =BB15*100/BC$1 -> 0.044704762
C16: -284 | D16: =C16*100/D$1 -> -0.0012792793 | N16: =M16*100/N$1 -> 0 | X16: =W16*100/X$1 -> 0 | AH16: 7502 | AI16: =AH16*100/AI$1 -> 0.03572381 | AR16: 15701 | AS16: =AR16*100/AS$1 -> 0.074766667 | BC16: =BB16*100/BC$1 -> 0
B17: week4 | C17: =-24194+4390 -> -19804 | D17: =C17*100/D$1 -> -0.089207207 | E17: =SUM(C17:C21) -> 383 | F17: =E17*100/D1 -> 0.0017252252 | L17: week4 | N17: =M17*100/N$1 -> 0 | O17: =SUM(M17:M21) -> 85053 | P17: =O17*100/N1 -> 0.38312162 | V17: week4 | W17: 2479 | X17: =W17*100/X$1 -> 0.011166667 | Y17: =SUM(W17:W21) -> 24159 | Z17: =Y17*100/X1 -> 0.10882432 | AG17: week4 | AI17: =AH17*100/AI$1 -> 0 | AJ17: =SUM(AH17:AH21) -> 22213 | AK17: =AJ17*100/AI1 -> 0.10577619 | AQ17: week4 | AS17: =AR17*100/AS$1 -> 0 | AT17: =SUM(AR17:AR21) -> 26108 | AU17: =AT17*100/AS1 -> 0.12432381 | BA17: week4 | BC17: =BB17*100/BC$1 -> 0 | BD17: =SUM(BB17:BB21) -> 23542 | BE17: =BD17*100/BC1 -> 0.11210476
C18: 6364 | D18: =C18*100/D$1 -> 0.028666667 | N18: =M18*100/N$1 -> 0 | W18: 9271 | X18: =W18*100/X$1 -> 0.041761261 | AI18: =AH18*100/AI$1 -> 0 | AR18: -23032 | AS18: =AR18*100/AS$1 -> -0.10967619 | BB18: 8900 | BC18: =BB18*100/BC$1 -> 0.042380952
C19: 13823 | D19: =C19*100/D$1 -> 0.062265766 | M19: 35029 | N19: =M19*100/N$1 -> 0.15778829 | W19: =11013-5559 -> 5454 | X19: =W19*100/X$1 -> 0.024567568 | AH19: 13273 | AI19: =AH19*100/AI$1 -> 0.063204762 | AR19: 26616 | AS19: =AR19*100/AS$1 -> 0.12674286 | BC19: =BB19*100/BC$1 -> 0
D20: =C20*100/D$1 -> 0 | M20: 43096 | N20: =M20*100/N$1 -> 0.19412613 | W20: 6955 | X20: =W20*100/X$1 -> 0.031328829 | AH20: 6000 | AI20: =AH20*100/AI$1 -> 0.028571429 | AR20: 13771 | AS20: =AR20*100/AS$1 -> 0.06557619 | BB20: 14642 | BC20: =BB20*100/BC$1 -> 0.06972381
D21: =C21*100/D$1 -> 0 | M21: 6928 | N21: =M21*100/N$1 -> 0.031207207 | X21: =W21*100/X$1 -> 0 | AH21: =3226-5862+5576 -> 2940 | AI21: =AH21*100/AI$1 -> 0.014 | AR21: 8753 | AS21: =AR21*100/AS$1 -> 0.041680952 | BC21: =BB21*100/BC$1 -> 0
B22: week5 | D22: =C22*100/D$1 -> 0 | E22: =SUM(C22:C26) -> 16934 | F22: =E22*100/D1 -> 0.076279279 | L22: week5 | M22: 450 | N22: =M22*100/N$1 -> 0.002027027 | O22: =SUM(M22:M26) -> -8530 | P22: =O22*100/N1 -> -0.038423423 | V22: week5 | W22: 990 | X22: =W22*100/X$1 -> 0.0044594595 | Y22: =SUM(W22:W26) -> 35016 | Z22: =Y22*100/X1 -> 0.15772973 | AG22: week5 | AI22: =AH22*100/AI$1 -> 0 | AJ22: =SUM(AH22:AH26) -> 38817 | AK22: =AJ22*100/AI1 -> 0.18484286 | AQ22: week5 | AR22: 2353 | AS22: =AR22*100/AS$1 -> 0.011204762 | AT22: =SUM(AR22:AR26) -> 2878 | AU22: =AT22*100/AS1 -> 0.013704762 | BA22: week5 | BC22: =BB22*100/BC$1 -> 0 | BD22: =SUM(BB22:BB26) -> 0 | BE22: =BD22*100/BC1 -> 0
C23: 16934 | D23: =C23*100/D$1 -> 0.076279279 | M23: -8980 | N23: =M23*100/N$1 -> -0.04045045 | W23: 1022 | X23: =W23*100/X$1 -> 0.0046036036 | AH23: 5696 | AI23: =AH23*100/AI$1 -> 0.02712381 | AR23: 525 | AS23: =AR23*100/AS$1 -> 0.0025 | BC23: =BB23*100/BC$1 -> 0
D24: =C24*100/D$1 -> 0 | N24: =M24*100/N$1 -> 0 | W24: 22704 | X24: =W24*100/X$1 -> 0.10227027 | AH24: 25309 | AI24: =AH24*100/AI$1 -> 0.12051905 | AS24: =AR24*100/AS$1 -> 0 | BC24: =BB24*100/BC$1 -> 0
D25: =C25*100/D$1 -> 0 | N25: =M25*100/N$1 -> 0 | X25: =W25*100/X$1 -> 0 | AH25: 7812 | AI25: =AH25*100/AI$1 -> 0.0372 | AS25: =AR25*100/AS$1 -> 0 | BC25: =BB25*100/BC$1 -> 0
D26: =C26*100/D$1 -> 0 | N26: =M26*100/N$1 -> 0 | W26: 10300 | X26: =W26*100/X$1 -> 0.046396396 | AI26: =AH26*100/AI$1 -> 0 | AS26: =AR26*100/AS$1 -> 0 | BC26: =BB26*100/BC$1 -> 0
C29: =SUM(C2:C27) -> 9920 | M29: =SUM(M2:M27) -> 163246 | W29: =SUM(W2:W27) -> 117564 | AH29: =SUM(AH2:AH27) -> 182871 | AR29: =SUM(AR2:AR27) -> 108694 | BB29: =SUM(BB2:BB27) -> 86164
B30: % return | C30: =C29*100/D$1 -> 0.044684685 | L30: % return | M30: =M29*100/N$1 -> 0.73534234 | V30: % return | W30: =W29*100/X$1 -> 0.52956757 | AG30: % return | AH30: =AH29*100/AI$1 -> 0.87081429 | AQ30: % return | AR30: =AR29*100/AS$1 -> 0.51759048 | BA30: % return | BB30: =BB29*100/BC$1 -> 0.41030476
B31: % return with others | C31: =((C29*100)+(H5*100)+(H6*100))/D$1 -> 1.0228735 | L31: % return with others | M31: =((M29*100)+(R5*100)+(R6*100))/N$1 -> 3.1448186 | V31: % return with others | W31: =((W29*100)+(AB5*100)+(AB6*100))/X$1 -> 2.009253 | AG31: % return with others | AH31: =((AH29*100)+(AM5*100)+(AM6*100))/AI$1 -> 1.4688524 | AQ31: % return with others | AR31: =((AR29*100)+(AW5*100)+(AW6*100))/AS$1 -> 0.84055714 | BA31: % return with others | BB31: =((BB29*100)+(BG5*100)+(BG6*100))/BC$1 -> 0.81330476
B33: May | D33: 22200000 | L33: July | N33: 22200000 | V33: September | X33: 22200000 | AG33: November | AI33: 21000000 | AQ33: January | AS33: 21000000 | BA33: March | BC33: 21000000
B34: week1 | D34: =C34*100/D$33 -> 0 | E34: =SUM(C34:C38) -> 5193 | F34: =E34*100/D33 -> 0.023391892 | G34: ani sal | H34: 172000 | L34: week1 | N34: =M34*100/N$33 -> 0 | O34: =SUM(M34:M38) -> 38474 | P34: =O34*100/N33 -> 0.17330631 | Q34: ani sal | R34: 192000 | V34: week1 | W34: 630 | X34: =W34*100/X$33 -> 0.0028378378 | Y34: =SUM(W34:W38) -> 25265 | Z34: =Y34*100/X33 -> 0.11380631 | AA34: ani sal | AB34: 192000 | AG34: week1 | AI34: =AH34*100/AI$33 -> 0 | AJ34: =SUM(AH34:AH38) -> 40794 | AK34: =AJ34*100/AI33 -> 0.19425714 | AL34: ani sal | AM34: 194000 | AQ34: week1 | AS34: =AR34*100/AS$33 -> 0 | AT34: =SUM(AR34:AR38) -> 31702 | AU34: =AT34*100/AS33 -> 0.1509619 | AV34: ani sal | AW34: 194000 | BA34: week1 | BC34: =BB34*100/BC$33 -> 0 | BD34: =SUM(BB34:BB38) -> 16625 | BE34: =BD34*100/BC33 -> 0.079166667 | BF34: ani sal | BG34: 209000
D35: =C35*100/D$33 -> 0 | G35: amr sal | H35: 70000 | N35: =M35*100/N$33 -> 0 | Q35: amr sal | R35: 130000 | W35: -4363 | X35: =W35*100/X$33 -> -0.019653153 | AA35: amr sal | AB35: 70000 | AI35: =AH35*100/AI$33 -> 0 | AL35: amr sal | AM35: 83000 | AS35: =AR35*100/AS$33 -> 0 | AV35: amr sal | AW35: 160000 | BB35: 10780 | BC35: =BB35*100/BC$33 -> 0.051333333 | BF35: amr sal | BG35: 83000
D36: =C36*100/D$33 -> 0 | G36: p | H36: =C61 -> 205902 | M36: 38474 | N36: =M36*100/N$33 -> 0.17330631 | Q36: p | R36: =M61 -> 189738 | W36: 10871 | X36: =W36*100/X$33 -> 0.048968468 | AA36: p | AB36: =W61 -> 143322 | AH36: 22000 | AI36: =AH36*100/AI$33 -> 0.1047619 | AL36: p | AM36: =AH61 -> 110459 | AS36: =AR36*100/AS$33 -> 0 | AV36: p | AW36: =AR61 -> 128348 | BC36: =BB36*100/BC$33 -> 0 | BF36: p | BG36: =BB61 -> 91521
C37: 3540 | D37: =C37*100/D$33 -> 0.015945946 | G37: nf strategy | H37: 5693.9474 | N37: =M37*100/N$33 -> 0 | Q37: nf strategy | R37: ='covered call-old'!L12+'covered call-old'!N12 -> 162072.57 | W37: 7000 | X37: =W37*100/X$33 -> 0.031531532 | AA37: nf strategy | AB37: 282854.68 | AH37: 13318 | AI37: =AH37*100/AI$33 -> 0.063419048 | AL37: nf strategy | AM37: 1815 | AR37: 17948 | AS37: =AR37*100/AS$33 -> 0.085466667 | AV37: nf strategy | AW37: 6787 | BB37: 5845 | BC37: =BB37*100/BC$33 -> 0.027833333 | BF37: nf strategy | BG37: -131
C38: 1653 | D38: =C38*100/D$33 -> 0.0074459459 | G38: int | H38: 80000 | I38: market total | J38: =H36+H37+H38 -> 291595.95 | N38: =M38*100/N$33 -> 0 | Q38: int | R38: 85000 | S38: market total | T38: =R36+R37+R38 -> 436810.57 | W38: =7173+3954 -> 11127 | X38: =W38*100/X$33 -> 0.050121622 | AA38: int | AB38: 85000 | AC38: market total | AD38: =AB36+AB37+AB38 -> 511176.68 | AH38: 5476 | AI38: =AH38*100/AI$33 -> 0.02607619 | AL38: int | AM38: 61000 | AN38: market total | AO38: =AM36+AM37+AM38 -> 173274 | AR38: 13754 | AS38: =AR38*100/AS$33 -> 0.065495238 | AV38: int | AW38: 69000 | AX38: market total | AY38: =AW36+AW37+AW38 -> 204135 | BC38: =BB38*100/BC$33 -> 0 | BF38: int | BG38: 88000 | BH38: market total | BI38: =BG36+BG37+BG38 -> 179390
B39: week2 | D39: =C39*100/D$33 -> 0 | E39: =SUM(C39:C43) -> 96630 | F39: =E39*100/D33 -> 0.43527027 | G39: total | H39: =SUM(H34:H38) -> 533595.95 | L39: week2 | N39: =M39*100/N$33 -> 0 | O39: =SUM(M39:M43) -> 32031 | P39: =O39*100/N33 -> 0.14428378 | Q39: total | R39: =SUM(R34:R38) -> 758810.57 | V39: week2 | W39: =2447+1200 -> 3647 | X39: =W39*100/X$33 -> 0.016427928 | Y39: =SUM(W39:W43) -> 45284 | Z39: =Y39*100/X33 -> 0.20398198 | AA39: total | AB39: =SUM(AB34:AB38) -> 773176.68 | AG39: week2 | AI39: =AH39*100/AI$33 -> 0 | AJ39: =SUM(AH39:AH43) -> 28175 | AK39: =AJ39*100/AI33 -> 0.13416667 | AL39: total | AM39: =SUM(AM34:AM38) -> 450274 | AQ39: week2 | AR39: -36520 | AS39: =AR39*100/AS$33 -> -0.17390476 | AT39: =SUM(AR39:AR43) -> -7233 | AU39: =AT39*100/AS33 -> -0.034442857 | AV39: total | AW39: =SUM(AW34:AW38) -> 558135 | BA39: week2 | BC39: =BB39*100/BC$33 -> 0 | BD39: =SUM(BB39:BB43) -> 16746 | BE39: =BD39*100/BC33 -> 0.079742857 | BF39: total | BG39: =SUM(BG34:BG38) -> 471390
D40: =C40*100/D$33 -> 0 | N40: =M40*100/N$33 -> 0 | W40: 19421 | X40: =W40*100/X$33 -> 0.087481982 | AI40: =AH40*100/AI$33 -> 0 | AR40: 15999 | AS40: =AR40*100/AS$33 -> 0.076185714 | BB40: 10596 | BC40: =BB40*100/BC$33 -> 0.050457143
C41: 92350 | D41: =C41*100/D$33 -> 0.41599099 | M41: 32031 | N41: =M41*100/N$33 -> 0.14428378 | W41: 1918 | X41: =W41*100/X$33 -> 0.0086396396 | AH41: 15745 | AI41: =AH41*100/AI$33 -> 0.07497619 | AS41: =AR41*100/AS$33 -> 0 | BC41: =BB41*100/BC$33 -> 0
C42: 4280 | D42: =C42*100/D$33 -> 0.019279279 | N42: =M42*100/N$33 -> 0 | W42: 4777 | X42: =W42*100/X$33 -> 0.021518018 | AH42: 12430 | AI42: =AH42*100/AI$33 -> 0.059190476 | AR42: 13288 | AS42: =AR42*100/AS$33 -> 0.06327619 | BB42: 6150 | BC42: =BB42*100/BC$33 -> 0.029285714
D43: =C43*100/D$33 -> 0 | N43: =M43*100/N$33 -> 0 | W43: =14431+1090 -> 15521 | X43: =W43*100/X$33 -> 0.069914414 | AI43: =AH43*100/AI$33 -> 0 | AS43: =AR43*100/AS$33 -> 0 | BC43: =BB43*100/BC$33 -> 0
B44: week3 | D44: =C44*100/D$33 -> 0 | E44: =SUM(C44:C48) -> 29627 | F44: =E44*100/D33 -> 0.13345495 | L44: week3 | N44: =M44*100/N$33 -> 0 | O44: =SUM(M44:M48) -> 41925 | P44: =O44*100/N33 -> 0.18885135 | V44: week3 | W44: 1450 | X44: =W44*100/X$33 -> 0.0065315315 | Y44: =SUM(W44:W48) -> 8067 | Z44: =Y44*100/X33 -> 0.036337838 | AG44: week3 | AH44: 1244 | AI44: =AH44*100/AI$33 -> 0.0059238095 | AJ44: =SUM(AH44:AH48) -> 31105 | AK44: =AJ44*100/AI33 -> 0.14811905 | AQ44: week3 | AS44: =AR44*100/AS$33 -> 0 | AT44: =SUM(AR44:AR48) -> 21864 | AU44: =AT44*100/AS33 -> 0.10411429 | BA44: week3 | BC44: =BB44*100/BC$33 -> 0 | BD44: =SUM(BB44:BB48) -> 24678 | BE44: =BD44*100/BC33 -> 0.11751429
C45: 15387 | D45: =C45*100/D$33 -> 0.069310811 | M45: 28902 | N45: =M45*100/N$33 -> 0.13018919 | W45: 2194 | X45: =W45*100/X$33 -> 0.0098828829 | AH45: 1210 | AI45: =AH45*100/AI$33 -> 0.0057619048 | AR45: 12747 | AS45: =AR45*100/AS$33 -> 0.0607 | BB45: 9678 | BC45: =BB45*100/BC$33 -> 0.046085714
C46: 6591 | D46: =C46*100/D$33 -> 0.029689189 | N46: =M46*100/N$33 -> 0 | W46: 21380 | X46: =W46*100/X$33 -> 0.096306306 | AI46: =AH46*100/AI$33 -> 0 | AS46: =AR46*100/AS$33 -> 0 | BC46: =BB46*100/BC$33 -> 0
C47: 7649 | D47: =C47*100/D$33 -> 0.034454955 | M47: 7200 | N47: =M47*100/N$33 -> 0.032432432 | W47: 7152 | X47: =W47*100/X$33 -> 0.032216216 | AH47: 20876 | AI47: =AH47*100/AI$33 -> 0.099409524 | AR47: 9117 | AS47: =AR47*100/AS$33 -> 0.043414286 | BB47: 15000 | BC47: =BB47*100/BC$33 -> 0.071428571
D48: =C48*100/D$33 -> 0 | M48: 5823 | N48: =M48*100/N$33 -> 0.02622973 | W48: -24109 | X48: =W48*100/X$33 -> -0.1085991 | AH48: 7775 | AI48: =AH48*100/AI$33 -> 0.03702381 | AS48: =AR48*100/AS$33 -> 0 | BC48: =BB48*100/BC$33 -> 0
B49: week4 | D49: =C49*100/D$33 -> 0 | E49: =SUM(C49:C53) -> 11476 | F49: =E49*100/D33 -> 0.051693694 | L49: week4 | M49: 2391 | N49: =M49*100/N$33 -> 0.01077027 | O49: =SUM(M49:M53) -> 57146 | P49: =O49*100/N33 -> 0.25741441 | V49: week4 | X49: =W49*100/X$33 -> 0 | Y49: =SUM(W49:W53) -> 65413 | Z49: =Y49*100/X33 -> 0.29465315 | AG49: week4 | AI49: =AH49*100/AI$33 -> 0 | AJ49: =SUM(AH49:AH53) -> 10385 | AK49: =AJ49*100/AI33 -> 0.049452381 | AQ49: week4 | AS49: =AR49*100/AS$33 -> 0 | AT49: =SUM(AR49:AR53) -> 42823 | AU49: =AT49*100/AS33 -> 0.20391905 | BA49: week4 | BC49: =BB49*100/BC$33 -> 0 | BD49: =SUM(BB49:BB53) -> 33472 | BE49: =BD49*100/BC33 -> 0.15939048
C50: -9964 | D50: =C50*100/D$33 -> -0.044882883 | M50: 11981 | N50: =M50*100/N$33 -> 0.053968468 | W50: -2194 | X50: =W50*100/X$33 -> -0.0098828829 | AI50: =AH50*100/AI$33 -> 0 | AR50: -5844 | AS50: =AR50*100/AS$33 -> -0.027828571 | BB50: 7102 | BC50: =BB50*100/BC$33 -> 0.033819048
C51: 17253 | D51: =C51*100/D$33 -> 0.077716216 | M51: 27753 | N51: =M51*100/N$33 -> 0.12501351 | W51: =44528-1973 -> 42555 | X51: =W51*100/X$33 -> 0.19168919 | AH51: =7146+6075 -> 13221 | AI51: =AH51*100/AI$33 -> 0.062957143 | AR51: 17290 | AS51: =AR51*100/AS$33 -> 0.082333333 | BC51: =BB51*100/BC$33 -> 0
C52: 4187 | D52: =C52*100/D$33 -> 0.01886036 | M52: 15021 | N52: =M52*100/N$33 -> 0.067662162 | W52: 11270 | X52: =W52*100/X$33 -> 0.050765766 | AH52: =5871-21771 -> -15900 | AI52: =AH52*100/AI$33 -> -0.075714286 | AR52: 16351 | AS52: =AR52*100/AS$33 -> 0.077861905 | BB52: 26370 | BC52: =BB52*100/BC$33 -> 0.12557143
D53: =C53*100/D$33 -> 0 | N53: =M53*100/N$33 -> 0 | W53: 13782 | X53: =W53*100/X$33 -> 0.062081081 | AH53: 13064 | AI53: =AH53*100/AI$33 -> 0.062209524 | AR53: 15026 | AS53: =AR53*100/AS$33 -> 0.071552381 | BC53: =BB53*100/BC$33 -> 0
B54: week5 | D54: =C54*100/D$33 -> 0 | E54: =SUM(C54:C58) -> 62976 | F54: =E54*100/D33 -> 0.28367568 | L54: week5 | N54: =M54*100/N$33 -> 0 | O54: =SUM(M54:M58) -> 20162 | P54: =O54*100/N33 -> 0.09081982 | V54: week5 | W54: -707 | X54: =W54*100/X$33 -> -0.0031846847 | Y54: =SUM(W54:W58) -> -707 | Z54: =Y54*100/X33 -> -0.0031846847 | AG54: week5 | AI54: =AH54*100/AI$33 -> 0 | AJ54: =SUM(AH54:AH58) -> 0 | AK54: =AJ54*100/AI33 -> 0 | AQ54: week5 | AR54: 4941 | AS54: =AR54*100/AS$33 -> 0.023528571 | AT54: =SUM(AR54:AR58) -> 39192 | AU54: =AT54*100/AS33 -> 0.18662857 | BA54: week5 | BC54: =BB54*100/BC$33 -> 0 | BD54: =SUM(BB54:BB58) -> 0 | BE54: =BD54*100/BC33 -> 0
D55: =C55*100/D$33 -> 0 | N55: =M55*100/N$33 -> 0 | X55: =W55*100/X$33 -> 0 | AI55: =AH55*100/AI$33 -> 0 | AR55: 8533 | AS55: =AR55*100/AS$33 -> 0.040633333 | BC55: =BB55*100/BC$33 -> 0
C56: 21350 | D56: =C56*100/D$33 -> 0.096171171 | M56: 20162 | N56: =M56*100/N$33 -> 0.09081982 | X56: =W56*100/X$33 -> 0 | AI56: =AH56*100/AI$33 -> 0 | AR56: 6891 | AS56: =AR56*100/AS$33 -> 0.032814286 | BC56: =BB56*100/BC$33 -> 0
C57: 41626 | D57: =C57*100/D$33 -> 0.1875045 | N57: =M57*100/N$33 -> 0 | X57: =W57*100/X$33 -> 0 | AI57: =AH57*100/AI$33 -> 0 | AR57: 18827 | AS57: =AR57*100/AS$33 -> 0.089652381 | BC57: =BB57*100/BC$33 -> 0
D58: =C58*100/D$33 -> 0 | N58: =M58*100/N$33 -> 0 | X58: =W58*100/X$33 -> 0 | AI58: =AH58*100/AI$33 -> 0 | AS58: =AR58*100/AS$33 -> 0 | BC58: =BB58*100/BC$33 -> 0
C61: =SUM(C34:C59) -> 205902 | M61: =SUM(M34:M59) -> 189738 | W61: =SUM(W34:W59) -> 143322 | AH61: =SUM(AH34:AH59) -> 110459 | AR61: =SUM(AR34:AR59) -> 128348 | BB61: =SUM(BB34:BB59) -> 91521
B62: % return | C62: =C61*100/D$33 -> 0.92748649 | L62: % return | M62: =M61*100/N$33 -> 0.85467568 | V62: % return | W62: =W61*100/X$33 -> 0.64559459 | AG62: % return | AH62: =AH61*100/AI$33 -> 0.52599524 | AQ62: % return | AR62: =AR61*100/AS$33 -> 0.61118095 | BA62: % return | BB62: =BB61*100/BC$33 -> 0.43581429
B63: % return with others | C63: =((C61*100)+(H37*100)+(H38*100))/D$33 -> 1.3134953 | L63: % return with others | M63: =((M61*100)+(R37*100)+(R38*100))/N$33 -> 1.9676152 | V63: % return with others | W63: =((W61*100)+(AB37*100)+(AB38*100))/X$33 -> 2.3025977 | AG63: % return with others | AH63: =((AH61*100)+(AM37*100)+(AM38*100))/AI$33 -> 0.82511429 | AQ63: % return with others | AR63: =((AR61*100)+(AW37*100)+(AW38*100))/AS$33 -> 0.97207143 | BA63: % return with others | BB63: =((BB61*100)+(BG37*100)+(BG38*100))/BC$33 -> 0.8542381
W66: Total capital | X66: 22000000
W67: Premium for return | AA67: nifty | AB67: 24400
W68: 0.001 | X68: 0.002 | Y68: 0.003 | AA68: lot size | AB68: 25
Q69: slabs | R69: lot size | S69: total lots | T69: qty per slab | U69: Total qty | V69: Instru | W69: =X66*W68 -> 22000 | X69: =X66*X68 -> 44000 | Y69: =X66*Y68 -> 66000 | AA69: contract size | AB69: =AB67*AB68 -> 610000 | AC69: capital invested | AD69: 7420338 | AE69: lots | AF69: =AD69/AB69 -> 12.164488 | AG69: qty | AH69: =AB68*AF69 -> 304.11221
Q70: 4 | R70: 75 | S70: =T70/R70 -> 42 | T70: =U70/Q70 -> 3150 | U70: 12600 | V70: MIDCP | W70: =W69/U70 -> 1.7460317 | X70: =X69/U70 -> 3.4920635 | Y70: =Y69/U70 -> 5.2380952 | AA70: niftybees | AB70: 218.5
Q71: 4 | R71: 40 | S71: =T71/R71 -> 40 | T71: =U71/Q71 -> 1600 | U71: 6400 | V71: FNF | W71: =W69/U71 -> 3.4375 | X71: =X69/U71 -> 6.875 | Y71: =Y69/U71 -> 10.3125 | AA71: qty niftybees | AB71: =AB69/AB70 -> 2791.762
Q72: 4 | R72: 15 | S72: =T72/R72 -> 45 | T72: =U72/Q72 -> 675 | U72: 2700 | V72: BNF | W72: =W69/U72 -> 8.1481481 | X72: =X69/U72 -> 16.296296 | Y72: =Y69/U72 -> 24.444444 | AA72: niftybees value | AB72: =AB71*AB70 -> 610000
Q73: 4 | R73: 50 | S73: =T73/R73 -> 30 | T73: =U73/Q73 -> 1500 | U73: 6000 | V73: NF | W73: =W69/U73 -> 3.6666667 | X73: =X69/U73 -> 7.3333333 | Y73: =Y69/U73 -> 11
Q74: 4 | R74: 10 | S74: =T74/R74 -> 45 | T74: =U74/Q74 -> 450 | U74: 1800 | V74: SENSEX | W74: =W69/U74 -> 12.222222 | X74: =X69/U74 -> 24.444444 | Y74: =Y69/U74 -> 36.666667
Q75: 4 | R75: 15 | S75: =T75/R75 -> 30 | T75: =U75/Q75 -> 450 | U75: 1800 | V75: BANKEX | W75: =W69/U75 -> 12.222222 | X75: =X69/U75 -> 24.444444 | Y75: =Y69/U75 -> 36.666667 | AA75: haircut | AB75: 0.08 | AC75: =AB72*AB75 -> 48800
AA76: niftybees value after haircut | AB76: =AB72-AC75 -> 561200
E77: 2984000 | F77: 2640000 | V77: 0.35 | W77: 0.3 | AA77: monthly return assumed | AB77: 0.012 | AF77: nifty | AG77: 25000
F78: =E77-F77 -> 344000 | U78: 45352 | V78: 12000000 | W78: 12000000 | AA78: monthly profit | AB78: =AB76*AB77 -> 6734.4 | AF78: lot size | AG78: 25
F79: =F78/F77 -> 0.13030303 | U79: 45717 | V79: =V78+V78*V77 -> 16200000 | W79: =W78+W78*W77 -> 15600000 | AA79: actual monthly profit (considering haircut) | AB79: =AB78/AB72 -> 0.01104 | AC79: =AB79*AB72 -> 6734.4 | AF79: contract size | AG79: =AG77*AG78 -> 625000 | AH79: capital invested | AI79: 7420338 | AJ79: lots | AK79: =AI79/AG79 -> 11.872541 | AL79: qty | AM79: =AG78*AK79 -> 296.81352
U80: 46082 | V80: =V79+V79*V77 -> 21870000 | W80: =W79+W79*W77 -> 20280000 | AF80: niftybees | AG80: 218.5
E81: 2905431 | F81: 2568046 | U81: 46447 | V81: =V80+V80*V77 -> 29524500 | W81: =W80+W80*W77 -> 26364000 | AF81: qty niftybees | AG81: =AG79/AG80 -> 2860.4119
F82: =E81-F81 -> 337385 | U82: 46813 | V82: =V81+V81*V77 -> 39858075 | W82: =W81+W81*W77 -> 34273200 | AF82: niftybees value | AG82: =AG81*AG80 -> 625000
F83: =F82/F81 -> 0.1313781

Sheet Strategic Indices
A1: Date | B1: NIFTY NEXT 50 | C1: NIFTY NEXT 50 | D1: NIFTY ALPHA 50 | E1: NIFTY ALPHA 50 | F1: NIFTY ALPHA LOW-VOLATILITY 30 | G1: NIFTY ALPHA LOW-VOLATILITY 30 | H1: NIFTY ALPHA QUALITY LOW-VOLATILITY 30 | I1: NIFTY ALPHA QUALITY LOW-VOLATILITY 30 | J1: NIFTY ALPHA QUALITY VALUE LOW-VOLATILITY 30 | K1: NIFTY ALPHA QUALITY VALUE LOW-VOLATILITY 30 | L1: NIFTY MIDCAP150 MOMENTUM 50 | M1: NIFTY MIDCAP150 MOMENTUM 50 | N1: NIFTY MIDCAP150 QUALITY 50 | O1: NIFTY MIDCAP150 QUALITY 50 | P1: NIFTY MIDSMALLCAP400 MOMENTUM QUALITY 100 | Q1: NIFTY MIDSMALLCAP400 MOMENTUM QUALITY 100 | R1: NIFTY200 ALPHA 30 | S1: NIFTY200 ALPHA 30 | T1: NIFTY200 MOMENTUM 30 | U1: NIFTY200 MOMENTUM 30 | V1: NIFTY200 QUALITY 30 | W1: NIFTY200 QUALITY 30 | X1: NIFTY200 VALUE 30 | Y1: NIFTY200 VALUE 30 | Z1: NIFTY500 MOMENTUM 50 | AA1: NIFTY500 MOMENTUM 50 | AB1: NIFTY 50 | AC1: NIFTY 50
A2: 42037 | B2: 19729.95 | C2: =B2/B$2*100 -> 100 | D2: 8660.54 | E2: =D2/D$2*100 -> 100 | F2: 6950.47 | G2: =F2/F$2*100 -> 100 | H2: 6331.77 | I2: =H2/H$2*100 -> 100 | J2: 5103.46 | K2: =J2/J$2*100 -> 100 | L2: 8512.02 | M2: =L2/L$2*100 -> 100 | N2: 6563.98 | O2: =N2/N$2*100 -> 100 | P2: 9685.38 | Q2: =P2/P$2*100 -> 100 | R2: 4208.76 | S2: =R2/R$2*100 -> 100 | T2: 6388.77 | U2: =T2/T$2*100 -> 100 | V2: 7314.99 | W2: =V2/V$2*100 -> 100 | X2: 4142.69 | Y2: =X2/X$2*100 -> 100 | Z2: 9917.6 | AA2: =Z2/Z$2*100 -> 100 | AB2: 8797.4 | AC2: =AB2/AB$2*100 -> 100
A3: 42038 | B3: 19552.4 | C3: =B3/B$2*100 -> 99.100099 | D3: 8648.33 | E3: =D3/D$2*100 -> 99.859016 | F3: 6907.82 | G3: =F3/F$2*100 -> 99.386372 | H3: 6324.37 | I3: =H3/H$2*100 -> 99.883129 | J3: 5091.11 | K3: =J3/J$2*100 -> 99.758007 | L3: 8553.2 | M3: =L3/L$2*100 -> 100.48379 | N3: 6598.72 | O3: =N3/N$2*100 -> 100.52925 | P3: 9721.62 | Q3: =P3/P$2*100 -> 100.37417 | R3: 4167.8 | S3: =R3/R$2*100 -> 99.026792 | T3: 6288.73 | U3: =T3/T$2*100 -> 98.434127 | V3: 7314.74 | W3: =V3/V$2*100 -> 99.996582 | X3: 4047.11 | Y3: =X3/X$2*100 -> 97.692803 | Z3: 9903.38 | AA3: =Z3/Z$2*100 -> 99.856619 | AB3: 8756.55 | AC3: =AB3/AB$2*100 -> 99.535658
A4: 42039 | B4: 19414.35 | C4: =B4/B$2*100 -> 98.400401 | D4: 8634 | E4: =D4/D$2*100 -> 99.693553 | F4: 6866.95 | G4: =F4/F$2*100 -> 98.798355 | H4: 6298.97 | I4: =H4/H$2*100 -> 99.481977 | J4: 5075.65 | K4: =J4/J$2*100 -> 99.455076 | L4: 8537.78 | M4: =L4/L$2*100 -> 100.30263 | N4: 6577.59 | O4: =N4/N$2*100 -> 100.20734 | P4: 9708.36 | Q4: =P4/P$2*100 -> 100.23726 | R4: 4148.56 | S4: =R4/R$2*100 -> 98.56965 | T4: 6246.33 | U4: =T4/T$2*100 -> 97.770463 | V4: 7310.83 | W4: =V4/V$2*100 -> 99.94313 | X4: 4050.85 | Y4: =X4/X$2*100 -> 97.783083 | Z4: 9861.5 | AA4: =Z4/Z$2*100 -> 99.434339 | AB4: 8723.7 | AC4: =AB4/AB$2*100 -> 99.162252
A5: 42040 | B5: 19196.15 | C5: =B5/B$2*100 -> 97.294469 | D5: 8553.69 | E5: =D5/D$2*100 -> 98.766243 | F5: 6848.57 | G5: =F5/F$2*100 -> 98.533912 | H5: 6293.07 | I5: =H5/H$2*100 -> 99.388796 | J5: 5089.95 | K5: =J5/J$2*100 -> 99.735278 | L5: 8431.64 | M5: =L5/L$2*100 -> 99.055688 | N5: 6522.21 | O5: =N5/N$2*100 -> 99.363648 | P5: 9611.37 | Q5: =P5/P$2*100 -> 99.235859 | R5: 4109.79 | S5: =R5/R$2*100 -> 97.648476 | T5: 6177.24 | U5: =T5/T$2*100 -> 96.689034 | V5: 7326.01 | W5: =V5/V$2*100 -> 100.15065 | X5: 3972.9 | Y5: =X5/X$2*100 -> 95.901455 | Z5: 9718.11 | AA5: =Z5/Z$2*100 -> 97.988525 | AB5: 8711.7 | AC5: =AB5/AB$2*100 -> 99.025849
A6: 42041 | B6: 19081.6 | C6: =B6/B$2*100 -> 96.713879 | D6: 8407.83 | E6: =D6/D$2*100 -> 97.082053 | F6: 6793.52 | G6: =F6/F$2*100 -> 97.741879 | H6: 6244.53 | I6: =H6/H$2*100 -> 98.622186 | J6: 5042.73 | K6: =J6/J$2*100 -> 98.810023 | L6: 8348.92 | M6: =L6/L$2*100 -> 98.083886 | N6: 6451.32 | O6: =N6/N$2*100 -> 98.283663 | P6: 9519.07 | Q6: =P6/P$2*100 -> 98.282876 | R6: 4052.89 | S6: =R6/R$2*100 -> 96.296534 | T6: 6089.71 | U6: =T6/T$2*100 -> 95.318974 | V6: 7288.74 | W6: =V6/V$2*100 -> 99.641148 | X6: 3948 | Y6: =X6/X$2*100 -> 95.300397 | Z6: 9546.52 | AA6: =Z6/Z$2*100 -> 96.258369 | AB6: 8661.05 | AC6: =AB6/AB$2*100 -> 98.45011
A7: 42044 | B7: 18742.35 | C7: =B7/B$2*100 -> 94.994412 | D7: 8246.94 | E7: =D7/D$2*100 -> 95.224316 | F7: 6733.53 | G7: =F7/F$2*100 -> 96.878772 | H7: 6204.06 | I7: =H7/H$2*100 -> 97.983028 | J7: 4974.16 | K7: =J7/J$2*100 -> 97.466425 | L7: 8208.41 | M7: =L7/L$2*100 -> 96.433162 | N7: 6350.94 | O7: =N7/N$2*100 -> 96.754408 | P7: 9379.05 | Q7: =P7/P$2*100 -> 96.837192 | R7: 3972.41 | S7: =R7/R$2*100 -> 94.384332 | T7: 5952.72 | U7: =T7/T$2*100 -> 93.174743 | V7: 7252.88 | W7: =V7/V$2*100 -> 99.150922 | X7: 3841.26 | Y7: =X7/X$2*100 -> 92.72381 | Z7: 9332.04 | AA7: =Z7/Z$2*100 -> 94.095749 | AB7: 8526.35 | AC7: =AB7/AB$2*100 -> 96.918976
A8: 42045 | B8: 18945.5 | C8: =B8/B$2*100 -> 96.024065 | D8: 8324.31 | E8: =D8/D$2*100 -> 96.117679 | F8: 6772.62 | G8: =F8/F$2*100 -> 97.44118 | H8: 6231.05 | I8: =H8/H$2*100 -> 98.409292 | J8: 4971.57 | K8: =J8/J$2*100 -> 97.415675 | L8: 8315.86 | M8: =L8/L$2*100 -> 97.695494 | N8: 6411.75 | O8: =N8/N$2*100 -> 97.680828 | P8: 9459.63 | Q8: =P8/P$2*100 -> 97.669167 | R8: 4010.09 | S8: =R8/R$2*100 -> 95.279607 | T8: 6013.59 | U8: =T8/T$2*100 -> 94.127508 | V8: 7255.09 | W8: =V8/V$2*100 -> 99.181134 | X8: 3860.45 | Y8: =X8/X$2*100 -> 93.187035 | Z8: 9450.34 | AA8: =Z8/Z$2*100 -> 95.288578 | AB8: 8565.55 | AC8: =AB8/AB$2*100 -> 97.364562
A9: 42046 | B9: 19286.7 | C9: =B9/B$2*100 -> 97.753415 | D9: 8517.24 | E9: =D9/D$2*100 -> 98.345369 | F9: 6876.74 | G9: =F9/F$2*100 -> 98.939208 | H9: 6304.78 | I9: =H9/H$2*100 -> 99.573737 | J9: 5019.19 | K9: =J9/J$2*100 -> 98.348767 | L9: 8504.76 | M9: =L9/L$2*100 -> 99.914709 | N9: 6502 | O9: =N9/N$2*100 -> 99.055756 | P9: 9594.1 | Q9: =P9/P$2*100 -> 99.057549 | R9: 4125.86 | S9: =R9/R$2*100 -> 98.030299 | T9: 6188.08 | U9: =T9/T$2*100 -> 96.858707 | V9: 7312.74 | W9: =V9/V$2*100 -> 99.969241 | X9: 3918.67 | Y9: =X9/X$2*100 -> 94.592403 | Z9: 9690.53 | AA9: =Z9/Z$2*100 -> 97.710434 | AB9: 8627.4 | AC9: =AB9/AB$2*100 -> 98.067611
A10: 42047 | B10: 19571.95 | C10: =B10/B$2*100 -> 99.199187 | D10: 8644.66 | E10: =D10/D$2*100 -> 99.81664 | F10: 6983.2 | G10: =F10/F$2*100 -> 100.4709 | H10: 6391.92 | I10: =H10/H$2*100 -> 100.94997 | J10: 5083.59 | K10: =J10/J$2*100 -> 99.610656 | L10: 8616.8 | M10: =L10/L$2*100 -> 101.23097 | N10: 6567.34 | O10: =N10/N$2*100 -> 100.05119 | P10: 9715.02 | Q10: =P10/P$2*100 -> 100.30603 | R10: 4211.92 | S10: =R10/R$2*100 -> 100.07508 | T10: 6282.25 | U10: =T10/T$2*100 -> 98.332699 | V10: 7357.14 | W10: =V10/V$2*100 -> 100.57621 | X10: 3915.21 | Y10: =X10/X$2*100 -> 94.508882 | Z10: 9836.51 | AA10: =Z10/Z$2*100 -> 99.182363 | AB10: 8711.55 | AC10: =AB10/AB$2*100 -> 99.024143
A11: 42048 | B11: 19661.3 | C11: =B11/B$2*100 -> 99.652052 | D11: 8726.27 | E11: =D11/D$2*100 -> 100.75896 | F11: 7047.29 | G11: =F11/F$2*100 -> 101.393 | H11: 6449.08 | I11: =H11/H$2*100 -> 101.85272 | J11: 5120.06 | K11: =J11/J$2*100 -> 100.32527 | L11: 8665.9 | M11: =L11/L$2*100 -> 101.8078 | N11: 6635.92 | O11: =N11/N$2*100 -> 101.09598 | P11: 9784.09 | Q11: =P11/P$2*100 -> 101.01916 | R11: 4244.85 | S11: =R11/R$2*100 -> 100.8575 | T11: 6331.37 | U11: =T11/T$2*100 -> 99.101548 | V11: 7418.69 | W11: =V11/V$2*100 -> 101.41764 | X11: 3986.73 | Y11: =X11/X$2*100 -> 96.235296 | Z11: 9910.76 | AA11: =Z11/Z$2*100 -> 99.931032 | AB11: 8805.5 | AC11: =AB11/AB$2*100 -> 100.09207
A12: 42051 | B12: 19559.5 | C12: =B12/B$2*100 -> 99.136085 | D12: 8732.13 | E12: =D12/D$2*100 -> 100.82662 | F12: 7038.49 | G12: =F12/F$2*100 -> 101.26639 | H12: 6457.06 | I12: =H12/H$2*100 -> 101.97875 | J12: 5119.98 | K12: =J12/J$2*100 -> 100.3237 | L12: 8653.52 | M12: =L12/L$2*100 -> 101.66236 | N12: 6658.14 | O12: =N12/N$2*100 -> 101.4345 | P12: 9793.3 | Q12: =P12/P$2*100 -> 101.11426 | R12: 4218.34 | S12: =R12/R$2*100 -> 100.22762 | T12: 6251.51 | U12: =T12/T$2*100 -> 97.851543 | V12: 7412.64 | W12: =V12/V$2*100 -> 101.33493 | X12: 3986.81 | Y12: =X12/X$2*100 -> 96.237228 | Z12: 9894.38 | AA12: =Z12/Z$2*100 -> 99.765871 | AB12: 8809.35 | AC12: =AB12/AB$2*100 -> 100.13584
A13: 42053 | B13: 19667.6 | C13: =B13/B$2*100 -> 99.683983 | D13: 8838.64 | E13: =D13/D$2*100 -> 102.05645 | F13: 7123.82 | G13: =F13/F$2*100 -> 102.49408 | H13: 6511.81 | I13: =H13/H$2*100 -> 102.84344 | J13: 5168.81 | K13: =J13/J$2*100 -> 101.2805 | L13: 8768.19 | M13: =L13/L$2*100 -> 103.00951 | N13: 6698.13 | O13: =N13/N$2*100 -> 102.04373 | P13: 9883.45 | Q13: =P13/P$2*100 -> 102.04504 | R13: 4263.99 | S13: =R13/R$2*100 -> 101.31226 | T13: 6302.65 | U13: =T13/T$2*100 -> 98.65201 | V13: 7429.78 | W13: =V13/V$2*100 -> 101.56924 | X13: 3970.56 | Y13: =X13/X$2*100 -> 95.84497 | Z13: 10000.44 | AA13: =Z13/Z$2*100 -> 100.83528 | AB13: 8869.1 | AC13: =AB13/AB$2*100 -> 100.81501
... A2484: 45693 | B2484: 64012.8 | C2484: =B2484/B$2*100 -> 324.44482 | D2484: 49603.1 | E2484: =D2484/D$2*100 -> 572.74835 | F2484: 26259.2 | G2484: =F2484/F$2*100 -> 377.80467 | H2484: 21842.35 | I2484: =H2484/H$2*100 -> 344.96436 | J2484: 19850.2 | K2484: =J2484/J$2*100 -> 388.95573 | L2484: 58459.9 | M2484: =L2484/L$2*100 -> 686.79232 | N2484: 23034.75 | O2484: =N2484/N$2*100 -> 350.92657 | P2484: 46816.5 | Q2484: =P2484/P$2*100 -> 483.37288 | R2484: 23742.95 | S2484: =R2484/R$2*100 -> 564.13172 | T2484: 30229.7 | U2484: =T2484/T$2*100 -> 473.16933 | V2484: 20329.1 | W2484: =V2484/V$2*100 -> 277.91015 | X2484: 11947.45 | Y2484: =X2484/X$2*100 -> 288.39836 | Z2484: 51430.9 | AA2484: =Z2484/Z$2*100 -> 518.58212 | AB2484: 23696.3 | AC2484: =AB2484/AB$2*100 -> 269.35572

Sheet Momentum
A1: Week | B1: MID150 30 7 | C1: MID150 20 7 | D1: MID150 10 7 | E1: NF200 30 7 | F1: NF200 20 7 | G1: NF200 10 7 | H1: NF50 30 7 | I1: NF50 20 7 | J1: NF50 10 7 | K1: NF500 30 7 | L1: NF500 20 7 | M1: NF500 10 7 | N1: Date | O1: NIFTYM150MOMNTM50 | P1: NIFTYM150MOMNTM50 | Q1: NIFTY ALPHA 50 | R1: NIFTY ALPHA 50 | S1: Criteria: Within 25% from 52 Week High, 3months, 6months, 1year positive returns, above 200DMA | T1: Date | U1: NF500 30 7 | V1: NF500 20 7 | W1: NF500 10 7 | X1: MID150 30 7 | Y1: MID150 20 7 | Z1: MID150 10 7 | AA1: NF200 30 7 | AB1: NF200 20 7 | AC1: NF200 10 7 | AD1: NF50 30 7 | AE1: NF50 20 7 | AF1: NF50 10 7 | AG1: Date | AH1: NIFTYM150MOMNTM50 | AI1: NIFTYM150MOMNTM50 | AJ1: NIFTY ALPHA 50 | AK1: NIFTY ALPHA 50 | AM1: N500 20 | AN1: 3M sort | AO1: NormMom | AP1: alpha | AQ1: Jalpha | AS1: 3M sort old | AT1: NormMom old | AU1: alpha old | AV1: Jalpha old | AX1: 3M sort | AY1: NormMom 3M | AZ1: alpha 3M | BA1: Jalpha 3M | BC1: 3M sort old | BD1: NormMom old 3M | BE1: alpha old 3M | BF1: Jalpha old 3M | BH1: alpha 1 | BI1: alpha 3M | BK1: alpha old 1 | BL1: alpha old 3M | BN1: 3M sort | BO1: alpha | BP1: 3M sort old | BQ1: alpha old | BS1: 3M sort | BT1: 6M sort | BU1: 1Y sort | BV1: 1M sort | BX1: 3M sort old | BY1: 6M sort old | BZ1: 1Y sort old | CA1: 1M sort old | CC1: WeightedSort | CD1: 6M sort | CE1: WeightedSortOld | CF1: 6M sort old
A2: 44068 | B2: 1024526.7 | C2: 1028695 | D2: 1049550 | E2: 1014153.3 | F2: 1022960 | G2: 1036580 | H2: 995147.37 | I2: 995147.37 | J2: 995050 | K2: 1060433.3 | L2: 1071600 | M2: 1101330 | N2: Tue Aug 25 2020 | O2: 16045.4 | P2: =O2/O$2*1000000 -> 1000000 | Q2: 15965.05 | R2: =Q2/Q$2*1000000 -> 1000000 | S2: Enter Tuesday at close, exit next Tuesday at close | T2: 42500 | U2: 1020146.7 | V2: 1021030 | W2: 1017750 | X2: 1006826.7 | Y2: 1002490 | Z2: 1003080 | AA2: 1003380 | AB2: 1004970 | AC2: 1001900 | AD2: 1010829.4 | AE2: 1010829.4 | AF2: 1001360 | AG2: Tue May 10 2016 | AH2: 9249.29 | AI2: =AH2/AH$2*1000000 -> 1000000 | AJ2: 8657.19 | AK2: =AJ2/AJ$2*1000000 -> 1000000 | AM2: 1year daily returns used for alpha | AN2: 919095 | AO2: 953005 | AP2: 972640 | AQ2: 956030 | AS2: 1021030 | AT2: 1021600 | AU2: 1019695 | AV2: 1002280 | AW2: 3months daily returns used for alpha | AX2: 919095 | AY2: 953005 | AZ2: 972640 | BA2: 956030 | BC2: 1021030 | BD2: 1021600 | BE2: 1019695 | BF2: 1002280 | BH2: 972640 | BI2: 972640 | BK2: 1019695 | BL2: 1019695 | BN2: 919095 | BO2: 972640 | BP2: 1021030 | BQ2: 1019695 | BS2: 919095 | BT2: 957020 | BU2: 972755 | BV2: 943835 | BX2: 1021030 | BY2: 1021480 | BZ2: 1021530 | CA2: 1012080 | CC2: 1013860 | CD2: 1013860 | CE2: 979700 | CF2: 979700
A3: 44075 | B3: 986837.75 | C3: 988267.29 | D3: 1005899.2 | E3: 977157.02 | F3: 982875.31 | G3: 974913.86 | H3: 980201.2 | I3: 980304.75 | J3: 983407.91 | K3: 989727.17 | L3: 989895.86 | M3: 986923.84 | N3: Wed Aug 26 2020 | O3: 16063.37 | P3: =O3/O$2*1000000 -> 1001119.9 | Q3: 15979.2 | R3: =Q3/Q$2*1000000 -> 1000886.3 | S3: Overall NF200 20 and NF500 20 seems better. NF500 20 is more volatile but can generate more returns. Beaten strategic indices | T3: 42507 | U3: 1032612.9 | V3: 1045228.4 | W3: 1047509 | X3: 1021090 | Y3: 1012354.5 | Z3: 1022690.2 | AA3: 1011811.7 | AB3: 1006753.8 | AC3: 1005847.5 | AD3: 1018786.9 | AE3: 1018786.9 | AF3: 1019474.6 | AG3: Wed May 11 2016 | AH3: 9202.9 | AI3: =AH3/AH$2*1000000 -> 994984.48 | AJ3: 8639.07 | AK3: =AJ3/AJ$2*1000000 -> 997906.94 | AN3: 933988.93 | AO3: 995842.57 | AP3: 1019886 | AQ3: 951742.21 | AS3: 1045228.4 | AT3: 1052447.2 | AU3: 1040053.2 | AV3: 1003041.7 | AX3: 933988.93 | AY3: 995842.57 | AZ3: 1010689.7 | BA3: 951742.21 | BC3: 1045228.4 | BD3: 1052447.2 | BE3: 1040053.2 | BF3: 1003041.7 | BH3: 1019886 | BI3: 1010689.7 | BK3: 1040053.2 | BL3: 1040053.2 | BN3: 933988.93 | BO3: 1019886 | BP3: 1045228.4 | BQ3: 1040053.2 | BS3: 933988.93 | BT3: 980385.64 | BU3: 1009880.2 | BV3: 969101.46 | BX3: 1045228.4 | BY3: 1057007.1 | BZ3: 1041924.8 | CA3: 1016345.9 | CC3: 1047504.9 | CD3: 1047504.9 | CE3: 1024668.2 | CF3: 1024668.2
A4: 44082 | B4: 989571.29 | C4: 998258.67 | D4: 1016974.2 | E4: 975873.69 | F4: 980747.39 | G4: 993242.24 | H4: 971047.99 | I4: 971629.05 | J4: 963798.76 | K4: 1009756 | L4: 1005937.1 | M4: 994996.88 | N4: Thu Aug 27 2020 | O4: 16066.62 | P4: =O4/O$2*1000000 -> 1001322.5 | Q4: 15974.95 | R4: =Q4/Q$2*1000000 -> 1000620.1 | S4: 3months sorted filter and 1 year Alpha criteria are top performers | T4: 42514 | U4: 1017337.1 | V4: 1026597.2 | W4: 1043109.5 | X4: 993721.43 | Y4: 980510.89 | Z4: 1017126.8 | AA4: 1000820.1 | AB4: 999560.57 | AC4: 1007155.1 | AD4: 999047.89 | AE4: 999047.89 | AF4: 1010391.1 | AG4: Thu May 12 2016 | AH4: 9265.82 | AI4: =AH4/AH$2*1000000 -> 1001787.2 | AJ4: 8730.31 | AK4: =AJ4/AJ$2*1000000 -> 1008446.2 | AN4: 987128.23 | AO4: 1069609.6 | AP4: 1099518.7 | AQ4: 1003483.7 | AS4: 1026597.2 | AT4: 1037976.1 | AU4: 993630.44 | AV4: 959033.28 | AX4: 987128.23 | AY4: 1069609.6 | AZ4: 1086082.1 | BA4: 997444.87 | BC4: 1026597.2 | BD4: 1037976.1 | BE4: 997130.21 | BF4: 957157.59 | BH4: 1099518.7 | BI4: 1086082.1 | BK4: 993630.44 | BL4: 997130.21 | BN4: 987128.23 | BO4: 1099518.7 | BP4: 1026597.2 | BQ4: 993630.44 | BS4: 987128.23 | BT4: 1031552 | BU4: 1088731.6 | BV4: 1037006.4 | BX4: 1026597.2 | BY4: 1045707.7 | BZ4: 995418.53 | CA4: 986749.92 | CC4: 1084083.8 | CD4: 1084083.8 | CE4: 1024857.8 | CF4: 1024857.8
A5: 44089 | B5: 1052244.1 | C5: 1053167.9 | D5: 1088721.7 | E5: 1031374.9 | F5: 1034021.6 | G5: 1066464.1 | H5: 1005135.5 | I5: 1011907.9 | J5: 997406.42 | K5: 1083353.7 | L5: 1063169.9 | M5: 1056079.7 | N5: Fri Aug 28 2020 | O5: 16048.16 | P5: =O5/O$2*1000000 -> 1000172 | Q5: 16019.3 | R5: =Q5/Q$2*1000000 -> 1003398 | T5: 42521 | U5: 1055083.7 | V5: 1076341 | W5: 1090508.4 | X5: 1039939.4 | Y5: 1034007.6 | Z5: 1079395.3 | AA5: 1044812.8 | AB5: 1041961.9 | AC5: 1064351.4 | AD5: 1026175.4 | AE5: 1026175.4 | AF5: 1026870.6 | AG5: Fri May 13 2016 | AH5: 9266.53 | AI5: =AH5/AH$2*1000000 -> 1001863.9 | AJ5: 8653.37 | AK5: =AJ5/AJ$2*1000000 -> 999558.75 | AN5: 935619.88 | AO5: 1010738.3 | AP5: 1049083.8 | AQ5: 941689.15 | AS5: 1076341 | AT5: 1086797.3 | AU5: 1022604.7 | AV5: 999336.65 | AX5: 935619.88 | AY5: 1010738.3 | AZ5: 1033396.2 | BA5: 933079.75 | BC5: 1076341 | BD5: 1081389.4 | BE5: 1026276.3 | BF5: 996587.7 | BH5: 1049083.8 | BI5: 1033396.2 | BK5: 1022604.7 | BL5: 1026276.3 | BN5: 935619.88 | BO5: 1049083.8 | BP5: 1076341 | BQ5: 1022604.7 | BS5: 935619.88 | BT5: 964150.36 | BU5: 1040043.6 | BV5: 962471.57 | BX5: 1076341 | BY5: 1088968.6 | BZ5: 1023081.2 | CA5: 1024167.5 | CC5: 1077904.5 | CD5: 1077904.5 | CE5: 998339.6 | CF5: 998339.6
A6: 44096 | B6: 997131.09 | C6: 1004011.3 | D6: 1029658.5 | E6: 977764.01 | F6: 974927.25 | G6: 1006784.7 | H6: 990065.92 | I6: 985912.02 | J6: 962237.87 | K6: 1023556.2 | L6: 1007693.7 | M6: 1006644.6 | N6: Mon Aug 31 2020 | O6: 15459.14 | P6: =O6/O$2*1000000 -> 963462.43 | Q6: 15442.25 | R6: =Q6/Q$2*1000000 -> 967253.47 | T6: 42528 | U6: 1082558 | V6: 1106193.3 | W6: 1149395.8 | X6: 1046872.3 | Y6: 1043810 | Z6: 1074721.5 | AA6: 1062727.9 | AB6: 1053308.9 | AC6: 1067118.7 | AD6: 1041402.7 | AE6: 1041402.7 | AF6: 1032467 | AG6: Mon May 16 2016 | AH6: 9268.07 | AI6: =AH6/AH$2*1000000 -> 1002030.4 | AJ6: 8626.27 | AK6: =AJ6/AJ$2*1000000 -> 996428.4 | AN6: 976745.06 | AO6: 1061189.3 | AP6: 1088319.5 | AQ6: 969916.28 | AS6: 1106193.3 | AT6: 1112521.8 | AU6: 1060149.6 | AV6: 1034728.2 | AX6: 976745.06 | AY6: 1056929 | AZ6: 1074726.9 | BA6: 961048.81 | BC6: 1106193.3 | BD6: 1106985.9 | BE6: 1066157.4 | BF6: 1031881.8 | BH6: 1088319.5 | BI6: 1074726.9 | BK6: 1060149.6 | BL6: 1066157.4 | BN6: 976745.06 | BO6: 1088319.5 | BP6: 1106193.3 | BQ6: 1060149.6 | BS6: 976745.06 | BT6: 1004664 | BU6: 1086923.5 | BV6: 1003906 | BX6: 1106193.3 | BY6: 1123412.7 | BZ6: 1062689.8 | CA6: 1037200 | CC6: 1071792.8 | CD6: 1071792.8 | CE6: 931595.6 | CF6: 931595.6
A7: 44103 | B7: 1026819 | C7: 1042053.3 | D7: 1073604.4 | E7: 1011764.1 | F7: 1010302.5 | G7: 1053559.9 | H7: 1005436.7 | I7: 1001218.3 | J7: 983128.06 | K7: 1063580.6 | L7: 1051986.9 | M7: 1055386.4 | N7: Tue Sep 01 2020 | O7: 15582.56 | P7: =O7/O$2*1000000 -> 971154.35 | Q7: 15680.55 | R7: =Q7/Q$2*1000000 -> 982179.82 | T7: 42535 | U7: 1097118.5 | V7: 1119168.9 | W7: 1186613.3 | X7: 1039635 | Y7: 1035903.1 | Z7: 1074635.5 | AA7: 1050208.9 | AB7: 1034459.9 | AC7: 1045349.5 | AD7: 1024410.5 | AE7: 1024990.2 | AF7: 1018384.2 | AG7: Tue May 17 2016 | AH7: 9306.47 | AI7: =AH7/AH$2*1000000 -> 1006182.1 | AJ7: 8687.03 | AK7: =AJ7/AJ$2*1000000 -> 1003446.8 | AN7: 1009480.7 | AO7: 1080460.5 | AP7: 1086681.6 | AQ7: 992364.99 | AS7: 1119168.9 | AT7: 1124431.3 | AU7: 1088211.8 | AV7: 1053906.8 | AX7: 1009480.7 | AY7: 1083214.9 | AZ7: 1077655.5 | BA7: 979938.23 | BC7: 1119168.9 | BD7: 1118681.2 | BE7: 1097619.7 | BF7: 1050440.2 | BH7: 1086681.6 | BI7: 1077655.5 | BK7: 1088211.8 | BL7: 1097619.7 | BN7: 1009480.7 | BO7: 1086681.6 | BP7: 1119168.9 | BQ7: 1088211.8 | BS7: 1009480.7 | BT7: 1029514.3 | BU7: 1080760.7 | BV7: 1015742 | BX7: 1119168.9 | BY7: 1152110.2 | BZ7: 1094618.3 | CA7: 1029099.5 | CC7: 1081230 | CD7: 1081230 | CE7: 958346.37 | CF7: 958346.37
A8: 44110 | B8: 1035369 | C8: 1053687.8 | D8: 1085049 | E8: 1033668.8 | F8: 1042450.3 | G8: 1080404.7 | H8: 1038133.5 | I8: 1033777.9 | J8: 1020083.8 | K8: 1093325.4 | L8: 1087244.2 | M8: 1095923.8 | N8: Wed Sep 02 2020 | O8: 15873.49 | P8: =O8/O$2*1000000 -> 989286.03 | Q8: 16022.3 | R8: =Q8/Q$2*1000000 -> 1003586 | T8: 42542 | U8: 1113564.3 | V8: 1145603.7 | W8: 1213893.5 | X8: 1046493.1 | Y8: 1043397.9 | Z8: 1073023.6 | AA8: 1063683.1 | AB8: 1049687.2 | AC8: 1053963.2 | AD8: 1041745.8 | AE8: 1040575.1 | AF8: 1035635.6 | AG8: Wed May 18 2016 | AH8: 9321.33 | AI8: =AH8/AH$2*1000000 -> 1007788.7 | AJ8: 8728.07 | AK8: =AJ8/AJ$2*1000000 -> 1008187.4 | AN8: 991441.25 | AO8: 1068510.6 | AP8: 1080949.3 | AQ8: 984768.44 | AS8: 1145603.7 | AT8: 1128811 | AU8: 1087412 | AV8: 1088000.7 | AX8: 991441.25 | AY8: 1068732.3 | AZ8: 1069632.4 | BA8: 971148.18 | BC8: 1145603.7 | BD8: 1123038.5 | BE8: 1097817.3 | BF8: 1084422 | BH8: 1080949.3 | BI8: 1069632.4 | BK8: 1087412 | BL8: 1097817.3 | BN8: 991441.25 | BO8: 1080949.3 | BP8: 1145603.7 | BQ8: 1087412 | BS8: 991441.25 | BT8: 1017124.1 | BU8: 1075059.7 | BV8: 1021821.2 | BX8: 1145603.7 | BY8: 1153469.7 | BZ8: 1094361.1 | CA8: 1028970.8 | CC8: 1084635.8 | CD8: 1084635.8 | CE8: 1006450.6 | CF8: 1006450.6
A9: 44117 | B9: 1031665.8 | C9: 1048909.3 | D9: 1092850.5 | E9: 1052619.4 | F9: 1060104.2 | G9: 1090571.3 | H9: 1058450.6 | I9: 1060397.7 | J9: 1055154.3 | K9: 1082472.4 | L9: 1067815.2 | M9: 1067846.2 | N9: Thu Sep 03 2020 | O9: 16047.81 | P9: =O9/O$2*1000000 -> 1000150.2 | Q9: 16194.05 | R9: =Q9/Q$2*1000000 -> 1014343.8 | T9: 42549 | U9: 1129265.5 | V9: 1157500.8 | W9: 1252301.1 | X9: 1065277.6 | Y9: 1058568.9 | Z9: 1110515 | AA9: 1075248.9 | AB9: 1059097.6 | AC9: 1082578.3 | AD9: 1040720.7 | AE9: 1042864.4 | AF9: 1031358.4 | AG9: Thu May 19 2016 | AH9: 9205.12 | AI9: =AH9/AH$2*1000000 -> 995224.5 | AJ9: 8576.57 | AK9: =AJ9/AJ$2*1000000 -> 990687.51 | AN9: 983475.02 | AO9: 1059540.5 | AP9: 1081273.6 | AQ9: 998166.21 | AS9: 1157500.8 | AT9: 1148012 | AU9: 1102575.9 | AV9: 1101818.3 | AX9: 983475.02 | AY9: 1059760.3 | AZ9: 1062326.8 | BA9: 978261.84 | BC9: 1157500.8 | BD9: 1140512.9 | BE9: 1119576 | BF9: 1096491.6 | BH9: 1081273.6 | BI9: 1062326.8 | BK9: 1102575.9 | BL9: 1119576 | BN9: 983475.02 | BO9: 1081273.6 | BP9: 1157500.8 | BQ9: 1102575.9 | BS9: 983475.02 | BT9: 1008188.7 | BU9: 1069404.8 | BV9: 1007449.3 | BX9: 1157500.8 | BY9: 1168903.2 | BZ9: 1109621.9 | CA9: 1036333.1 | CC9: 1076756 | CD9: 1076756 | CE9: 1013364.9 | CF9: 1013364.9
A10: 44124 | B10: 1034358.5 | C10: 1038651 | D10: 1067070.1 | E10: 1037275.7 | F10: 1042262.7 | G10: 1069850.4 | H10: 1044106.3 | I10: 1048897.7 | J10: 1050437.8 | K10: 1077615.7 | L10: 1059235.3 | M10: 1081098.2 | N10: Fri Sep 04 2020 | O10: 15829.44 | P10: =O10/O$2*1000000 -> 986540.69 | Q10: 15989.5 | R10: =Q10/Q$2*1000000 -> 1001531.5 | T10: 42556 | U10: 1170050.8 | V10: 1186646.7 | W10: 1314164.8 | X10: 1090262 | Y10: 1080100.2 | Z10: 1127739.1 | AA10: 1109481.2 | AB10: 1086581.2 | AC10: 1104056.7 | AD10: 1067320.5 | AE10: 1070954 | AF10: 1068621.4 | AG10: Fri May 20 2016 | AH10: 9153.15 | AI10: =AH10/AH$2*1000000 -> 989605.69 | AJ10: 8489.68 | AK10: =AJ10/AJ$2*1000000 -> 980650.77 | AN10: 978857.6 | AO10: 1067757.2 | AP10: 1083236.1 | AQ10: 996928.48 | AS10: 1186646.7 | AT10: 1189219.9 | AU10: 1134131.6 | AV10: 1165845 | AX10: 978857.6 | AY10: 1073526.6 | AZ10: 1062932.3 | BA10: 978159.13 | BC10: 1186646.7 | BD10: 1188494.3 | BE10: 1160737.3 | BF10: 1165444.5 | BH10: 1083236.1 | BI10: 1062932.3 | BK10: 1134131.6 | BL10: 1160737.3 | BN10: 978857.6 | BO10: 1083236.1 | BP10: 1186646.7 | BQ10: 1134131.6 | BS10: 978857.6 | BT10: 1002729.3 | BU10: 1073848.2 | BV10: 1030394 | BX10: 1186646.7 | BY10: 1224040.3 | BZ10: 1145074.4 | CA10: 1059707.6 | CC10: 1056696 | CD10: 1056696 | CE10: 1047251.8 | CF10: 1047251.8
A11: 44131 | B11: 1043957.3 | C11: 1041284 | D11: 1074763.7 | E11: 1036300.7 | F11: 1036535.4 | G11: 1075060.6 | H11: 1029473.9 | I11: 1033908.9 | J11: 1030384.9 | K11: 1076890.1 | L11: 1054262.2 | M11: 1111801.4 | N11: Mon Sep 07 2020 | O11: 15729.67 | P11: =O11/O$2*1000000 -> 980322.71 | Q11: 15990.4 | R11: =Q11/Q$2*1000000 -> 1001587.8 | T11: 42563 | U11: 1180733.4 | V11: 1204612.5 | W11: 1340316.6 | X11: 1100575.8 | Y11: 1086289.1 | Z11: 1123803.3 | AA11: 1130065.8 | AB11: 1106232 | AC11: 1117791.1 | AD11: 1100109.5 | AE11: 1104051.8 | AF11: 1115117.1 | AG11: Mon May 23 2016 | AH11: 9139.61 | AI11: =AH11/AH$2*1000000 -> 988141.79 | AJ11: 8449.66 | AK11: =AJ11/AJ$2*1000000 -> 976028.02 | AN11: 1004645.6 | AO11: 1077601.9 | AP11: 1101564.5 | AQ11: 983719.18 | AS11: 1204612.5 | AT11: 1190105.9 | AU11: 1148234.6 | AV11: 1194140.1 | AX11: 1004645.6 | AY11: 1086607.5 | AZ11: 1085078.5 | BA11: 969927.92 | BC11: 1204612.5 | BD11: 1189320.3 | BE11: 1175977.7 | BF11: 1188025 | BH11: 1101564.5 | BI11: 1085078.5 | BK11: 1148234.6 | BL11: 1175977.7 | BN11: 1004645.6 | BO11: 1101564.5 | BP11: 1204612.5 | BQ11: 1148234.6 | BS11: 1004645.6 | BT11: 1020462.6 | BU11: 1092017.7 | BV11: 1016901 | BX11: 1204612.5 | BY11: 1247021.7 | BZ11: 1159611.1 | CA11: 1073240.1 | CC11: 1081871.8 | CD11: 1081871.8 | CE11: 1052776.1 | CF11: 1052776.1
A12: 44138 | B12: 1043960.8 | C12: 1042851.1 | D12: 1086113.2 | E12: 1048090.3 | F12: 1060914.7 | G12: 1101431.8 | H12: 1024109.2 | I12: 1028521.1 | J12: 1026809.5 | K12: 1085602.1 | L12: 1082036.7 | M12: 1143498.8 | N12: Tue Sep 08 2020 | O12: 15594.93 | P12: =O12/O$2*1000000 -> 971925.29 | Q12: 15954.5 | R12: =Q12/Q$2*1000000 -> 999339.18 | T12: 42570 | U12: 1178985.9 | V12: 1204925.7 | W12: 1340531.1 | X12: 1098448 | Y12: 1088749.6 | Z12: 1121533.2 | AA12: 1128901.8 | AB12: 1099561.4 | AC12: 1112705.2 | AD12: 1107476.2 | AE12: 1114926.7 | AF12: 1128632.3 | AG12: Tue May 24 2016 | AH12: 9099.86 | AI12: =AH12/AH$2*1000000 -> 983844.17 | AJ12: 8369.21 | AK12: =AJ12/AJ$2*1000000 -> 966735.16 | AN12: 1018997 | AO12: 1078835.8 | AP12: 1120561 | AQ12: 1011214.1 | AS12: 1204925.7 | AT12: 1186589.1 | AU12: 1147115 | AV12: 1190539.7 | AX12: 1018997 | AY12: 1087851.6 | AZ12: 1105261 | BA12: 999020.9 | BC12: 1204925.7 | BD12: 1191354.1 | BE12: 1178141.5 | BF12: 1184496.5 | BH12: 1120561 | BI12: 1105261 | BK12: 1147115 | BL12: 1178141.5 | BN12: 1018997 | BO12: 1120561 | BP12: 1204925.7 | BQ12: 1147115 | BS12: 1018997 | BT12: 1027422.2 | BU12: 1108337.9 | BV12: 1030654.6 | BX12: 1204925.7 | BY12: 1241784.2 | BZ12: 1162997.2 | CA12: 1076921.3 | CC12: 1071675.1 | CD12: 1071675.1 | CE12: 1062682.7 | CF12: 1062682.7
A13: 44145 | B13: 1071834.5 | C13: 1064797.9 | D13: 1122769.6 | E13: 1086621.6 | F13: 1100062.5 | G13: 1148242.7 | H13: 1047094.8 | I13: 1051605.7 | J13: 1068703.3 | K13: 1104053.7 | L13: 1097493.6 | M13: 1155722.8 | N13: Wed Sep 09 2020 | O13: 15565.68 | P13: =O13/O$2*1000000 -> 970102.33 | Q13: 15974.85 | R13: =Q13/Q$2*1000000 -> 1000613.8 | T13: 42577 | U13: 1223539.8 | V13: 1224843.1 | W13: 1352461.8 | X13: 1119941 | Y13: 1108423.3 | Z13: 1142214.3 | AA13: 1162825.3 | AB13: 1140283.7 | AC13: 1150381.4 | AD13: 1126453.9 | AE13: 1138345.7 | AF13: 1161825.4 | AG13: Wed May 25 2016 | AH13: 9179.19 | AI13: =AH13/AH$2*1000000 -> 992421.04 | AJ13: 8419.92 | AK13: =AJ13/AJ$2*1000000 -> 972592.72 | AN13: 1098132.3 | AO13: 1165277.5 | AP13: 1193929.7 | AQ13: 1064297.8 | AS13: 1224843.1 | AT13: 1212777.2 | AU13: 1151732.2 | AV13: 1221475.9 | AX13: 1098132.3 | AY13: 1183990.5 | AZ13: 1179650.6 | BA13: 1054711.3 | BC13: 1224843.1 | BD13: 1224515.4 | BE13: 1186365 | BF13: 1220487.5 | BH13: 1193929.7 | BI13: 1179650.6 | BK13: 1151732.2 | BL13: 1186365 | BN13: 1098132.3 | BO13: 1193929.7 | BP13: 1224843.1 | BQ13: 1151732.2 | BS13: 1098132.3 | BT13: 1113689.7 | BU13: 1173668.9 | BV13: 1129679.8 | BX13: 1224843.1 | BY13: 1258417.9 | BZ13: 1168213.2 | CA13: 1105653.6 | CC13: 1102255.4 | CD13: 1102255.4 | CE13: 1071210.7 | CF13: 1071210.7
A14: 44152 | B14: 1111856.8 | C14: 1111153.9 | D14: 1163604.7 | E14: 1142626.1 | F14: 1169646.9 | G14: 1248805.8 | H14: 1100044.5 | I14: 1103691.7 | J14: 1107262.1 | K14: 1175946 | L14: 1182724.9 | M14: 1255011 | N14: Thu Sep 10 2020 | O14: 15723.5 | P14: =O14/O$2*1000000 -> 979938.18 | Q14: 16088.7 | R14: =Q14/Q$2*1000000 -> 1007745 | T14: 42584 | U14: 1258276.1 | V14: 1259065.3 | W14: 1345672.5 | X14: 1149656.8 | Y14: 1139791.7 | Z14: 1219073.9 | AA14: 1192407.6 | AB14: 1177160.5 | AC14: 1216482.3 | AD14: 1153922.7 | AE14: 1170082.8 | AF14: 1189023.7 | AG14: Thu May 26 2016 | AH14: 9217.68 | AI14: =AH14/AH$2*1000000 -> 996582.44 | AJ14: 8504.06 | AK14: =AJ14/AJ$2*1000000 -> 982311.81 | AN14: 1121346.8 | AO14: 1191793.4 | AP14: 1231711.6 | AQ14: 1102080.4 | AS14: 1259065.3 | AT14: 1240119.2 | AU14: 1162109.3 | AV14: 1227845.9 | AX14: 1121346.8 | AY14: 1214957.8 | AZ14: 1224206 | BA14: 1092153.6 | BC14: 1259065.3 | BD14: 1252973.1 | BE14: 1209576.2 | BF14: 1210235.4 | BH14: 1231711.6 | BI14: 1224206 | BK14: 1162109.3 | BL14: 1209576.2 | BN14: 1121346.8 | BO14: 1231711.6 | BP14: 1259065.3 | BQ14: 1162109.3 | BS14: 1121346.8 | BT14: 1147367.6 | BU14: 1210809.7 | BV14: 1163073.2 | BX14: 1259065.3 | BY14: 1310604.5 | BZ14: 1203452.3 | CA14: 1094016.6 | CC14: 1104669.3 | CD14: 1108676 | CE14: 1114487.6 | CF14: 1114487.6
A15: 44159 | B15: 1137677.9 | C15: 1137677.1 | D15: 1159741.5 | E15: 1182541.9 | F15: 1202473.1 | G15: 1298695.5 | H15: 1136235.9 | I15: 1134700 | J15: 1143237.1 | K15: 1193550 | L15: 1207727.8 | M15: 1290615.6 | N15: Fri Sep 11 2020 | O15: 15825.14 | P15: =O15/O$2*1000000 -> 986272.7 | Q15: 16199.2 | R15: =Q15/Q$2*1000000 -> 1014666.4 | T15: 42591 | U15: 1272565.9 | V15: 1274451 | W15: 1360299.9 | X15: 1158984.3 | Y15: 1144162.8 | Z15: 1241029.4 | AA15: 1199637.6 | AB15: 1194500.1 | AC15: 1234109.1 | AD15: 1164691.3 | AE15: 1182830.9 | AF15: 1190260.3 | AG15: Fri May 27 2016 | AH15: 9271.65 | AI15: =AH15/AH$2*1000000 -> 1002417.5 | AJ15: 8607.81 | AK15: =AJ15/AJ$2*1000000 -> 994296.07 | AN15: 1175283.6 | AO15: 1231420.5 | AP15: 1272930.8 | AQ15: 1150351.5 | AS15: 1274451 | AT15: 1243163.7 | AU15: 1160273.1 | AV15: 1243912.3 | AX15: 1175283.6 | AY15: 1255355.2 | AZ15: 1262774.6 | BA15: 1143932.6 | BC15: 1274451 | BD15: 1256049.2 | BE15: 1204870.9 | BF15: 1233229.8 | BH15: 1272930.8 | BI15: 1262774.6 | BK15: 1160273.1 | BL15: 1204870.9 | BN15: 1175283.6 | BO15: 1272930.8 | BP15: 1274451 | BQ15: 1160273.1 | BS15: 1175283.6 | BT15: 1169729.8 | BU15: 1251220.4 | BV15: 1218499.4 | BX15: 1274451 | BY15: 1324031.6 | BZ15: 1191893.2 | CA15: 1098168.4 | CC15: 1140377.8 | CD15: 1155373.4 | CE15: 1109856.9 | CF15: 1101113.8
A16: 44166 | B16: 1157898.2 | C16: 1167228.3 | D16: 1203985.7 | E16: 1208900.7 | F16: 1231067.9 | G16: 1329994.1 | H16: 1148218.8 | I16: 1148299.3 | J16: 1172778.3 | K16: 1234858.7 | L16: 1265819.5 | M16: 1342562.9 | N16: Mon Sep 14 2020 | O16: 16280.08 | P16: =O16/O$2*1000000 -> 1014626 | Q16: 16677.8 | R16: =Q16/Q$2*1000000 -> 1044644.4 | T16: 42598 | U16: 1259314.2 | V16: 1259546.3 | W16: 1347037 | X16: 1166753.4 | Y16: 1160827.5 | Z16: 1282219.2 | AA16: 1200477.3 | AB16: 1202353.9 | AC16: 1247597.9 | AD16: 1158614.8 | AE16: 1174497.8 | AF16: 1199544.3 | AG16: Mon May 30 2016 | AH16: 9346.18 | AI16: =AH16/AH$2*1000000 -> 1010475.4 | AJ16: 8627.34 | AK16: =AJ16/AJ$2*1000000 -> 996552 | AN16: 1204695 | AO16: 1278540.8 | AP16: 1285431 | AQ16: 1179357.6 | AS16: 1259546.3 | AT16: 1238937 | AU16: 1133552.1 | AV16: 1207260.4 | AX16: 1204695 | AY16: 1303391.3 | AZ16: 1276684.1 | BA16: 1181201.9 | BC16: 1259546.3 | BD16: 1256802.8 | BE16: 1178267.4 | BF16: 1203909.8 | BH16: 1285431 | BI16: 1276684.1 | BK16: 1133552.1 | BL16: 1178267.4 | BN16: 1204695 | BO16: 1285431 | BP16: 1259546.3 | BQ16: 1133552.1 | BS16: 1204695 | BT16: 1201318.4 | BU16: 1269525.8 | BV16: 1211292 | BX16: 1259546.3 | BY16: 1310102.8 | BZ16: 1170594.1 | CA16: 1064103.2 | CC16: 1150224.9 | CD16: 1161878.2 | CE16: 1132387 | CF16: 1136222.8
... A233: 45685 | B233: 4703364.1 | C233: 4454548.9 | D233: 6284693.3 | E233: 5536180.3 | F233: 5629750.7 | G233: 8632080.5 | H233: 2413012.9 | I233: 2507781.1 | J233: 2784989.3 | K233: 7873783.6 | L233: 8527973.4 | M233: 6183877.2 | N233: Thu Jul 29 2021 | O233: 27238.11 | P233: =O233/O$2*1000000 -> 1697565 | Q233: 28418.85 | R233: =Q233/Q$2*1000000 -> 1780066.5 | T233: 44117 | U233: 2270259.6 | V233: 2510447.2 | W233: 1813420.3 | X233: 1906924.1 | Y233: 1976344.6 | Z233: 1600599.1 | AA233: 1937277.1 | AB233: 1909401.8 | AC233: 1433868.9 | AD233: 1901488.6 | AE233: 1945981.1 | AF233: 1977617 | AG233: Thu Apr 13 2017 | AH233: 12171.57 | AI233: =AH233/AH$2*1000000 -> 1315946.4 | AJ233: 11048.26 | AK233: =AJ233/AJ$2*1000000 -> 1276194.7 | AN233: 8341400.3 | AO233: 5132546.5 | AP233: 7264003 | AQ233: 6471128.7 | AS233: 2510471.8 | AT233: 2292269.5 | AU233: 2970900.4 | AV233: 2294281.6 | AX233: 8341400.3 | AY233: 6055437.5 | AZ233: 7497850.2 | BA233: 4769534.6 | BC233: 2510471.8 | BD233: 2519273.2 | BE233: 2470122.2 | BF233: 2155770.8 | BH233: 7264003 | BI233: 7497850.2 | BK233: 2970900.4 | BL233: 2470122.2 | BN233: 8341400.3 | BO233: 7264003 | BP233: 2510471.8 | BQ233: 2970900.4 | BS233: 8341400.3 | BT233: 8657884.3 | BU233: 7873431.1 | BV233: 5245552 | BX233: 2510471.8 | BY233: 3367171.1 | BZ233: 3080146.3 | CA233: 1395487.7 | CC233: 9210452.9 | CD233: 9327677.5 | CE233: 1732184.2 | CF233: 2007711.5
N234: Fri Jul 30 2021 | O234: 27539.54 | P234: =O234/O$2*1000000 -> 1716351.1 | Q234: 28513.05 | R234: =Q234/Q$2*1000000 -> 1785966.8 | AG234: Mon Apr 17 2017 | AH234: 12256.05 | AI234: =AH234/AH$2*1000000 -> 1325080.1 | AJ234: 11031.49 | AK234: =AJ234/AJ$2*1000000 -> 1274257.6 | CC234: 9707402.9 | CD234: 9859821.5 | CE234: 1809768.8 | CF234: 2121699.3
N235: Mon Aug 02 2021 | O235: 27846.88 | P235: =O235/O$2*1000000 -> 1735505.5 | Q235: 28778.8 | R235: =Q235/Q$2*1000000 -> 1802612.6 | AG235: Tue Apr 18 2017 | AH235: 12235.55 | AI235: =AH235/AH$2*1000000 -> 1322863.7 | AJ235: 10961.19 | AK235: =AJ235/AJ$2*1000000 -> 1266137.2 | CC235: 10345325 | CD235: 10409359 | CE235: 1839702.3 | CF235: 2195035.9
N236: Tue Aug 03 2021 | O236: 27959.99 | P236: =O236/O$2*1000000 -> 1742554.9 | Q236: 28862.5 | R236: =Q236/Q$2*1000000 -> 1807855.3 | AG236: Wed Apr 19 2017 | AH236: 12304.14 | AI236: =AH236/AH$2*1000000 -> 1330279.4 | AJ236: 10997.58 | AK236: =AJ236/AJ$2*1000000 -> 1270340.6 | CC236: 10657443 | CD236: 10722732 | CE236: 1825775.8 | CF236: 2208008.5
N237: Wed Aug 04 2021 | O237: 27706.9 | P237: =O237/O$2*1000000 -> 1726781.5 | Q237: 28762 | R237: =Q237/Q$2*1000000 -> 1801560.3 | AG237: Thu Apr 20 2017 | AH237: 12469.22 | AI237: =AH237/AH$2*1000000 -> 1348127.3 | AJ237: 11141.16 | AK237: =AJ237/AJ$2*1000000 -> 1286925.7 | CC237: 10332658 | CD237: 10315429 | CE237: 1838054.1 | CF237: 2218231.6
N238: Thu Aug 05 2021 | O238: 27904.07 | P238: =O238/O$2*1000000 -> 1739069.8 | Q238: 28791.1 | R238: =Q238/Q$2*1000000 -> 1803383 | AG238: Fri Apr 21 2017 | AH238: 12405.15 | AI238: =AH238/AH$2*1000000 -> 1341200.2 | AJ238: 11087.51 | AK238: =AJ238/AJ$2*1000000 -> 1280728.5 | CC238: 10749890 | CD238: 10577802 | CE238: 1886220.3 | CF238: 2246924.4
N239: Fri Aug 06 2021 | O239: 27931 | P239: =O239/O$2*1000000 -> 1740748.1 | Q239: 28932.85 | R239: =Q239/Q$2*1000000 -> 1812261.8 | AG239: Mon Apr 24 2017 | AH239: 12499 | AI239: =AH239/AH$2*1000000 -> 1351347 | AJ239: 11189.82 | AK239: =AJ239/AJ$2*1000000 -> 1292546.4 | CC239: 11208911 | CD239: 11034023 | CE239: 1869697.1 | CF239: 2225050.6
N240: Mon Aug 09 2021 | O240: 27761.66 | P240: =O240/O$2*1000000 -> 1730194.3 | Q240: 28596.7 | R240: =Q240/Q$2*1000000 -> 1791206.4 | AG240: Tue Apr 25 2017 | AH240: 12628.49 | AI240: =AH240/AH$2*1000000 -> 1365347 | AJ240: 11348.99 | AK240: =AJ240/AJ$2*1000000 -> 1310932.3 | CC240: 10710619 | CD240: 10622454 | CE240: 1884850.9 | CF240: 2263288.1
N241: Tue Aug 10 2021 | O241: 27399.66 | P241: =O241/O$2*1000000 -> 1707633.3 | Q241: 28003.4 | R241: =Q241/Q$2*1000000 -> 1754044 | AG241: Wed Apr 26 2017 | AH241: 12591.4 | AI241: =AH241/AH$2*1000000 -> 1361336.9 | AJ241: 11305.96 | AK241: =AJ241/AJ$2*1000000 -> 1305961.9 | CC241: 10952197 | CD241: 10869532 | CE241: 1837192.5 | CF241: 2191802.2
N242: Wed Aug 11 2021 | O242: 27370.93 | P242: =O242/O$2*1000000 -> 1705842.8 | Q242: 27892.6 | R242: =Q242/Q$2*1000000 -> 1747103.8 | AG242: Thu Apr 27 2017 | AH242: 12551.63 | AI242: =AH242/AH$2*1000000 -> 1357037.1 | AJ242: 11297.69 | AK242: =AJ242/AJ$2*1000000 -> 1305006.6 | CC242: 11842610 | CD242: 11923496 | CE242: 1888202.1 | CF242: 2251243.8
N243: Thu Aug 12 2021 | O243: 27767.46 | P243: =O243/O$2*1000000 -> 1730555.8 | Q243: 28388.1 | R243: =Q243/Q$2*1000000 -> 1778140.4 | AG243: Fri Apr 28 2017 | AH243: 12642.7 | AI243: =AH243/AH$2*1000000 -> 1366883.3 | AJ243: 11346.23 | AK243: =AJ243/AJ$2*1000000 -> 1310613.5 | CC243: 11612094 | CD243: 11713702 | CE243: 1897086.1 | CF243: 2269546.4
N244: Fri Aug 13 2021 | O244: 27772.89 | P244: =O244/O$2*1000000 -> 1730894.2 | Q244: 28437.05 | R244: =Q244/Q$2*1000000 -> 1781206.4 | AG244: Tue May 02 2017 | AH244: 12733.32 | AI244: =AH244/AH$2*1000000 -> 1376680.8 | AJ244: 11409.72 | AK244: =AJ244/AJ$2*1000000 -> 1317947.3 | CC244: 10627737 | CD244: 11002271 | CE244: 1910384.7 | CF244: 2275878.5
N245: Mon Aug 16 2021 | O245: 27799.78 | P245: =O245/O$2*1000000 -> 1732570.1 | Q245: 28463.6 | R245: =Q245/Q$2*1000000 -> 1782869.5 | AG245: Wed May 03 2017 | AH245: 12689.11 | AI245: =AH245/AH$2*1000000 -> 1371901 | AJ245: 11392.42 | AK245: =AJ245/AJ$2*1000000 -> 1315948.9 | CC245: 11689979 | CD245: 11919530 | CE245: 1896161.9 | CF245: 2280293.7
... N285: Wed Oct 13 2021 | O285: 33229.38 | P285: =O285/O$2*1000000 -> 2070959.9 | Q285: 33436.65 | R285: =Q285/Q$2*1000000 -> 2094365.5 | AG285: Thu Jun 29 2017 | AH285: 12884.47 | AI285: =AH285/AH$2*1000000 -> 1393022.6 | AJ285: 11407.7 | AK285: =AJ285/AJ$2*1000000 -> 1317713.9 | CC285: 9762922.3 | CD285: 10636696 | CE285: 2239466.2 | CF285: 2682353.9
N286: Thu Oct 14 2021 | O286: 33574.79 | P286: =O286/O$2*1000000 -> 2092486.9 | Q286: 33913.7 | R286: =Q286/Q$2*1000000 -> 2124246.4 | AG286: Fri Jun 30 2017 | AH286: 12981.58 | AI286: =AH286/AH$2*1000000 -> 1403521.8 | AJ286: 11462.19 | AK286: =AJ286/AJ$2*1000000 -> 1324008.1
N287: Mon Oct 18 2021 | O287: 33954.37 | P287: =O287/O$2*1000000 -> 2116143.6 | Q287: 34172.35 | R287: =Q287/Q$2*1000000 -> 2140447.4 | AG287: Mon Jul 03 2017 | AH287: 13103.78 | AI287: =AH287/AH$2*1000000 -> 1416733.6 | AJ287: 11625.13 | AK287: =AJ287/AJ$2*1000000 -> 1342829.5
N288: Tue Oct 19 2021 | O288: 33340.34 | P288: =O288/O$2*1000000 -> 2077875.3 | Q288: 33850.65 | R288: =Q288/Q$2*1000000 -> 2120297.1 | AG288: Tue Jul 04 2017 | AH288: 13087.43 | AI288: =AH288/AH$2*1000000 -> 1414965.9 | AJ288: 11587.9 | AK288: =AJ288/AJ$2*1000000 -> 1338529
N289: Wed Oct 20 2021 | O289: 32589.14 | P289: =O289/O$2*1000000 -> 2031058.1 | Q289: 32964.95 | R289: =Q289/Q$2*1000000 -> 2064819.7 | AG289: Wed Jul 05 2017 | AH289: 13206.39 | AI289: =AH289/AH$2*1000000 -> 1427827.4 | AJ289: 11684.83 | AK289: =AJ289/AJ$2*1000000 -> 1349725.5
N290: Thu Oct 21 2021 | O290: 32169.41 | P290: =O290/O$2*1000000 -> 2004899.2 | Q290: 32529.05 | R290: =Q290/Q$2*1000000 -> 2037516.3 | AG290: Thu Jul 06 2017 | AH290: 13253.91 | AI290: =AH290/AH$2*1000000 -> 1432965.1 | AJ290: 11744.9 | AK290: =AJ290/AJ$2*1000000 -> 1356664.2
N291: Fri Oct 22 2021 | O291: 31776.35 | P291: =O291/O$2*1000000 -> 1980402.5 | Q291: 31998.25 | R291: =Q291/Q$2*1000000 -> 2004268.7 | AG291: Fri Jul 07 2017 | AH291: 13247.58 | AI291: =AH291/AH$2*1000000 -> 1432280.7 | AJ291: 11722.51 | AK291: =AJ291/AJ$2*1000000 -> 1354077.9
N292: Mon Oct 25 2021 | O292: 31318.31 | P292: =O292/O$2*1000000 -> 1951856 | Q292: 31477 | R292: =Q292/Q$2*1000000 -> 1971619.3 | AG292: Mon Jul 10 2017 | AH292: 13284.98 | AI292: =AH292/AH$2*1000000 -> 1436324.3 | AJ292: 11791.14 | AK292: =AJ292/AJ$2*1000000 -> 1362005.5
N293: Tue Oct 26 2021 | O293: 31927.58 | P293: =O293/O$2*1000000 -> 1989827.6 | Q293: 32196.8 | R293: =Q293/Q$2*1000000 -> 2016705.2 | AG293: Tue Jul 11 2017 | AH293: 13219.25 | AI293: =AH293/AH$2*1000000 -> 1429217.8 | AJ293: 11727.41 | AK293: =AJ293/AJ$2*1000000 -> 1354643.9
N294: Wed Oct 27 2021 | O294: 32052.91 | P294: =O294/O$2*1000000 -> 1997638.6 | Q294: 32372.4 | R294: =Q294/Q$2*1000000 -> 2027704.3 | AG294: Wed Jul 12 2017 | AH294: 13366.88 | AI294: =AH294/AH$2*1000000 -> 1445179 | AJ294: 11858.44 | AK294: =AJ294/AJ$2*1000000 -> 1369779.3
N295: Thu Oct 28 2021 | O295: 31409.64 | P295: =O295/O$2*1000000 -> 1957548 | Q295: 31568.2 | R295: =Q295/Q$2*1000000 -> 1977331.7 | AG295: Thu Jul 13 2017 | AH295: 13433.4 | AI295: =AH295/AH$2*1000000 -> 1452370.9 | AJ295: 11914.77 | AK295: =AJ295/AJ$2*1000000 -> 1376286.1
N296: Fri Oct 29 2021 | O296: 31389.96 | P296: =O296/O$2*1000000 -> 1956321.4 | Q296: 31388.8 | R296: =Q296/Q$2*1000000 -> 1966094.7 | AG296: Fri Jul 14 2017 | AH296: 13462.86 | AI296: =AH296/AH$2*1000000 -> 1455556 | AJ296: 11939.63 | AK296: =AJ296/AJ$2*1000000 -> 1379157.7
N297: Mon Nov 01 2021 | O297: 31918.88 | P297: =O297/O$2*1000000 -> 1989285.4 | Q297: 31994.35 | R297: =Q297/Q$2*1000000 -> 2004024.4 | AG297: Mon Jul 17 2017 | AH297: 13478.78 | AI297: =AH297/AH$2*1000000 -> 1457277.3 | AJ297: 11982.37 | AK297: =AJ297/AJ$2*1000000 -> 1384094.6
... N1104: Thu Jan 30 2025 | O1104: 56177.7 | P1104: =O1104/O$2*1000000 -> 3501171.7 | Q1104: 48452.6 | R1104: =Q1104/Q$2*1000000 -> 3034916.9 | AG1104: Tue Oct 20 2020 | AH1104: 16085.64 | AI1104: =AH1104/AH$2*1000000 -> 1739121.6 | AJ1104: 16757.7 | AK1104: =AJ1104/AJ$2*1000000 -> 1935697.4
N1105: Fri Jan 31 2025 | O1105: 57144.4 | P1105: =O1105/O$2*1000000 -> 3561419.5 | Q1105: 49962.65 | R1105: =Q1105/Q$2*1000000 -> 3129501.6
N1106: Sat Feb 01 2025 | O1106: 56888 | P1106: =O1106/O$2*1000000 -> 3545439.8 | Q1106: 49416.05 | R1106: =Q1106/Q$2*1000000 -> 3095264.3
N1107: Mon Feb 03 2025 | O1107: 56662.8 | P1107: =O1107/O$2*1000000 -> 3531404.6 | Q1107: 47948.95 | R1107: =Q1107/Q$2*1000000 -> 3003369.9
N1108: Tue Feb 04 2025 | O1108: 57726.65 | P1108: =O1108/O$2*1000000 -> 3597707.1 | Q1108: 48747.25 | R1108: =Q1108/Q$2*1000000 -> 3053372.8

Sheet Crypto
B2: GIOTTUS:
B3: Date | C3: Coin | D3: Type | E3: Price | F3: Amount | G3: Total | H3: Fee | I3: Tds
B4: 45609.838 | C4: BTC/INR | D4: Sell | E4: 7425000.000 INR | F4: 0.00011507 BTC | G4: 854.395 INR | H4: 3.41700000 INR | I4: 8.50900000 INR | K4: Crypto sold:
B5: 45609.838 | C5: BTC/INR | D5: Sell | E5: 7425000.000 INR | F5: 0.00403140 BTC | G5: 29933.145 INR | H5: 119.73200000 INR | I5: 298.13400000 INR | K5: 0.00011507
B6: 45609.838 | C6: BTC/INR | D6: Sell | E6: 7425000.000 INR | F6: 0.00401714 BTC | G6: 29827.265 INR | H6: 119.30900000 INR | I6: 297.07900000 INR | K6: 0.0040314 | O6: Alternative way:
B7: 45609.838 | C7: BTC/INR | D7: Sell | E7: 7425000.000 INR | F7: 0.00400294 BTC | G7: 29721.829 INR | H7: 118.88700000 INR | I7: 296.02900000 INR | K7: 0.00401714 | O7: Invested 4.19L. Gave 60K extra due to mistake. Total 4.79L. 0.2332 BTC
B8: 45609.838 | C8: BTC/INR | D8: Sell | E8: 7425000.000 INR | F8: 0.00398879 BTC | G8: 29616.766 INR | H8: 118.46700000 INR | I8: 294.98200000 INR | K8: 0.00400294 | P8: 419000 | Q8: 0.2332
B9: 45609.838 | C9: BTC/INR | D9: Sell | E9: 7425000.000 INR | F9: 0.00397469 BTC | G9: 29512.073 INR | H9: 118.04800000 INR | I9: 293.94000000 INR | K9: 0.00398879 | P9: ? | Q9: 1
B10: 45609.837 | C10: BTC/INR | D10: Sell | E10: 7425000.000 INR | F10: 0.00396065 BTC | G10: 29407.826 INR | H10: 117.63100000 INR | I10: 292.90100000 INR | K10: 0.00397469 | O10: 1BTC Rate of Buying | P10: =P8/Q8 -> 1796741
B11: 45609.837 | C11: BTC/INR | D11: Sell | E11: 7425000.000 INR | F11: 0.00394663 BTC | G11: 29303.728 INR | H11: 117.21400000 INR | I11: 291.86500000 INR | K11: 0.00396065
B12: 45609.837 | C12: BTC/INR | D12: Sell | E12: 7425000.000 INR | F12: 0.00393268 BTC | G12: 29200.149 INR | H12: 116.80000000 INR | I12: 290.83300000 INR | K12: 0.00394663 | O12: Buy Cost | P12: =K18*P10 -> 112521.48
B13: 45609.837 | C13: BTC/INR | D13: Sell | E13: 7425000.000 INR | F13: 0.00363699 BTC | G13: 27004.651 INR | H13: 108.01800000 INR | I13: 268.96600000 INR | K13: 0.00393268 | O13: P&L | P13: =C18-P12 -> 346314.26
B14: 45609.694 | C14: BTC/INR | D14: Sell | E14: 7425000.000 INR | F14: 0.01346802 BTC | G14: 100000.049 INR | H14: 400.00000000 INR | I14: 996.00000000 INR | K14: 0.00363699
B15: 45609.45 | C15: BTC/INR | D15: Sell | E15: 7450000.000 INR | F15: 0.01342281 BTC | G15: 99999.935 INR | H15: 399.99900000 INR | I15: 995.99900000 INR | K15: 0.01346802
B16: 45609.45 | C16: BTC/INR | D16: Sell | E16: 7450000.000 INR | F16: 0.00012751 BTC | G16: 949.949 INR | H16: 3.79900000 INR | I16: 9.46100000 INR | K16: 0.01342281
K17: 0.00012751
B18: Total INR received | C18: =198144.68+260691.06 -> 458835.74 | D18: these are after giottus charges | J18: Total | K18: =SUM(K5:K17) -> 0.06262532
B19: Amount Paid (mentioned by Giottus is TDS Form 16A)
B20: 463470 | F20: INR Spent | G20: 463551
F21: BTC Purchased | G21: 0.211263
B22: 198144.68 withdrawn on 13 Nov 2024 | F22: Purchase Rate | G22: =G20/G21 -> 2194189.2
B23: 200000 withdrawn on 15 Nov 2024 | F23: BTC Sold | G23: =K18 -> 0.06262532
B24: 60691.06 withdrawn on 18 Nov 2024 | F24: Cost of Acquisition | G24: =G23*G22 -> 137411.8
F25: P&L | G25: =B20-G24 -> 326058.2
B27: DISCARD BELOW: | F27: Date of Acquisition | G27: 44691 | H27: Bought between 10-05-2022 and 31-12-2022
B28: 45492 | F28: Date of Transfer | G28: 45609
B29: Wazirx
B30: Tax on crypto: | C30: https://support.wazirx.com/hc/en-us/articles/4701662097050-TDS-on-Crypto-Trades
B32: BTC | C32: Average Price | D32: Total | E32: Fee | F32: TDS | G32: Net Total
B33: 0.08332 | C33: 4890035 | D33: 407437 | E33: 1923.106 | F33: 4055.1461 | G33: =D33-E33-F33 -> 401458.75
B34: 0.01702 | C34: 4700000 | D34: 79994 | E34: 377.57168 | F34: 796.16428 | G34: =D34-E34-F34 -> 78820.264
F35: =SUM(F33:F34) -> 4851.3104 | G35: =SUM(G33:G34) -> 480279.01

Sheet tax-regime FY2025-26
C1: Disclaimer: This calculator uses information from Budget 2025 presented on 1st Feb 2025 for income earned from 1st Apr 2025 onwards. Please refer to the Income Tax website for the latest rules in effect | I1: Article: https://arthgyaan.com/blog/budget-2025-best-tax-regime-to-choose-from-1st-april-2025.html
I2: Updated on 1-Feb-2025 after Union Budget 2025
C3: Only enter data in yellow cells | I3: This calculator is applicable for FY2024-25 for age 0-60 and is not guaranteed to be correct. Check income tax website for the latest version and correct figures. | N3: Refer to this YouTube playlist to see what this tool can do apart from tax calculation:
E4: Old Tax Regime | G4: New Tax Regime | N4: https://www.youtube.com/playlist?list=PLotlPYqRy3-_vD_w_pAvoClpwSlHin9dP
C5: Gross Income (A) | E5: =4300000 -> 4300000 | G5: =E5 -> 4300000
C6: Other income (interest, freelancing etc) | E6: 0 | G6: =E6 -> 0
C7: Less: Deductions
C8: 80C (PPF, ELSS, Sukanya, Life insurance...) | E8: 150000
C9: 80D Medical insurance premium | E9: 30000
C10: Standard Deduction | E10: 50000 | G10: 75000 | I10: This calculator is standalone from the rest of the workbook
C11: 24b home loan interest | E11: 0
C12: NPS Self contribution [80CCD(1b)] | E12: 50000
C13: Employer NPS Contribution [80CCD(2)] | E13: 0 | G13: =E13 -> 0
C14: HRA (see table below for calculation) | E14: =MAX(0,P30) -> 120000
C15: 80TTA Interest from savings account | E15: 2000
C16: Leave Travel Allowance (LTA) | E16: 0
C17: Other deductions | E17: 0 | I17: Deduction on NPS Contributions: Old regime: ₹50,000 under 80CCD1B and upto 10% of basic+DA New regime: Upto 14% of basic+DA. 80CCD1B is not allowed
C18: Total deductions (B) | E18: =SUM(E8:E17)-E11+MIN(200000,E11) -> 402000 | G18: =SUM(G8:G17) -> 75000
C20: Taxable income C= A-B | E20: =MAX(E5+E6-E18,0) -> 3898000 | G20: =MAX(G5+G6-G18-E13,0) -> 4225000
B22: 0 | C22: Slabs | D22: Rate | E22: =E4 -> Old Tax Regime | G22: =G4 -> New Tax Regime
B23: 250000 | C23: 0-2.5L @ 0% | D23: 0 | E23: =MAX(0,IF(E$20>B23,B23-B22,E$20-B22)*D23) -> 0
B24: 500000 | C24: 2.5-5L @ 5% | D24: 0.05 | E24: =MAX(0,IF(E$20>B24,B24-B23,E$20-B23)*D24) -> 12500 | I24: HRA calculation
B25: 1000000 | C25: 5-10L @ 20% | D25: 0.2 | E25: =MAX(0,IF(E$20>B25,B25-B24,E$20-B24)*D25) -> 100000 | I25: (please enter annual numbers only in the yellow cells)
B26: 1e+15 | C26: >10L @ 30% | D26: 0.3 | E26: =MAX(0,IF(E$20>B26,B26-B25,E$20-B25)*D26) -> 869400 | I26: Basic salary plus DA | P26: 300000
B27: 0 | I27: HRA received | P27: 200000
B28: 400000 | C28: 0-4L @ 0% | D28: 0 | G28: =MAX(0,IF(G$20>B28,B28-B27,G$20-B27)*D28) -> 0 | I28: Rent paid to landlord | P28: 240000
B29: 800000 | C29: 4-8L @ 5% | D29: =D28+5% -> 0.05 | G29: =MAX(0,IF(G$20>B29,B29-B28,G$20-B28)*D29) -> 20000 | I29: Is the rented house in Delhi, Mumbai, Kolkata or Chennai? | P29: Yes
B30: 1200000 | C30: 8-12L @ 10% | D30: =D29+5% -> 0.1 | G30: =MAX(0,IF(G$20>B30,B30-B29,G$20-B29)*D30) -> 40000 | I30: HRA applicable | P30: =MIN(P27,P28-0.1*P26,IF(P29="Yes",0.5,0.4)*P28) -> 120000
B31: 1600000 | C31: 12-16L @ 15% | D31: =D30+5% -> 0.15 | G31: =MAX(0,IF(G$20>B31,B31-B30,G$20-B30)*D31) -> 60000
B32: 2000000 | C32: 16-20L @ 20% | D32: =D31+5% -> 0.2 | G32: =MAX(0,IF(G$20>B32,B32-B31,G$20-B31)*D32) -> 80000
B33: 2400000 | C33: 20-24L @ 25% | D33: 0.25 | G33: =MAX(0,IF(G$20>B33,B33-B32,G$20-B32)*D33) -> 100000
B34: 1e+15 | C34: >24L @ 30% | D34: =D33+5% -> 0.3 | G34: =MAX(0,IF(G$20>B34,B34-B33,G$20-B33)*D34) -> 547500
C36: Tax | E36: =IF(AND(E20>500000,SUM(E23:E35)>(E20-500000)),E20-500000,SUM(E23:E35)) -> 981900 | G36: =IF(AND(G20>700000,SUM(G23:G35)>(G20-700000)),G20-700000,SUM(G23:G35)) -> 847500
C37: Plus: Cess | D37: 0.04 | E37: =E36*$D$37*IF(E20/10^5<50,1,1.1) -> 39276 | G37: =G36*$D$37*IF(G20/10^5<50,1,1.1) -> 33900
C38: Total tax | E38: =SUM(E36:E37)+IF(E20>50*10^5,0.1,0)*E36 -> 1021176 | G38: =SUM(G36:G37)+IF(G20>50*10^5,0.1,0)*G36 -> 881400
C40: Recommended | E40: =IF(E38<G38,E4,G4) &" is better by ₹" &TEXT(ABS(G38-E38),"#,##0") -> New Tax Regime is better by ₹1,39,776

Sheet tax-regime FY2024-25
C1: Disclaimer: This calculator uses tax laws applicable as on Jul 2024 for income earned from 1st Apr 2024 onwards. Please refer to the Income Tax website for the latest rules in effect | I1: Article: https://arthgyaan.com/blog/budget-2024-best-tax-regime-to-choose-from-1st-april-2024.html
I2: Updated on 23-Jul-2024 after Union Budget 2024
C3: Only enter data in yellow cells | I3: This calculator is applicable for FY2024-25 for age 0-60 and is not guaranteed to be correct. Check income tax website for the latest version and correct figures. | N3: Refer to this YouTube playlist to see what this tool can do apart from tax calculation:
E4: Old Tax Regime | G4: New Tax Regime | N4: https://www.youtube.com/playlist?list=PLotlPYqRy3-_vD_w_pAvoClpwSlHin9dP
C5: Gross Income (A) | E5: 3000000 | G5: =E5 -> 3000000
C6: Other income (interest, freelancing etc) | E6: 0 | G6: =E6 -> 0
C7: Less: Deductions
C8: 80C (PPF, ELSS, Sukanya, Life insurance...) | E8: 150000
C9: 80D Medical insurance premium | E9: 30000
C10: Standard Deduction | E10: 50000 | G10: 75000 | I10: This calculator is standalone from the rest of the workbook
C11: 24b home loan interest | E11: 0
C12: NPS Self contribution [80CCD(1b)] | E12: 50000
C13: Employer NPS Contribution [80CCD(2)] | E13: 0 | G13: =E13 -> 0
C14: HRA (see table below for calculation) | E14: =MAX(0,P30) -> 120000
C15: 80TTA Interest from savings account | E15: 2000
C16: Leave Travel Allowance (LTA) | E16: 0
C17: Other deductions | E17: 0 | I17: Deduction on NPS Contributions: Old regime: ₹50,000 under 80CCD1B and upto 10% of basic+DA New regime: Upto 14% of basic+DA. 80CCD1B is not allowed
C18: Total deductions (B) | E18: =SUM(E8:E17)-E11+MIN(200000,E11) -> 402000 | G18: =SUM(G8:G17) -> 75000
C20: Taxable income C= A-B | E20: =MAX(E5+E6-E18,0) -> 2598000 | G20: =MAX(G5+G6-G18-E13,0) -> 2925000
B22: 0 | C22: Slabs | D22: Rate | E22: =E4 -> Old Tax Regime | G22: =G4 -> New Tax Regime
B23: 250000 | C23: 0-2.5L @ 0% | D23: 0 | E23: =MAX(0,IF(E$20>B23,B23-B22,E$20-B22)*D23) -> 0
B24: 500000 | C24: 2.5-5L @ 5% | D24: 0.05 | E24: =MAX(0,IF(E$20>B24,B24-B23,E$20-B23)*D24) -> 12500 | I24: HRA calculation
B25: 1000000 | C25: 5-10L @ 20% | D25: 0.2 | E25: =MAX(0,IF(E$20>B25,B25-B24,E$20-B24)*D25) -> 100000 | I25: (please enter annual numbers only in the yellow cells)
B26: 1e+15 | C26: >10L @ 30% | D26: 0.3 | E26: =MAX(0,IF(E$20>B26,B26-B25,E$20-B25)*D26) -> 479400 | I26: Basic salary plus DA | P26: 300000
B27: 0 | I27: HRA received | P27: 200000
B28: 300000 | C28: 0-3L @ 0% | D28: 0 | G28: =MAX(0,IF(G$20>B28,B28-B27,G$20-B27)*D28) -> 0 | I28: Rent paid to landlord | P28: 240000
B29: 700000 | C29: 3-7L @ 5% | D29: =D28+5% -> 0.05 | G29: =MAX(0,IF(G$20>B29,B29-B28,G$20-B28)*D29) -> 20000 | I29: Is the rented house in Delhi, Mumbai, Kolkata or Chennai? | P29: Yes
B30: 1000000 | C30: 7-10L @ 10% | D30: =D29+5% -> 0.1 | G30: =MAX(0,IF(G$20>B30,B30-B29,G$20-B29)*D30) -> 30000 | I30: HRA applicable | P30: =MIN(P27,P28-0.1*P26,IF(P29="Yes",0.5,0.4)*P28) -> 120000
B31: 1200000 | C31: 10-12L @ 15% | D31: =D30+5% -> 0.15 | G31: =MAX(0,IF(G$20>B31,B31-B30,G$20-B30)*D31) -> 30000
B32: 1500000 | C32: 12-15L @ 20% | D32: =D31+5% -> 0.2 | G32: =MAX(0,IF(G$20>B32,B32-B31,G$20-B31)*D32) -> 60000
B33: 1e+15 | C33: >15L @ 30% | D33: =D32+10% -> 0.3 | G33: =MAX(0,IF(G$20>B33,B33-B32,G$20-B32)*D33) -> 427500
C35: Tax | E35: =IF(AND(E20>500000,SUM(E23:E34)>(E20-500000)),E20-500000,SUM(E23:E34)) -> 591900 | G35: =IF(AND(G20>700000,SUM(G23:G34)>(G20-700000)),G20-700000,SUM(G23:G34)) -> 567500
C36: Plus: Cess | D36: 0.04 | E36: =E35*$D$36*IF(E20/10^5<50,1,1.1) -> 23676 | G36: =G35*$D$36*IF(G20/10^5<50,1,1.1) -> 22700
C37: Total tax | E37: =SUM(E35:E36)+IF(E20>50*10^5,0.1,0)*E35 -> 615576 | G37: =SUM(G35:G36)+IF(G20>50*10^5,0.1,0)*G35 -> 590200
C39: Recommended | E39: =IF(E37<G37,E4,G4) &" is better by ₹" &TEXT(ABS(G37-E37),"#,##0") -> New Tax Regime is better by ₹25,376

Sheet covered call-old
A1: Slab | B1: Date | C1: Instru | D1: Qty | E1: Entry | F1: LTP | G1: PnL | H1: Nifty at Entry | I1: Amount invested | K1: Expiry | L1: CC P&L | M1: Put Bfly P&L | N1: Nifty P&L | O1: Nifty start | P1: Nifty end | Q1: HDFC start | R1: HDFC end | S1: HDFC P&L | T1: ICICI start | U1: ICICI end | V1: ICICI P&L | W1: Niftybees start | X1: Niftybees end | Y1: Niftybees P&L | Z1: Total | AA1: Cum Total PnL | AB1: Total Invested | AC1: Cum Return | AI1: Slab | AJ1: Date | AK1: CC Strike | AL1: Qty | AM1: Entry | AN1: Exit | AO1: PnL | AP1: Nifty at Entry | AQ1: Nifty at Exit
A2: 1 | B2: 45254.438 | C2: NIFTYBEES | D2: 4532 | E2: 218.45 | F2: 266.95 | G2: =(F2-E2)*D2 -> 219802 | H2: 19800 | I2: =D2*E2 -> 990015.4 | K2: 45288 | L2: =-83335-33260 -> -116595 | M2: 0 | N2: =S2+V2+Y2 -> 144033.7 | Q2: 192.056 | R2: 207.707 | S2: 45643.985 | T2: 207.672 | U2: 224.57 | V2: 0 | W2: 222.13 | X2: 240.16 | Y2: 98389.72 | Z2: =L2+M2+N2 -> 27438.705 | AA2: =SUM(Z2:Z46) -> 1685802.7 | AB2: =SUM(I2:I15) -> 8030307.6 | AC2: =AA2/AB2 -> 0.20993003 | AI2: 1 | AJ2: 45254.438 | AK2: Dec 19800CE | AL2: 50 | AM2: 312 | AN2: 1978.7 | AO2: =(AM2-AN2)*AL2 -> -83335 | AP2: 19800 | AQ2: 21778.7
A3: 2 | B3: 45265.646 | C3: HDFC Index Nifty 50 Plan | D3: 5202.483 | E3: 198.9335 | F3: 230.5786 | G3: =(F3-E3)*D3 -> 164633.09 | H3: 20850 | I3: =D3*E3 -> 1034948.2 | K3: 45292 | L3: =SUM(AO4:AO7)-2955 -> 71662.5 | M3: 0 | N3: =S3+V3+Y3 -> -62617.329 | Q3: 207.707 | R3: 203.705 | S3: -44444.009 | T3: 224.57 | U3: 220.239 | V3: 0 | W3: 240.16 | X3: 236.15 | Y3: -18173.32 | Z3: =L3+M3+N3 -> 9045.1709 | AI3: 2 | AJ3: 45265.642 | AK3: Dec 20800CE | AL3: 50 | AM3: 313.5 | AN3: 978.7 | AO3: =(AM3-AN3)*AL3 -> -33260 | AP3: 20850 | AQ3: 21778.7
A4: 3 | B4: 45289.646 | C4: HDFC Index Nifty 50 Plan | D4: 5234.832 | E4: 207.2551 | F4: 230.5786 | G4: =(F4-E4)*D4 -> 122094.6 | H4: 21750 | I4: =D4*E4 -> 1084945.6 | K4: 45323 | L4: 600 | M4: -4532.55 | N4: =S4+V4+Y4 -> 182364.65 | Q4: 203.705 | R4: 209.9396 | S4: 97665.053 | T4: 220.239 | U4: 226.9912 | V4: 52522.402 | W4: 236.15 | X4: 243.25 | Y4: 32177.2 | Z4: =L4+M4+N4 -> 178432.1 | AB4: Nifty P&L (only nifty, not CC and P-bfly) | AI4: 3 | AJ4: 45289.635 | AK4: Jan 21700CE | AL4: 50 | AM4: 425.25 | AN4: 0 | AO4: =(AM4-AN4)*AL4 -> 21262.5 | AP4: 21700 | AQ4: 21350
A5: 4 | B5: 45309.646 | C5: HDFC Index Nifty 50 Plan | D5: 5227.692 | E5: 204.669 | F5: 230.5786 | G5: =(F5-E5)*D5 -> 135447.41 | H5: 21450 | I5: =D5*E5 -> 1069946.5 | K5: 45352 | L5: 25648 | M5: -692.5 | N5: =S5+V5+Y5 -> 5938.5271 | O5: 21982 | P5: 21998 | Q5: 209.9396 | R5: 210.0655 | S5: 1972.2244 | T5: 226.9912 | U5: 227.1209 | V5: 1881.5827 | W5: 243.25 | X5: 243.71 | Y5: 2084.72 | Z5: =L5+M5+N5 -> 30894.027 | AB5: fund | AC5: qty | AD5: Entry | AE5: Exit | AF5: pnl | AI5: 1 | AJ5: 45288.635 | AK5: Jan 21800CE | AL5: 50 | AM5: 431.55 | AN5: 0 | AO5: =(AM5-AN5)*AL5 -> 21577.5 | AP5: 21800 | AQ5: 21350
A6: 5 | B6: 45315.646 | C6: ICICI Prudential Nifty 50 Index Fund | D6: 4836.062 | E6: 221.2847 | F6: 249.2639 | G6: =(F6-E6)*D6 -> 135309.15 | H6: 21400 | I6: =D6*E6 -> 1070146.5 | K6: 45365 | L6: =AO22+AO23 -> -1090 | M6: 0 | N6: =S6+V6+Y6 -> 52121.037 | O6: 21998 | P6: 22150 | Q6: 210.0655 | R6: 211.4857 | S6: 22247.443 | T6: 227.1209 | U6: 228.6553 | V6: 22259.834 | W6: 243.71 | X6: 245.39 | Y6: 7613.76 | Z6: =L6+M6+N6 -> 51031.037 | AB6: hdfc index | AC6: 18266.15 | AD6: 241.774 | AE6: 251.9594 | AF6: =(AE6-AD6)*AC6 -> 186048.04 | AI6: 2 | AJ6: 45288.635 | AK6: Jan 21800CE | AL6: 50 | AM6: 431.55 | AN6: 0 | AO6: =(AM6-AN6)*AL6 -> 21577.5 | AP6: 21800 | AQ6: 21350
A7: 6 | B7: 45323.646 | C7: ICICI Prudential Nifty 50 Index Fund | D7: 4845.491 | E7: 224 | F7: 249.2639 | G7: =(F7-E7)*D7 -> 122416 | H7: 21700 | I7: =D7*E7 -> 1085390 | K7: 45372 | L7: =AO24 -> 69426 | M7: -5767.5 | N7: =S7+V7+Y7 -> -46824.885 | O7: 22150 | P7: 22011.95 | Q7: 211.4857 | R7: 210.1933 | S7: -20245.455 | T7: 228.6553 | U7: 227.2605 | V7: -20234.63 | W7: 245.39 | X7: 243.99 | Y7: -6344.8 | Z7: =L7+M7+N7 -> 16833.615 | AB7: icici index | AC7: 14507.191 | AD7: 261.3712 | AE7: 272.3878 | AF7: =(AE7-AD7)*AC7 -> 159819.92 | AI7: 4 | AJ7: 45309.635 | AK7: Jan 21450CE | AL7: 50 | AM7: 204 | AN7: 0 | AO7: =(AM7-AN7)*AL7 -> 10200 | AP7: 21450 | AQ7: 21350
A8: 7 | B8: 45331.646 | C8: ICICI Prudential Nifty 50 Index Fund | D8: 4825.638 | E8: 224.8295 | F8: 249.2639 | G8: =(F8-E8)*D8 -> 117911.57 | H8: 21800 | I8: =D8*E8 -> 1084945.8 | K8: 45379 | L8: =AO25 -> -23625 | M8: 0 | N8: =S8+V8+Y8 -> 107082.02 | O8: 22011.95 | P8: 22327 | Q8: 210.1933 | R8: 213.2028 | S8: 47143.839 | T8: 227.2605 | U8: 230.4643 | V8: 46478.139 | W8: 243.99 | X8: 246.96 | Y8: 13460.04 | Z8: =L8+M8+N8 -> 83457.017 | AB8: niftybees | AC8: 4532 | AD8: 280.1 | AE8: 291.55 | AF8: =(AE8-AD8)*AC8 -> 51891.4 | AI8: 1 | AJ8: 45316.635 | AK8: Feb 21800CE | AL8: 50 | AM8: 220 | AN8: 182.8 | AO8: =(AM8-AN8)*AL8 -> 1860 | AP8: 21350 | AQ8: 21982
A9: 8 | B9: 45589.646 | C9: HDFC Index Nifty 50 Plan | D9: 2601.143 | E9: 234.5006 | F9: 230.5786 | G9: =(F9-E9)*D9 -> -10201.683 | H9: 24400 | I9: =D9*E9 -> 609969.59 | K9: 45407 | L9: 57010 | N9: =S9+V9+Y9 -> 81147.923 | O9: 22327 | P9: 22570.35 | Q9: 213.2028 | R9: 215.4644 | S9: 35427.98 | T9: 230.4643 | U9: 232.8942 | V9: 35251.023 | W9: 246.96 | X9: 249.27 | Y9: 10468.92 | Z9: =L9+M9+N9 -> 138157.92 | AI9: 2 | AJ9: 45316.635 | AK9: Feb 21800CE | AL9: 50 | AM9: 220 | AN9: 182.8 | AO9: =(AM9-AN9)*AL9 -> 1860 | AP9: 21350 | AQ9: 21982
K10: 45442 | L10: 9403 | N10: =S10+V10+Y10 -> -3709.0526 | O10: 22570.35 | P10: 22488.65 | Q10: 215.4644 | R10: 215.183 | S10: -4408.133 | T10: 232.8942 | U10: 232.605 | V10: -4195.4796 | W10: 249.27 | X10: 250.35 | Y10: 4894.56 | Z10: =L10+M10+N10 -> 5693.9474 | AI10: 3 | AJ10: 45316.635 | AK10: Feb 21700CE | AL10: 50 | AM10: 261 | AN10: 282.8 | AO10: =(AM10-AN10)*AL10 -> -1090 | AP10: 21350 | AQ10: 21982
K11: 45470 | L11: -172042.5 | M11: =45698-30919 -> 14779 | N11: =S11+V11+Y11 -> 558077.23 | O11: 22488.65 | P11: 24044 | Q11: 215.183 | R11: 230.5786 | S11: 241172.18 | T11: 232.605 | U11: 249.2639 | V11: 241673.84 | W11: 250.35 | X11: 266.95 | Y11: 75231.2 | Z11: =L11+M11+N11 -> 400813.73 | AB11: HDFC Profit | AC11: =AC6*(AE6-208.025) -> 802512.34 | AI11: 4 | AJ11: 45316.635 | AK11: Feb 21450CE | AL11: 50 | AM11: 380.3 | AN11: 532.8 | AO11: =(AM11-AN11)*AL11 -> -7625 | AP11: 21350 | AQ11: 21982
K12: 45498 | L12: 27431 | N12: =S12+V12+Y12 -> 134641.57 | O12: 24044 | P12: 24406.1 | Q12: 230.5786 | R12: 234.161 | S12: 56118.321 | T12: 249.2639 | U12: 253.124 | V12: 55999.208 | W12: 266.95 | X12: 271.92 | Y12: 22524.04 | Z12: =L12+M12+N12 -> 162072.57 | AB12: ICICI Profit | AC12: =AC7*(AE7-223.34) -> 711545.8 | AI12: 5 | AJ12: 45315.635 | AK12: Feb 21400CE | AL12: 50 | AM12: 500 | AN12: 582.8 | AO12: =(AM12-AN12)*AL12 -> -4140 | AP12: 21400 | AQ12: 21982
K13: 45533 | L13: -32483 | N13: =S13+V13+Y13 -> 275973.16 | O13: 24406.1 | P13: 25151.95 | Q13: 234.161 | R13: 241.774 | S13: 119257.7 | T13: 253.124 | U13: 261.3712 | V13: 119643.71 | W13: 271.92 | X13: 280.1 | Y13: 37071.76 | Z13: =L13+M13+N13 -> 243490.16 | AB13: NFBEES Profit | AC13: =AC8*(AE8-E2) -> 331289.2 | AI13: 6 | AJ13: 45323.635 | AK13: Feb 21700CE | AL13: 50 | AM13: 354 | AN13: 282.8 | AO13: =(AM13-AN13)*AL13 -> 3560 | AP13: 21700 | AQ13: 21982
K14: 45561 | L14: -88411 | N14: =S14+V14+Y14 -> 371265.68 | O14: 25151.95 | P14: 26216.05 | Q14: 241.774 | R14: 251.9594 | S14: 159554.36 | T14: 261.3712 | U14: 272.3878 | V14: 159819.92 | W14: 280.1 | X14: 291.55 | Y14: 51891.4 | Z14: =L14+M14+N14 -> 282854.68 | AB14: Total Index Profit | AC14: =SUM(AC11:AC13) -> 1845347.3 | AI14: 7 | AJ14: 45331.642 | AK14: Feb 21800CE | AL14: 50 | AM14: 306.3 | AN14: 182.8 | AO14: =(AM14-AN14)*AL14 -> 6175 | AP14: 21800 | AQ14: 21982
K15: 45596 | L15: 55588 | N15: =S15+V15+Y15 -> 0 | Z15: =L15+M15+N15 -> 55588 | AI15: 1 | AJ15: 45351.642 | AK15: Mar 22000CE | AL15: 50 | AM15: 454.92 | AN15: 381.64 | AO15: =(AM15-AN15)*AL15 -> 3664 | AP15: 21982 | AQ15: 21998
H16: Invested | I16: =SUM(I2:I15) -> 8030307.6 | N16: =S16+V16+Y16 -> 0 | Z16: =L16+M16+N16 -> 0 | AI16: 2 | AJ16: 45351.642 | AK16: Mar 22000CE | AL16: 50 | AM16: 454.92 | AN16: 381.64 | AO16: =(AM16-AN16)*AL16 -> 3664 | AP16: 21982 | AQ16: 21998
N17: =S17+V17+Y17 -> 0 | Z17: =L17+M17+N17 -> 0 | AI17: 3 | AJ17: 45351.642 | AK17: Mar 22000CE | AL17: 50 | AM17: 454.92 | AN17: 381.64 | AO17: =(AM17-AN17)*AL17 -> 3664 | AP17: 21982 | AQ17: 21998
G18: Avg nifty | H18: =SUM(I21:I28)/I16 -> 21508.276 | N18: =S18+V18+Y18 -> 0 | Z18: =L18+M18+N18 -> 0 | AI18: 4 | AJ18: 45351.642 | AK18: Mar 22000CE | AL18: 50 | AM18: 454.92 | AN18: 381.64 | AO18: =(AM18-AN18)*AL18 -> 3664 | AP18: 21982 | AQ18: 21998
